Workbook

Sheet PRODUCTOS
B2: ROTACIÓN PRODUCTOS | E2: ROTACIÓN BODEGA TU PIEL ENERO
E3: Fecha Reporte: | H3: =C7 -> 46072
B4: REPORTE PRODUCTOS FEBRERO | E4: CONTROL BOTOX | H4: CONTROL RADIESSE
B5: DÍAS HÁB MES | C5: ='BALANCE PPTO'!E15 -> 24 | E5: Meta Febrero | F5: 5000 | H5: Meta Febrero | I5: 20
B6: DÍAS EJECT | C6: ='TABLERO Y AGENDA'!P3 -> 16 | E6: Vendidos | F6: =F22 -> 2328 | H6: Vendidos | I6: =I22 -> 3
B7: FECHA | C7: ='TABLERO Y AGENDA'!N3 -> 46072 | E7: Faltan | F7: =F5-F6 -> 2672 | H7: Faltan | I7: =I5-I6 -> 17
B8: META FEBRERO | C8: 60000000 | E8: CONTROL HARMONYCA | H8: CONTROL BELOTERO
B9: META DÍA | C9: =+C8/C5 -> 2500000 | E9: Meta Febrero | F9: 20 | H9: AH Balance | I9: 10
B10: VENTA ESPERADA | C10: =+(C8/C5)*C6 -> 40000000 | E10: Vendidos | F10: =F26 -> 3 | H10: AH Intense | I10: 20
B11: FACTURADO FEB | C11: 47404171 | E11: Faltan | F11: =F9-F10 -> 17 | H11: AH Volume | I11: 4
B12: VENTA ADICIONAL | C12: =+C11-C10 -> 7404171 | E12: CONTROL SKINVIVE | H12: AH Revive | I12: 3
B13: FALTA X CUMPLIR | C13: =C8-C11 -> 12595829 | E13: Meta Febrero | F13: 17 | H13: Meta Febrero | I13: =SUM(I9:I12) -> 37
B14: % ESPERADO | C14: =C10/C8 -> 0.66666667 | E14: Vendidos | F14: =F30 -> 15 | H14: Vendidos | I14: =I30 -> 17 | N14: f
B15: CUMPLIMIENTO | C15: =+C11/C8 -> 0.79006952 | E15: Faltan | F15: =F13-F14 -> 2 | H15: Faltan | I15: =I13-I14 -> 20
E19: CONTROL BOTOX | H19: CONTROL RADIESSE
E20: Meta Febrero | F20: 14359 | H20: Meta Febrero | I20: 49
E21: Disponibles Hoy | F21: 12031 | H21: Disponibles Hoy | I21: 46
E22: Unidades Botox Vendidas | F22: =F20-F21 -> 2328 | H22: Radiesse Vendidos | I22: =I20-I21 -> 3
E23: CONTROL HARMONYCA | H23: CONTROL BELOTERO
E24: Meta Febrero | F24: 89 | H24: AH Balance | I24: 40
E25: Disponibles Hoy | F25: 86 | H25: AH Intense | I25: 64
E26: Hca Vendidos | F26: =F24-F25 -> 3 | H26: AH Volume | I26: 19
E27: CONTROL SKINVIVE | H27: AH Revive | I27: 3
E28: Meta Febrero | F28: 17 | H28: Meta Febrero | I28: 143
E29: Disponibles Hoy | F29: 2 | H29: Disponibles Hoy | I29: =I24+I25+I26+I27 -> 126
E30: Skinvive Vendidos | F30: =F28-F29 -> 15 | H30: AH Belotero Vendidos | I30: =I28-I29 -> 17

Sheet PPTO TP LOUNGE
M4: % ESP | O4: REPORTE GENERAL
M5: =(E5+J5)/F5 -> #DIV/0! | O5: ='PPTO TP LOUNGE'!P18 -> 46072
M6: =(E6+J6)/F6 -> #DIV/0!
R7: EQUIPO TP PM
M8: =(E8+J8)/F8 -> #DIV/0! | O8: % ESPERADO AL DÍA | P8: % REAL AL DÍA
M9: =(E10+J10)/F10 -> #DIV/0! | O9: ='PPTO TP LOUNGE'!P31 -> 0.66666667 | P9: =P32 -> 0.65254681
M10: =(E11+J11)/F11 -> #DIV/0! | O10: =O33 -> % DIFERENCIA | P10: NOS FALTA VENDER
M11: =(E17+J17)/F17 -> 1.42275 | O11: =P33 -> -0.014119858 | P11: =100%-P9 -> 0.34745319
M12: =(E18+J18)/F18 -> 0.42375
M13: =(E19+J19)/F19 -> 1.0035 | O13: =P25 -> 0.87602021 | P13: =(P19*P25) -> 411729500 | Q13: QUITAR
B14: CONTROLADOR DE PRESUPUESTOS TP LOUNGE
M15: =(E20+J20)/F20 -> 0.164375 | O15: ESTRATEGIA DICIEMBRE
B16: ='TABLERO Y AGENDA'!N3 -> 46072 | C16: PERSONAL | D16: # ATENCIONES | E16: $ VENTA | F16: PRESUPUESTO | G16: VENTA | H16: VENTA IDEAL | I16: PROYECCIÓN % | J16: PROYECCIÓN $ | K16: PENDIENTE % | L16: PENDIENTE $ | O16: DÍAS HÁB MES | P16: ='BALANCE PPTO'!E15 -> 24
B17: TP LOUNGE | C17: LUISA FERNANDA CORREA HERNANDEZ | D17: =+COUNTIF(INFO.RENTABILIDAD!$F:F,C17) -> 17 | E17: =SUMIFS(INFO.RENTABILIDAD!$L$1:$L$15000,INFO.RENTABILIDAD!$F$1:$F$15000,C17,INFO.RENTABILIDAD!$W$1:$W$15000,"SI") -> 2340000 | F17: 8000000 | G17: =E17/F17 -> 0.2925 | H17: =(F17/$P$16)*$P$17 -> 5333333.3 | I17: =J17/F17 -> 1.13025 | J17: =SUMIF(INFO.PROYECCIÓN!$F:$F,C17,INFO.PROYECCIÓN!L:L) -> 9042000 | K17: =(L17/F17) -> 0.42275 | L17: =-(+F17-E17-J17) -> 3382000 | O17: DÍAS EJECT | P17: ='BALANCE PPTO'!E16 -> 16
C18: YANED FAYSURI RESTREPO | D18: =+COUNTIF(INFO.RENTABILIDAD!$F:F,C18) -> 32 | E18: =SUMIFS(INFO.RENTABILIDAD!$L$1:$L$15000,INFO.RENTABILIDAD!$F$1:$F$15000,C18,INFO.RENTABILIDAD!$W$1:$W$15000,"SI") -> 3390000 | F18: 8000000 | G18: =E18/F18 -> 0.42375 | H18: =(F18/$P$16)*$P$17 -> 5333333.3 | I18: =J18/F18 -> 0 | J18: =SUMIF(INFO.PROYECCIÓN!$F:$F,C18,INFO.PROYECCIÓN!L:L) -> 0 | K18: =(L18/F18) -> -0.57625 | L18: =-(+F18-E18-J18) -> -4610000 | O18: FECHA | P18: ='TABLERO Y AGENDA'!N3 -> 46072
C19: LINDA ELIANA AROCA LONDOÑO | D19: =+COUNTIF(INFO.RENTABILIDAD!$F:F,C19) -> 46 | E19: =SUMIFS(INFO.RENTABILIDAD!$L$1:$L$15000,INFO.RENTABILIDAD!$F$1:$F$15000,C19,INFO.RENTABILIDAD!$W$1:$W$15000,"SI") -> 6916000 | F19: 8000000 | G19: =E19/F19 -> 0.8645 | H19: =(F19/$P$16)*$P$17 -> 5333333.3 | I19: =J19/F19 -> 0.139 | J19: =SUMIF(INFO.PROYECCIÓN!$F:$F,C19,INFO.PROYECCIÓN!L:L) -> 1112000 | K19: =(L19/F19) -> 0.0035 | L19: =-(+F19-E19-J19) -> 28000 | O19: META DICIEMBRE | P19: 470000000
C20: ISABELLA GONZALEZ MEJIA | D20: =+COUNTIF(INFO.RENTABILIDAD!$F:F,C20) -> 9 | E20: =SUMIFS(INFO.RENTABILIDAD!$L$1:$L$15000,INFO.RENTABILIDAD!$F$1:$F$15000,C20,INFO.RENTABILIDAD!$W$1:$W$15000,"SI") -> 1315000 | F20: 8000000 | G20: =E20/F20 -> 0.164375 | H20: =(F20/$P$16)*$P$17 -> 5333333.3 | I20: =J20/F20 -> 0 | J20: =SUMIF(INFO.PROYECCIÓN!$F:$F,C20,INFO.PROYECCIÓN!L:L) -> 0 | K20: =(L20/F20) -> -0.835625 | L20: =-(+F20-E20-J20) -> -6685000 | O20: VENTA ESPERADA DIC | P20: =P34*P17 -> 3.1333333e+08
C21: KAREN LORENA AMARIS GARCES | D21: =+COUNTIF(INFO.RENTABILIDAD!$F:F,C21) -> 29 | E21: =SUMIFS(INFO.RENTABILIDAD!$L$1:$L$15000,INFO.RENTABILIDAD!$F$1:$F$15000,C21,INFO.RENTABILIDAD!$W$1:$W$15000,"SI") -> 4946000 | F21: 8000000 | G21: =E21/F21 -> 0.61825 | H21: =(F21/$P$16)*$P$17 -> 5333333.3 | I21: =J21/F21 -> 0.055 | J21: =SUMIF(INFO.PROYECCIÓN!$F:$F,C21,INFO.PROYECCIÓN!L:L) -> 440000 | K21: =(L21/F21) -> -0.32675 | L21: =-(+F21-E21-J21) -> -2614000 | O21: FACTURADO DIC | P21: ='REPORTE X DÍAS'!K16 -> 306697000
D22: Total TP Lounge: | E22: =SUM(E17:E21) -> 18907000 | F22: =SUM(F17:F21) -> 40000000 | H22: =SUM(H17:H21) -> 26666667 | O22: PROYECCIÓN DIC | P22: =SUM(INFO.PROYECCIÓN!L:L) -> 105032500
O23: FALTA X CUMPLIR | P23: =P19-P22-P21 -> 58270500
O24: RESULTADO ESP | P24: =P21+P22 -> 411729500
O25: % RESULTADO ESP | P25: =P24/P19 -> 0.87602021
O27: =O10 -> % DIFERENCIA | P27: =O11 -> -0.014119858
O30: NO INCLUIR EN EL INFORME POR FA!
O31: % AL DÍA | P31: =P17/P16 -> 0.66666667
O32: % REAL CUM | P32: =P21/P19 -> 0.65254681
O33: % DIFERENCIA | P33: =P32-P31 -> -0.014119858
O34: META DIARIA | P34: =P19/P16 -> 19583333 | Q34: =P34*22 -> 4.3083333e+08
O35: OTRAS VENTAS | P35: =P21-(E5+E6+E8+E10+E11+E17+E18+E19) -> 294051000
O36: FALTA X CUMPLIR | P36: ='REPORTE X DÍAS'!K20 -> 108270500
O37: CARTERA OCT | P37: ='REPORTE X DÍAS'!K18 -> 0
O38: ANTICIPOS OCT | P38: ='REPORTE X DÍAS'!K19 -> 6687000

Sheet PPTO TP C.E
B2: CONTROLADOR DE PRESUPUESTOS ESPECIALISTAS
B4: ='TABLERO Y AGENDA'!N3 -> 46072 | C4: PERSONAL | D4: # ATENCIONES | E4: $ VENTA | F4: PRESUPUESTO | G4: % VENTA | H4: VENTA IDEAL | I4: PROYECCIÓN % | J4: PROYECCIÓN $ | K4: PENDIENTE % | L4: PENDIENTE $ | M4: % ESP | O4: REPORTE GENERAL
B5: DERMATOLOGÍA | C5: LUISA HERNANDEZ TEJADA | D5: =+COUNTIF(INFO.RENTABILIDAD!$F:F,C5) -> 153 | E5: =SUMIFS(INFO.RENTABILIDAD!$L$1:$L$15000,INFO.RENTABILIDAD!$F$1:$F$15000,C5,INFO.RENTABILIDAD!$W$1:$W$15000,"SI") -> 59554500 | F5: 80000000 | G5: =E5/F5 -> 0.74443125 | H5: =(F5/$P$17)*$P$18 -> 53333333 | I5: =J5/F5 -> 0.249125 | J5: =SUMIF(INFO.PROYECCIÓN!$F:$F,C5,INFO.PROYECCIÓN!L:L) -> 19930000 | K5: =(L5/F5) -> -0.00644375 | L5: =-(+F5-E5-J5) -> -515500 | M5: =(E5+J5)/F5 -> 0.99355625 | O5: ='PPTO TP C.E'!P19 -> 46072
C6: DANIELA ASTAROT SALAZAR URIBE | D6: =+COUNTIF(INFO.RENTABILIDAD!$F:F,C6) -> 157 | E6: =SUMIFS(INFO.RENTABILIDAD!$L$1:$L$15000,INFO.RENTABILIDAD!$F$1:$F$15000,C6,INFO.RENTABILIDAD!$W$1:$W$15000,"SI") -> 78240000 | F6: 110000000 | G6: =E6/F6 -> 0.71127273 | H6: =(F6/$P$17)*$P$18 -> 73333333 | I6: =J6/F6 -> 0.28202273 | J6: =SUMIF(INFO.PROYECCIÓN!$F:$F,C6,INFO.PROYECCIÓN!L:L) -> 31022500 | K6: =(L6/F6) -> -0.0067045455 | L6: =-(+F6-E6-J6) -> -737500 | M6: =(E6+J6)/F6 -> 0.99329545
C7: JURANY SANCHEZ | D7: =+COUNTIF(INFO.RENTABILIDAD!$F:F,C7) -> 144 | E7: =SUMIFS(INFO.RENTABILIDAD!$L$1:$L$15000,INFO.RENTABILIDAD!$F$1:$F$15000,C7,INFO.RENTABILIDAD!$W$1:$W$15000,"SI") -> 60705000 | F7: 110000000 | G7: =E7/F7 -> 0.55186364 | H7: =(F7/$P$17)*$P$18 -> 73333333 | I7: =J7/F7 -> 0.20827273 | J7: =SUMIF(INFO.PROYECCIÓN!$F:$F,C7,INFO.PROYECCIÓN!L:L) -> 22910000 | K7: =(L7/F7) -> -0.23986364 | L7: =-(+F7-E7-J7) -> -26385000 | R7: EQUIPO TP PM
C8: PAULA ANDREA ARISTIZABAL DIAZ | D8: =+COUNTIF(INFO.RENTABILIDAD!$F:F,C8) -> 107 | E8: =SUMIFS(INFO.RENTABILIDAD!$L$1:$L$15000,INFO.RENTABILIDAD!$F$1:$F$15000,C8,INFO.RENTABILIDAD!$W$1:$W$15000,"SI") -> 22214000 | F8: 30000000 | G8: =E8/F8 -> 0.74046667 | H8: =(F8/$P$17)*$P$18 -> 20000000 | I8: =J8/F8 -> 0.079533333 | J8: =SUMIF(INFO.PROYECCIÓN!$F:$F,C8,INFO.PROYECCIÓN!L:L) -> 2386000 | K8: =(L8/F8) -> -0.18 | L8: =-(+F8-E8-J8) -> -5400000 | M8: =(E8+J8)/F8 -> 0.82 | O8: % ESPERADO AL DÍA | P8: % REAL AL DÍA
C9: DAVID CHALARCA CANAS | D9: =+COUNTIF(INFO.RENTABILIDAD!$F:F,C9) -> 100 | E9: =SUMIFS(INFO.RENTABILIDAD!$L$1:$L$15000,INFO.RENTABILIDAD!$F$1:$F$15000,C9,INFO.RENTABILIDAD!$W$1:$W$15000,"SI") -> 29544500 | F9: 70000000 | G9: =E9/F9 -> 0.42206429 | H9: =(F9/$P$17)*$P$18 -> 46666667 | I9: =J9/F9 -> 0.091571429 | J9: =SUMIF(INFO.PROYECCIÓN!$F:$F,C9,INFO.PROYECCIÓN!L:L) -> 6410000 | K9: =(L9/F9) -> -0.48636429 | L9: =-(+F9-E9-J9) -> -34045500 | M9: =(E11+J11)/F11 -> 0.663375 | O9: ='PPTO TP C.E'!P32 -> 0.66666667 | P9: =P33 -> 0.65254681
D10: Total Derma: | E10: =SUM(E5:E9) -> 250258000 | F10: =SUM(F5:F9) -> 400000000 | H10: =(F10/$P$17)*$P$18 -> 2.6666667e+08
B11: MED ESTÉTICA | C11: MARIA CAMILA ZULUAGA ALVAREZ | D11: =+COUNTIF(INFO.RENTABILIDAD!$F:F,C11) -> 26 | E11: =SUMIFS(INFO.RENTABILIDAD!$L$1:$L$15000,INFO.RENTABILIDAD!$F$1:$F$15000,C11,INFO.RENTABILIDAD!$W$1:$W$15000,"SI") -> 16275000 | F11: 40000000 | G11: =E11/F11 -> 0.406875 | H11: =(F11/$P$17)*$P$18 -> 26666667 | I11: =J11/F11 -> 0.2565 | J11: =SUMIF(INFO.PROYECCIÓN!$F:$F,C11,INFO.PROYECCIÓN!L:L) -> 10260000 | K11: =(L11/F11) -> -0.336625 | L11: =-(+F11-E11-J11) -> -13465000 | M11: =(E12+J12)/F12 -> 0.565925 | O11: =O34 -> % DIFERENCIA | P11: NOS FALTA VENDER
C12: STEPHANIA LAGUADO GONZALEZ | D12: =+COUNTIF(INFO.RENTABILIDAD!$F:F,C12) -> 29 | E12: =SUMIFS(INFO.RENTABILIDAD!$L$1:$L$15000,INFO.RENTABILIDAD!$F$1:$F$15000,C12,INFO.RENTABILIDAD!$W$1:$W$15000,"SI") -> 21257000 | F12: 40000000 | G12: =E12/F12 -> 0.531425 | H12: =(F12/$P$17)*$P$18 -> 26666667 | I12: =J12/F12 -> 0.0345 | J12: =SUMIF(INFO.PROYECCIÓN!$F:$F,C12,INFO.PROYECCIÓN!L:L) -> 1380000 | K12: =(L12/F12) -> -0.434075 | L12: =-(+F12-E12-J12) -> -17363000 | M12: =(E18+J18)/F18 -> #DIV/0! | O12: =P34 -> -0.014119858 | P12: =100%-P9 -> 0.34745319
D13: Total Med Estética: | E13: =SUM(E11:E12) -> 37532000 | F13: =SUM(F11:F12) -> 80000000 | H13: =SUM(H11:H12) -> 53333333
M14: =(E20+J20)/F20 -> #DIV/0! | O14: =P26 -> 0.87602021 | P14: =(P20*P26) -> 411729500 | Q14: QUITAR
M16: =(E21+J21)/F21 -> #DIV/0! | O16: ESTRATEGIA DICIEMBRE
O17: DÍAS HÁB MES | P17: ='BALANCE PPTO'!E15 -> 24
O18: DÍAS EJECT | P18: ='BALANCE PPTO'!E16 -> 16
O19: FECHA | P19: ='TABLERO Y AGENDA'!N3 -> 46072
O20: META DICIEMBRE | P20: 470000000
O21: VENTA ESPERADA DIC | P21: =P35*P18 -> 3.1333333e+08
O22: FACTURADO DIC | P22: ='REPORTE X DÍAS'!K16 -> 306697000
O23: PROYECCIÓN DIC | P23: =SUM(INFO.PROYECCIÓN!L:L) -> 105032500
O24: FALTA X CUMPLIR | P24: =P20-P23-P22 -> 58270500
O25: RESULTADO ESP | P25: =P22+P23 -> 411729500
O26: % RESULTADO ESP | P26: =P25/P20 -> 0.87602021
O28: =O11 -> % DIFERENCIA | P28: =O12 -> -0.014119858
O31: NO INCLUIR EN EL INFORME POR FA!
O32: % AL DÍA | P32: =P18/P17 -> 0.66666667
O33: % REAL CUM | P33: =P22/P20 -> 0.65254681
O34: % DIFERENCIA | P34: =P33-P32 -> -0.014119858
O35: META DIARIA | P35: =P20/P17 -> 19583333 | Q35: =P35*22 -> 4.3083333e+08
O36: OTRAS VENTAS | P36: =P22-(E5+E6+E8+E11+E12+E18+E19+E20) -> 109156500
O37: FALTA X CUMPLIR | P37: ='REPORTE X DÍAS'!K20 -> 108270500
O38: CARTERA OCT | P38: ='REPORTE X DÍAS'!K18 -> 0
O39: ANTICIPOS OCT | P39: ='REPORTE X DÍAS'!K19 -> 6687000

Sheet BALANCE PPTO
B4: % ESP | D4: REPORTE GENERAL
B5: =(#REF!+#REF!)/#REF! -> #REF! | D5: ='BALANCE PPTO'!E17 -> 46072
B6: =(#REF!+#REF!)/#REF! -> #REF!
I7: Meta Tu Piel Centro Especializado
B8: =(#REF!+#REF!)/#REF! -> #REF! | D8: % ESPERADO AL DÍA | E8: % REAL AL DÍA
B9: =(#REF!+#REF!)/#REF! -> #REF! | D9: ='BALANCE PPTO'!E30 -> 0.66666667 | E9: =E31 -> 0.58980192
B10: =(#REF!+#REF!)/#REF! -> #REF! | D10: =D32 -> % DIFERENCIA | E10: NOS FALTA VENDER
B11: =(#REF!+#REF!)/#REF! -> #REF! | D11: =E32 -> -0.076864744 | E11: =100%-E9 -> 0.41019808
B12: =(#REF!+#REF!)/#REF! -> #REF!
B14: =(#REF!+#REF!)/#REF! -> #REF! | D14: ESTRATEGIA FEBRERO
D15: DÍAS HÁB MES | E15: 24 | G15: Unidad de Negocio | H15: Venta | I15: Meta | J15: Faltaría | L15: Balance Meta
D16: DÍAS EJECT | E16: ='TABLERO Y AGENDA'!P3 -> 16 | G16: Tu Piel Derma | H16: ='PPTO TP C.E'!E10 -> 250258000 | I16: ='PPTO TP C.E'!F10 -> 400000000 | J16: =H16-I16 -> -149742000 | L16: Meta Global | M16: =I20 -> 580000000
D17: FECHA | E17: ='TABLERO Y AGENDA'!N3 -> 46072 | G17: Tu Piel Medicina Estética | H17: ='PPTO TP C.E'!E13 -> 37532000 | I17: 80000000 | J17: =H17-I17 -> -42468000 | L17: Ventas | M17: =H20 -> 354101171
D18: META ENERO | E18: 520000000 | G18: TP Lounge | H18: ='PPTO TP LOUNGE'!E22 -> 18907000 | I18: 40000000 | J18: =H18-I18 -> -21093000 | L18: Agendamiento | M18: =E21 -> 105032500
D19: VENTA ESPERADA FEB | E19: =E33*E16 -> 3.4666667e+08 | G19: Productos | H19: =PRODUCTOS!C11 -> 47404171 | I19: 60000000 | J19: =H19-I19 -> -12595829 | L19: Falta | M19: =M18+M17-M16 -> -120866329
D20: FACTURADO FEB | E20: ='REPORTE X DÍAS'!K16 -> 306697000 | G20: Total | H20: =SUM(H16:H19) -> 354101171 | I20: =SUM(I16:I19) -> 580000000
D21: PROYECCIÓN FEB | E21: =SUM(INFO.PROYECCIÓN!L:L) -> 105032500 | H21: =H20*3 -> 1062303513
D22: FALTA X CUMPLIR | E22: =E18-E21-E20 -> 108270500
D23: RESULTADO ESP | E23: =E20+E21 -> 411729500 | G23: =+H20/21 -> 16861961
D24: % RESULTADO ESP | E24: =E23/E18 -> 0.7917875
D26: =D10 -> % DIFERENCIA | E26: =D11 -> -0.076864744
D29: NO INCLUIR EN EL INFORME POR FA!
D30: % AL DÍA | E30: =E16/E15 -> 0.66666667
D31: % REAL CUM | E31: =E20/E18 -> 0.58980192
D32: % DIFERENCIA | E32: =E31-E30 -> -0.076864744
D33: META DIARIA | E33: =E18/E15 -> 21666667 | F33: =E33*22 -> 4.7666667e+08
D34: OTRAS VENTAS | E34: =E20-(#REF!+#REF!+#REF!+#REF!+#REF!+#REF!+#REF!+#REF!) -> #REF!
D35: FALTA X CUMPLIR | E35: ='REPORTE X DÍAS'!K20 -> 108270500
D36: CARTERA OCT | E36: ='REPORTE X DÍAS'!K18 -> 0
D37: ANTICIPOS OCT | E37: ='REPORTE X DÍAS'!K19 -> 6687000
D42: Meta Ventas | E42: Valor $
D43: Tu Piel Centro Especializado | E43: 420000000
D44: Tu Piel Lounge | E44: 40000000
D45: Venta de Producto | E45: 55000000

Sheet INFO.PROYECCIÓN
A1: # Atención | B1: # Registro | C1: Fecha | D1: Doc. Paciente | E1: Nombre Paciente | F1: Personal Atiende | G1: Código Cups | H1: Cups | I1: Sub Categoria | J1: Categoria | K1: Dispositivo | L1: Vlr | M1: Vlr Comisiones | N1: Vlr Insumos | O1: Costo Adicional | P1: Rentabilidad Insumos | Q1: Rentabilidad Equipos | R1: Rentabilidad Ips | S1: Rentabilidad Total | T1: Rentabilidad Porcentaje | U1: Pendiente Registrar | V1: Fecha Facturación | W1: Pagado este mes | X1: Procedencia / Recomendacion | Y1: Edad del paciente | Z1: Numero Factura
A2: 24079 | B2: 6805 | C2: 46073 | D2: CC 1017206567 | E2: MARIA ALEJANDRA RAMIREZ | F2: LUISA FERNANDA CORREA HERNANDEZ | G2: DL0011 | H2: COMBO 7 (DEPILACIÓN ZONA MINI + MEDIANA) | I2: DEPILACION - COSMETOLOGÍA | J2: COSMETOLOGÍA | K2: 1050 DEPILACIÓN REMOVALL | L2: 130000 | M2: 22100 | N2: 0 | O2: 0 | P2: 0 | Q2: 0 | R2: 107900 | S2: 107900 | T2: 0.83 | U2: SI | W2: SIN PAGO | X2: AMIG@ | Y2: 33
A3: 28314 | B3: 13524 | C3: 46074 | D3: CC 1033489106 | E3: JUAN JOSE ARBOLEDA GARCIA | F3: JURANY SANCHEZ | G3: 890242 | H3: CONSULTA DE PRIMERA VEZ POR MEDICINA ESPECIALIZADA -DERMATOL | I3: CONSULTA PRIMERA VEZ - CONSULTA | J3: CONSULTA | L3: 230000 | M3: 115000 | N3: 0 | O3: 0 | P3: 0 | Q3: 0 | R3: 115000 | S3: 115000 | T3: 0.5 | U3: SI | W3: SIN PAGO | X3: AMIG@ | Y3: 0
A4: 30702 | B4: 17553 | C4: 46080 | D4: CC 1049611021 | E4: YESICA PAOLA ARIZA MORA | F4: LUISA HERNANDEZ TEJADA | G4: LP0001 | H4: LONGPULSE - MELASMA COMPONENTE VASCULAR + PIGMENTARIO - PASO 1/2 | I4: LONGPULSE - PROCEDIMIENTOS | J4: PROCEDIMIENTOS | K4: 60 LONGPULSE | L4: 150000 | M4: 75000 | N4: 0 | O4: 0 | P4: 0 | Q4: 0 | R4: 75000 | S4: 75000 | T4: 0.5 | U4: SI | W4: SIN PAGO | X4: INSTAGRAM | Y4: 37
A5: 30702 | B5: 17554 | C5: 46080 | D5: CC 1049611021 | E5: YESICA PAOLA ARIZA MORA | F5: LUISA HERNANDEZ TEJADA | G5: HP0001 | H5: HANDPICO - MELASMA COMPONENTE PIGMENTARIO - PASO 2/2 | I5: HANDPICO - PROCEDIMIENTOS | J5: PROCEDIMIENTOS | K5: 60 LONGPULSE | L5: 450000 | M5: 225000 | N5: 0 | O5: 0 | P5: 0 | Q5: 0 | R5: 225000 | S5: 225000 | T5: 0.5 | U5: SI | W5: SIN PAGO | X5: INSTAGRAM | Y5: 37
A6: 32356 | B6: 20091 | C6: 46077 | D6: CC 1192741542 | E6: LAURA VICTORIA LOPEZ HERNANDEZ | F6: JURANY SANCHEZ | G6: HP0008 | H6: HANDPICO - TATUAJE PEQUEÑO HASTA 3 CM | I6: HANDPICO - PROCEDIMIENTOS | J6: PROCEDIMIENTOS | K6: 1034 HANDPICO | L6: 540000 | M6: 264600 | N6: 0 | O6: 0 | P6: 0 | Q6: 0 | R6: 275400 | S6: 264600 | T6: 0.49 | U6: SI | V6: 2025-10-03 11:34:00 | W6: NO | X6: INSTAGRAM | Y6: 25 | Z6: FE10984
A7: 32370 | B7: 21321 | C7: 46076 | D7: CC 1007053639 | E7: SEBASTIAN VELEZ ZAPATA | F7: DANIELA ASTAROT SALAZAR URIBE | G7: 861401 | H7: INFILTRACION INTRALESIONAL 1-5 LESIONES | I7: PROCE DERMA - PROCEDIMIENTOS | J7: PROCEDIMIENTOS | L7: 250000 | M7: 125000 | N7: 0 | O7: 0 | P7: 0 | Q7: 0 | R7: 125000 | S7: 125000 | T7: Revisar insumos | U7: SI | W7: SIN PAGO | X7: PAGINA WEB | Y7: 23
A8: 33282 | B8: 21442 | C8: 46080 | D8: CC 1036643377 | E8: CAMILA PELAEZ USMA | F8: JURANY SANCHEZ | G8: PD0009 | H8: CICATRICES POST QUIRURGICAS 6-10 CMS - PRODEEP | I8: PRODEEP - PROCEDIMIENTOS | J8: PROCEDIMIENTOS | K8: 59 PRODEEP | L8: 500000 | M8: 250000 | N8: 0 | O8: 0 | P8: 0 | Q8: 0 | R8: 250000 | S8: 250000 | T8: 0.5 | U8: SI | W8: SIN PAGO | X8: INSTAGRAM | Y8: 33
A9: 33013 | B9: 21585 | C9: 46076 | D9: CC 1152683958 | E9: CAMILO OCHOA HERNANDEZ | F9: LUISA FERNANDA CORREA HERNANDEZ | G9: DL0001 | H9: DEPILACION ZONA PEQUEÑA (AXILAS, LINEA ALBA, MANOS) | I9: DEPILACION - COSMETOLOGÍA | J9: COSMETOLOGÍA | K9: 1050 DEPILACIÓN REMOVALL | L9: 57000 | M9: 9496.2 | N9: 0 | O9: 0 | P9: 0 | Q9: 0 | R9: 47503.8 | S9: 46363.8 | T9: 0.8134 | U9: SI | V9: 2025-11-08 13:59:00 | W9: NO | X9: AMIG@ | Y9: 34 | Z9: FE58
A10: 33776 | B10: 22262 | C10: 46074 | D10: TI 1064191165 | E10: JUAN CARLOS MARTINEZ BERRIO | F10: LUISA HERNANDEZ TEJADA | G10: 890302 | H10: CONSULTA DE CONTROL O DE SEGUIMIENTO POR MEDICINA ESPECIALIZADA > 1 MES | I10: CONSULTA CONTROL - CONSULTA | J10: CONSULTA | L10: 150000 | M10: 75000 | N10: 0 | O10: 0 | P10: 0 | Q10: 0 | R10: 75000 | S10: 75000 | T10: 0.5 | U10: SI | W10: SIN PAGO | X10: AMIG@ | Y10: 18
A11: 23034 | B11: 23194 | C11: 46079 | D11: CC 70753003 | E11: JUAN MANUEL RESTREPO | F11: JURANY SANCHEZ | G11: M00003 | H11: MESOTERAPIA PELO DUTASTERIDE | I11: MESOJECT - PROCEDIMIENTOS | J11: PROCEDIMIENTOS | L11: 450000 | M11: 225000 | N11: 0 | O11: 0 | P11: 0 | Q11: 0 | R11: 225000 | S11: 225000 | T11: Revisar insumos | U11: SI | W11: SIN PAGO | X11: AMIG@ | Y11: 50
A12: 34430 | B12: 23231 | C12: 46074 | D12: CC 43664001 | E12: MARGARITA ELENA MARIN MARIN | F12: LUISA HERNANDEZ TEJADA | G12: 868114 | H12: RESECCION BENIGNA < 1 CM SIN PATOLOGIA | I12: PROCE DERMA - PROCEDIMIENTOS | J12: PROCEDIMIENTOS | L12: 600000 | M12: 300000 | N12: 0 | O12: 0 | P12: 0 | Q12: 0 | R12: 300000 | S12: 300000 | T12: Revisar insumos | U12: SI | W12: SIN PAGO | X12: AMIG@ | Y12: 58
A13: 34430 | B13: 23289 | C13: 46074 | D13: CC 43664001 | E13: MARGARITA ELENA MARIN MARIN | F13: LUISA HERNANDEZ TEJADA | G13: PD0020 | H13: REJUVENECIMIENTO FACIAL + EXOSOMAS - PRODEEP | I13: PRODEEP - PROCEDIMIENTOS | J13: PROCEDIMIENTOS | K13: 59 PRODEEP | L13: 1800000 | M13: 900000 | N13: 0 | O13: 0 | P13: 0 | Q13: 0 | R13: 900000 | S13: 900000 | T13: Revisar insumos | U13: SI | W13: SIN PAGO | X13: AMIG@ | Y13: 58
A14: 34617 | B14: 23500 | C14: 46080 | D14: CC 1037598968 | E14: LADY YAMILEY BEDOYA CORREA | F14: LUISA HERNANDEZ TEJADA | G14: HP0001 | H14: HANDPICO - MELASMA COMPONENTE PIGMENTARIO - PASO 2/2 | I14: HANDPICO - PROCEDIMIENTOS | J14: PROCEDIMIENTOS | K14: 1034 HANDPICO | L14: 350000 | M14: 175000 | N14: 0 | O14: 0 | P14: 0 | Q14: 0 | R14: 175000 | S14: 175000 | T14: 0.5 | U14: SI | W14: SIN PAGO | X14: FACEBOOK | Y14: 37
A15: 33360 | B15: 23577 | C15: 46074 | D15: CC 1001535287 | E15: SANDRA MORALES MORALES | F15: LUISA HERNANDEZ TEJADA | G15: IP0001 | H15: IPL PROCEDIMIENTOS POR ZONA | I15: IPL-SQ - PROCEDIMIENTOS | J15: PROCEDIMIENTOS | K15: 43 IPL-SQ | L15: 400000 | M15: 200000 | N15: 0 | O15: 0 | P15: 0 | Q15: 0 | R15: 200000 | S15: 200000 | T15: 0.5 | U15: SI | W15: SIN PAGO | X15: INSTAGRAM | Y15: 23
A16: 34710 | B16: 23660 | C16: 46074 | D16: CC 1128329773 | E16: ADRIANA LUCIA SINNING OSORIO | F16: JURANY SANCHEZ | G16: 890242 | H16: CONSULTA DE PRIMERA VEZ POR MEDICINA ESPECIALIZADA -DERMATOL | I16: CONSULTA PRIMERA VEZ - CONSULTA | J16: CONSULTA | L16: 230000 | M16: 115000 | N16: 0 | O16: 0 | P16: 0 | Q16: 0 | R16: 115000 | S16: 115000 | T16: 0.5 | U16: SI | W16: SIN PAGO | X16: GOOGLE | Y16: 0
A17: 31859 | B17: 23739 | C17: 46080 | D17: CC 1042094737 | E17: ERICA LICETH GAVIRIA MEJIA | F17: DANIELA ASTAROT SALAZAR URIBE | G17: CM0017 | H17: COLOR MAX MELASMA - HIPERPIGMENTEACIONES | I17: COLOR MAX - PROCEDIMIENTOS | J17: PROCEDIMIENTOS | K17: NA LÁSER COLOR MAX | L17: 600000 | M17: 300000 | N17: 0 | O17: 0 | P17: 0 | Q17: 0 | R17: 300000 | S17: 300000 | T17: Revisar insumos | U17: SI | W17: SIN PAGO | X17: AMIG@ | Y17: 35
A18: 34302 | B18: 23908 | C18: 46076 | D18: CC 43255508 | E18: MARCELA VANEGAS GONZALEZ | F18: JURANY SANCHEZ | G18: 861415 | H18: APLICACIÓN BIOESTIMULADOR SCULPTRA | I18: INYECTABLES - PROCEDIMIENTOS | J18: PROCEDIMIENTOS | L18: 250000 | M18: 122500 | N18: 0 | O18: 0 | P18: 0 | Q18: 0 | R18: 127500 | S18: 122500 | T18: Revisar insumos | U18: SI | V18: 2026-01-26 13:54:00 | W18: NO | X18: AMIG@ | Y18: 44 | Z18: FE13689
A19: 33771 | B19: 24096 | C19: 46080 | D19: CC 1041328840 | E19: VERONICA ANDREA OCHOA SANCHEZ | F19: LUISA HERNANDEZ TEJADA | G19: IP0001 | H19: IPL PROCEDIMIENTOS POR ZONA | I19: IPL-SQ - PROCEDIMIENTOS | J19: PROCEDIMIENTOS | K19: 43 IPL-SQ | L19: 350000 | M19: 175000 | N19: 0 | O19: 0 | P19: 0 | Q19: 0 | R19: 175000 | S19: 175000 | T19: 0.5 | U19: SI | W19: SIN PAGO | X19: INSTAGRAM | Y19: 29
A20: 33771 | B20: 24097 | C20: 46080 | D20: CC 1041328840 | E20: VERONICA ANDREA OCHOA SANCHEZ | F20: LUISA HERNANDEZ TEJADA | G20: HP0001 | H20: HANDPICO - MELASMA COMPONENTE PIGMENTARIO - PASO 2/2 | I20: HANDPICO - PROCEDIMIENTOS | J20: PROCEDIMIENTOS | K20: 1034 HANDPICO | L20: 350000 | M20: 175000 | N20: 0 | O20: 0 | P20: 0 | Q20: 0 | R20: 175000 | S20: 175000 | T20: 0.5 | U20: SI | W20: SIN PAGO | X20: INSTAGRAM | Y20: 29
A21: 35029 | B21: 24100 | C21: 46073 | D21: CC 1000762846 | E21: RONALD DAVID MORELO GUARIN | F21: DANIELA ASTAROT SALAZAR URIBE | G21: 890242 | H21: CONSULTA DE PRIMERA VEZ POR MEDICINA ESPECIALIZADA -DERMATOL | I21: CONSULTA PRIMERA VEZ - CONSULTA | J21: CONSULTA | L21: 250000 | M21: 125000 | N21: 0 | O21: 0 | P21: 0 | Q21: 0 | R21: 125000 | S21: 125000 | T21: 0.5 | U21: SI | W21: SIN PAGO | X21: INSTAGRAM | Y21: 0
A22: 35071 | B22: 24152 | C22: 46081 | D22: RC 1036692000 | E22: DOMINIC CANO DUQUE | F22: PAULA ANDREA ARISTIZABAL DIAZ | G22: 890303 | H22: CONSULTA DE CONTROL - PROCEDIMIENTO | I22: CONSULTA CONTROL - CONSULTA | J22: CONSULTA | L22: 0 | M22: 0 | N22: 0 | O22: 0 | P22: 0 | Q22: 0 | R22: 0 | S22: 0 | T22: Revisar insumos | U22: SI | W22: SIN PAGO | X22: INSTAGRAM | Y22: 4
A23: 28033 | B23: 24170 | C23: 46073 | D23: CC 1037525219 | E23: MARIA JOSE ARROYAVE TABORDA | F23: LUISA FERNANDA CORREA HERNANDEZ | G23: DL0013 | H23: COMBO 8 (ZONA PEQUEÑA + ZONA MEDIANA) | I23: DEPILACION - COSMETOLOGÍA | J23: COSMETOLOGÍA | L23: 140000 | M23: 2800 | N23: 0 | O23: 0 | P23: 0 | Q23: 0 | R23: 137200 | S23: 137200 | T23: Revisar insumos | U23: SI | W23: SIN PAGO | X23: VITRINA | Y23: 26
A24: 35160 | B24: 24299 | C24: 46073 | D24: CC 1096253120 | E24: NAYBEHD AGUILAR JEREZ | F24: DANIELA ASTAROT SALAZAR URIBE | G24: LP0008 | H24: TRATAMIENTO DE ONICOMICOSIS - LONGPULSE | I24: LONGPULSE - PROCEDIMIENTOS | J24: PROCEDIMIENTOS | K24: 60 LONGPULSE | L24: 332500 | M24: 162925 | N24: 0 | O24: 0 | P24: 0 | Q24: 0 | R24: 169575 | S24: 162925 | T24: 0.49 | U24: SI | V24: 2026-01-06 19:15:00 | W24: NO | X24: INSTAGRAM | Y24: 26 | Z24: FE13231
A25: 35206 | B25: 24358 | C25: 46074 | D25: TI 1013463311 | E25: MARIANA RUIZ PEREIRA | F25: JURANY SANCHEZ | G25: M00011 | H25: FOTOAGE | I25: FOTOAGE - PROCEDIMIENTOS | J25: PROCEDIMIENTOS | K25: A123 DISPOSITIVO FOTOAGE | L25: 650000 | M25: 325000 | N25: 0 | O25: 0 | P25: 0 | Q25: 0 | R25: 325000 | S25: 325000 | T25: Revisar insumos | U25: SI | W25: SIN PAGO | X25: GOOGLE | Y25: 15
A26: 35135 | B26: 24388 | C26: 46077 | D26: CC 1048045744 | E26: KELLY YISELA OLARTE MEJIA | F26: DANIELA ASTAROT SALAZAR URIBE | G26: 868116 | H26: SUBCISION | I26: PROCE DERMA - PROCEDIMIENTOS | J26: PROCEDIMIENTOS | L26: 200000 | M26: 100000 | N26: 0 | O26: 0 | P26: 0 | Q26: 0 | R26: 100000 | S26: 100000 | T26: Revisar insumos | U26: SI | W26: SIN PAGO | X26: INSTAGRAM | Y26: 31
A27: 35135 | B27: 24389 | C27: 46077 | D27: CC 1048045744 | E27: KELLY YISELA OLARTE MEJIA | F27: DANIELA ASTAROT SALAZAR URIBE | G27: LC0001 | H27: CO2 CICATRICES ACNE CARA | I27: LASER Co2 - PROCEDIMIENTOS | J27: PROCEDIMIENTOS | K27: NA LÁSER IBLAZE (CO2) | L27: 1000000 | M27: 500000 | N27: 0 | O27: 0 | P27: 0 | Q27: 0 | R27: 500000 | S27: 500000 | T27: Revisar insumos | U27: SI | W27: SIN PAGO | X27: INSTAGRAM | Y27: 31
A28: 27318 | B28: 24515 | C28: 46080 | D28: CC 43182047 | E28: SANDRA VIVIANA BOTERO SERNA | F28: LUISA HERNANDEZ TEJADA | G28: LC0004 | H28: CO2 REJUVENICIMIENTO FACIAL | I28: LASER Co2 - PROCEDIMIENTOS | J28: PROCEDIMIENTOS | K28: NA LÁSER IBLAZE (CO2) | L28: 800000 | M28: 400000 | N28: 0 | O28: 0 | P28: 0 | Q28: 0 | R28: 400000 | S28: 400000 | T28: 0.5 | U28: SI | W28: SIN PAGO | X28: VITRINA | Y28: 41
A29: 35344 | B29: 24574 | C29: 46074 | D29: CC 1152218205 | E29: SARA ISABEL BRICEÑO MARIN | F29: LUISA HERNANDEZ TEJADA | G29: 890303 | H29: CONSULTA DE CONTROL - PROCEDIMIENTO | I29: CONSULTA CONTROL - CONSULTA | J29: CONSULTA | L29: 0 | M29: 0 | N29: 0 | O29: 0 | P29: 0 | Q29: 0 | R29: 0 | S29: 0 | T29: Revisar insumos | U29: SI | W29: SIN PAGO | X29: INSTAGRAM | Y29: 28
A30: 35421 | B30: 24709 | C30: 46078 | D30: CC 1000406864 | E30: JHON STEVEN SCHNAIDER ARISTIZABAL | F30: PAULA ANDREA ARISTIZABAL DIAZ | G30: 890303 | H30: CONSULTA DE CONTROL O DE SEGUIMIENTO POR ESPECIALISTA EN DERMATOLOGÍA < 1 MES | I30: PROCE DERMA - PROCEDIMIENTOS | J30: PROCEDIMIENTOS | L30: 0 | M30: 0 | N30: 0 | O30: 0 | P30: 0 | Q30: 0 | R30: 0 | S30: 0 | T30: 0 | U30: SI | W30: SIN PAGO | X30: INSTAGRAM | Y30: 26
A31: 35425 | B31: 24719 | C31: 46079 | D31: CC 1027740425 | E31: MANUELA POSADA PEREZ | F31: LUISA HERNANDEZ TEJADA | G31: HP0012 | H31: HANDPICO HIPERPIGMENTACIONES | I31: HANDPICO - PROCEDIMIENTOS | J31: PROCEDIMIENTOS | K31: 1034 HANDPICO | L31: 700000 | M31: 350000 | N31: 0 | O31: 0 | P31: 0 | Q31: 0 | R31: 350000 | S31: 350000 | T31: Revisar insumos | U31: SI | W31: SIN PAGO | X31: GOOGLE | Y31: 20
A32: 34655 | B32: 24814 | C32: 46080 | D32: CC 1214735381 | E32: KEVIN ESTEBAN ANGEL GARCIA | F32: LUISA HERNANDEZ TEJADA | G32: N00003 | H32: NANOPORE CICATRICES | I32: NANOPORE - PROCEDIMIENTOS | J32: PROCEDIMIENTOS | K32: N/A NANOPORE | L32: 700000 | M32: 350000 | N32: 0 | O32: 0 | P32: 0 | Q32: 0 | R32: 350000 | S32: 350000 | T32: Revisar insumos | U32: SI | W32: SIN PAGO | X32: INSTAGRAM | Y32: 29
A33: 34446 | B33: 24818 | C33: 46074 | D33: CC 1128446377 | E33: EDILSA BUITRAGO GARCIA | F33: MARIA CAMILA ZULUAGA ALVAREZ | G33: P00008 | H33: PEELING MELASMA MELINE | I33: PEELING - PROCEDIMIENTOS | J33: PROCEDIMIENTOS | L33: 900000 | M33: 450000 | N33: 0 | O33: 0 | P33: 0 | Q33: 0 | R33: 450000 | S33: 450000 | T33: Revisar insumos | U33: SI | W33: SIN PAGO | X33: INSTAGRAM | Y33: 38
A34: 34446 | B34: 24819 | C34: 46074 | D34: CC 1128446377 | E34: EDILSA BUITRAGO GARCIA | F34: MARIA CAMILA ZULUAGA ALVAREZ | G34: P00009 | H34: PEELING DESPIGMENTANTE DE OJERAS | I34: PEELING - PROCEDIMIENTOS | J34: PROCEDIMIENTOS | L34: 1900000 | M34: 950000 | N34: 0 | O34: 0 | P34: 0 | Q34: 0 | R34: 950000 | S34: 950000 | T34: Revisar insumos | U34: SI | W34: SIN PAGO | X34: INSTAGRAM | Y34: 38
A35: 35543 | B35: 24889 | C35: 46074 | D35: CC 1152202772 | E35: VANESSA DURANGO TABORDA | F35: DANIELA ASTAROT SALAZAR URIBE | G35: IP0001 | H35: IPL PROCEDIMIENTOS POR ZONA | I35: IPL-SQ - PROCEDIMIENTOS | J35: PROCEDIMIENTOS | K35: 43 IPL-SQ | L35: 100000 | M35: 65000 | N35: 0 | O35: 0 | P35: 0 | Q35: 0 | R35: 35000 | S35: 35000 | T35: Revisar insumos | U35: SI | W35: SIN PAGO | X35: AMIG@ | Y35: 32
A36: 25459 | B36: 24912 | C36: 46074 | D36: CC 1067093514 | E36: JESSICA PAOLA GUZMAN ALEMAN | F36: LUISA FERNANDA CORREA HERNANDEZ | G36: DL0002 | H36: DEPILACION ZONA MEDIANA ( ROSTRO COMPLETO, BIKINI) | I36: DEPILACION - COSMETOLOGÍA | J36: COSMETOLOGÍA | K36: 1050 DEPILACIÓN REMOVALL | L36: 90000 | M36: 15300 | N36: 0 | O36: 0 | P36: 0 | Q36: 0 | R36: 74700 | S36: 74700 | T36: Revisar insumos | U36: SI | W36: SIN PAGO | X36: GOOGLE | Y36: 35
A37: 32879 | B37: 24916 | C37: 46074 | D37: CC 1000438804 | E37: FELIPE GARZON TORRES | F37: DANIELA ASTAROT SALAZAR URIBE | G37: PD0007 | H37: CICATRICES ACNE - PRODEEP | I37: PRODEEP - PROCEDIMIENTOS | J37: PROCEDIMIENTOS | K37: 59 PRODEEP | L37: 1100000 | M37: 550000 | N37: 0 | O37: 0 | P37: 0 | Q37: 0 | R37: 550000 | S37: 550000 | T37: Revisar insumos | U37: SI | W37: SIN PAGO | X37: INSTAGRAM | Y37: 23
A38: 32879 | B38: 24917 | C38: 46074 | D38: CC 1000438804 | E38: FELIPE GARZON TORRES | F38: DANIELA ASTAROT SALAZAR URIBE | G38: 868116 | H38: SUBCISION | I38: PROCE DERMA - PROCEDIMIENTOS | J38: PROCEDIMIENTOS | K38: 59 PRODEEP | L38: 200000 | M38: 100000 | N38: 0 | O38: 0 | P38: 0 | Q38: 0 | R38: 100000 | S38: 100000 | T38: Revisar insumos | U38: SI | W38: SIN PAGO | X38: INSTAGRAM | Y38: 23
A39: 35554 | B39: 24922 | C39: 46074 | D39: CC 1020402627 | E39: YEIDY NATALY RAMIREZ BONILLA | F39: STEPHANIA LAGUADO GONZALEZ | G39: 861426 | H39: JALUPRO CLASIC | I39: INYECTABLES - PROCEDIMIENTOS | J39: PROCEDIMIENTOS | L39: 900000 | M39: 450000 | N39: 0 | O39: 0 | P39: 0 | Q39: 0 | R39: 450000 | S39: 450000 | T39: Revisar insumos | U39: SI | W39: SIN PAGO | X39: AMIG@ | Y39: 39
A40: 35579 | B40: 24954 | C40: 46081 | D40: CC 1001028073 | E40: GISELA MARTINEZ PALACIOS | F40: PAULA ANDREA ARISTIZABAL DIAZ | G40: 890303 | H40: CONSULTA DE CONTROL O DE SEGUIMIENTO POR ESPECIALISTA EN DERMATOLOGÍA < 1 MES | I40: PROCE DERMA - PROCEDIMIENTOS | J40: PROCEDIMIENTOS | L40: 0 | M40: 0 | N40: 0 | O40: 0 | P40: 0 | Q40: 0 | R40: 0 | S40: 0 | T40: 0 | U40: SI | W40: SIN PAGO | X40: FACEBOOK | Y40: 25
A41: 35580 | B41: 24955 | C41: 46074 | D41: CC 1010021483 | E41: HANNAH SOFIA SANCHEZ ARCE | F41: DANIELA ASTAROT SALAZAR URIBE | G41: 890303 | H41: CONSULTA DE CONTROL - PROCEDIMIENTO | I41: CONSULTA CONTROL - CONSULTA | J41: CONSULTA | L41: 0 | M41: 0 | N41: 0 | O41: 0 | P41: 0 | Q41: 0 | R41: 0 | S41: 0 | T41: Revisar insumos | U41: SI | W41: SIN PAGO | X41: INSTAGRAM | Y41: 23
A42: 35593 | B42: 24971 | C42: 46073 | D42: CC 8033191 | E42: CAMILO PATIÑO VELASQUEZ | F42: LUISA FERNANDA CORREA HERNANDEZ | G42: HF0012 | H42: HYDRAFACIAL PIEL LUMINOSA (1+1) | I42: HYDRAFACIAL - COSMETOLOGÍA | J42: COSMETOLOGÍA | L42: 1056000 | M42: 179520 | N42: 0 | O42: 0 | P42: 0 | Q42: 0 | R42: 876480 | S42: 876480 | T42: Revisar insumos | U42: SI | W42: SIN PAGO | X42: VITRINA | Y42: 40
A43: 35594 | B43: 24972 | C43: 46077 | D43: CC 1039758831 | E43: VIVIANA ANDREA CANO CANO | F43: DANIELA ASTAROT SALAZAR URIBE | G43: 890303 | H43: CONSULTA DE CONTROL - PROCEDIMIENTO | I43: CONSULTA CONTROL - CONSULTA | J43: CONSULTA | L43: 0 | M43: 0 | N43: 0 | O43: 0 | P43: 0 | Q43: 0 | R43: 0 | S43: 0 | T43: Revisar insumos | U43: SI | W43: SIN PAGO | X43: INSTAGRAM | Y43: 37
A44: 34098 | B44: 24976 | C44: 46080 | D44: CC 1140814708 | E44: GARY GARCIA VALENCIA | F44: DANIELA ASTAROT SALAZAR URIBE | G44: M00007 | H44: MESOTERAPIA CAPILAR | I44: MESOJECT - PROCEDIMIENTOS | J44: PROCEDIMIENTOS | L44: 500000 | M44: 250000 | N44: 0 | O44: 0 | P44: 0 | Q44: 0 | R44: 250000 | S44: 250000 | T44: Revisar insumos | U44: SI | W44: SIN PAGO | X44: INSTAGRAM | Y44: 37
A45: 35630 | B45: 25041 | C45: 46080 | D45: CC 1128415477 | E45: LUISA MARIA ESPITIA GOMEZ | F45: LUISA HERNANDEZ TEJADA | G45: 890303 | H45: CONSULTA DE CONTROL - PROCEDIMIENTO | I45: CONSULTA CONTROL - CONSULTA | J45: CONSULTA | L45: 0 | M45: 0 | N45: 0 | O45: 0 | P45: 0 | Q45: 0 | R45: 0 | S45: 0 | T45: Revisar insumos | U45: SI | W45: SIN PAGO | X45: INSTAGRAM | Y45: 37
A46: 29461 | B46: 25076 | C46: 46074 | D46: CC 1035283321 | E46: DANIELA ALEJANDRA HIGUITA HIGUITA | F46: DANIELA ASTAROT SALAZAR URIBE | G46: 861401 | H46: INFILTRACION INTRALESIONAL 1-5 LESIONES | I46: PROCE DERMA - PROCEDIMIENTOS | J46: PROCEDIMIENTOS | L46: 300000 | M46: 150000 | N46: 0 | O46: 0 | P46: 0 | Q46: 0 | R46: 150000 | S46: 150000 | T46: 0.5 | U46: SI | W46: SIN PAGO | X46: INSTAGRAM | Y46: 31
A47: 29461 | B47: 25077 | C47: 46074 | D47: CC 1035283321 | E47: DANIELA ALEJANDRA HIGUITA HIGUITA | F47: DANIELA ASTAROT SALAZAR URIBE | G47: LC0001 | H47: CO2 CICATRICES ACNE CARA | I47: LASER Co2 - PROCEDIMIENTOS | J47: PROCEDIMIENTOS | K47: NA LÁSER IBLAZE (CO2) | L47: 1000000 | M47: 500000 | N47: 0 | O47: 0 | P47: 0 | Q47: 0 | R47: 500000 | S47: 500000 | T47: 0.5 | U47: SI | W47: SIN PAGO | X47: INSTAGRAM | Y47: 31
A48: 30220 | B48: 25086 | C48: 46077 | D48: CC 43745737 | E48: NANCY TOBON MUÑOZ | F48: MARIA JOSE SANCHEZ HIGUITA | G48: DL0003 | H48: DEPILACION ZONA GRANDE (PIERNAS, ESPALDA, MUSLOS, PECHO, ABDOMEN) | I48: DEPILACION - COSMETOLOGÍA | J48: COSMETOLOGÍA | K48: 1050 DEPILACIÓN REMOVALL | L48: 140000 | M48: 23800 | N48: 0 | O48: 0 | P48: 0 | Q48: 0 | R48: 116200 | S48: 116200 | T48: 0.83 | U48: SI | W48: SIN PAGO | X48: AMIG@ | Y48: 51
A49: 34189 | B49: 25103 | C49: 46074 | D49: RC 1034930060 | E49: DANNA VICTORIA CARRASCAL GONZALEZ | F49: DANIELA ASTAROT SALAZAR URIBE | G49: LC0008 | H49: CO2 FULGURACION 1- 5 LESIONES MENORES 0.5 CM | I49: LASER IBLAZE (CO2) - PROCEDIMIENTOS | J49: PROCEDIMIENTOS | K49: NA LÁSER IBLAZE (CO2) | L49: 450000 | M49: 225000 | N49: 0 | O49: 0 | P49: 0 | Q49: 0 | R49: 225000 | S49: 225000 | T49: 0.5 | U49: SI | W49: SIN PAGO | X49: PAGINA WEB | Y49: 4
A50: 35703 | B50: 25164 | C50: 46076 | D50: CC 43908630 | E50: ELENA HIGUITA | F50: LUISA HERNANDEZ TEJADA | G50: 890303 | H50: CONSULTA DE CONTROL - PROCEDIMIENTO | I50: CONSULTA CONTROL - CONSULTA | J50: CONSULTA | L50: 0 | M50: 0 | N50: 0 | O50: 0 | P50: 0 | Q50: 0 | R50: 0 | S50: 0 | T50: Revisar insumos | U50: SI | W50: SIN PAGO | X50: MEDICO | Y50: 43
A51: 27678 | B51: 25187 | C51: 46073 | D51: CC 1017204597 | E51: STEFANY RIOS | F51: DANIELA ASTAROT SALAZAR URIBE | G51: LC0001 | H51: CO2 CICATRICES ACNE CARA | I51: LASER Co2 - PROCEDIMIENTOS | J51: PROCEDIMIENTOS | K51: NA LÁSER IBLAZE (CO2) | L51: 0 | M51: 0 | N51: 0 | O51: 0 | P51: 0 | Q51: 0 | R51: 0 | S51: 0 | T51: 0 | U51: SI | W51: SIN PAGO | X51: INSTAGRAM | Y51: 33
A52: 35759 | B52: 25278 | C52: 46073 | D52: TI 1035872498 | E52: EMILY YEPES CARMONA | F52: DANIELA ASTAROT SALAZAR URIBE | G52: 890303 | H52: CONSULTA DE CONTROL - PROCEDIMIENTO | I52: CONSULTA CONTROL - CONSULTA | J52: CONSULTA | L52: 0 | M52: 0 | N52: 0 | O52: 0 | P52: 0 | Q52: 0 | R52: 0 | S52: 0 | T52: Revisar insumos | U52: SI | W52: SIN PAGO | X52: INSTAGRAM | Y52: 11
A53: 27833 | B53: 25283 | C53: 46080 | D53: CC 43513918 | E53: NANCY DEL SOCORRO SEPULVEDA MUÑOZ | F53: JURANY SANCHEZ | G53: PD0013 | H53: ALOPECIA GENERAL - PRODEEP | I53: PRODEEP - PROCEDIMIENTOS | J53: PROCEDIMIENTOS | K53: 59 PRODEEP | L53: 700000 | M53: 350000 | N53: 0 | O53: 0 | P53: 0 | Q53: 0 | R53: 350000 | S53: 350000 | T53: 0.5 | U53: SI | W53: SIN PAGO | X53: AMIG@ | Y53: 58
A54: 35766 | B54: 25286 | C54: 46073 | D54: CC 1037661680 | E54: MARIA CAMILA DEL RIO JARAMILLO | F54: LUISA HERNANDEZ TEJADA | G54: 890303 | H54: CONSULTA DE CONTROL O DE SEGUIMIENTO POR ESPECIALISTA EN DERMATOLOGÍA < 1 MES | I54: PROCE DERMA - PROCEDIMIENTOS | J54: PROCEDIMIENTOS | L54: 0 | M54: 0 | N54: 0 | O54: 0 | P54: 0 | Q54: 0 | R54: 0 | S54: 0 | T54: 0 | U54: SI | W54: SIN PAGO | X54: INSTAGRAM | Y54: 29
A55: 28441 | B55: 25300 | C55: 46074 | D55: CC 22237951 | E55: ROSA MARIA FLOREZ VASQUEZ | F55: LUISA HERNANDEZ TEJADA | G55: HP0001 | H55: HANDPICO - MELASMA COMPONENTE PIGMENTARIO - PASO 2/2 | I55: HANDPICO - PROCEDIMIENTOS | J55: PROCEDIMIENTOS | K55: 1034 HANDPICO | L55: 350000 | M55: 175000 | N55: 0 | O55: 0 | P55: 0 | Q55: 0 | R55: 175000 | S55: 175000 | T55: 0.5 | U55: SI | W55: SIN PAGO | X55: MEDICO | Y55: 56
A56: 28441 | B56: 25301 | C56: 46074 | D56: CC 22237951 | E56: ROSA MARIA FLOREZ VASQUEZ | F56: LUISA HERNANDEZ TEJADA | G56: IP0001 | H56: IPL PROCEDIMIENTOS POR ZONA | I56: IPL-SQ - PROCEDIMIENTOS | J56: PROCEDIMIENTOS | K56: 1034 HANDPICO | L56: 650000 | M56: 325000 | N56: 0 | O56: 0 | P56: 0 | Q56: 0 | R56: 325000 | S56: 325000 | T56: 0.5 | U56: SI | W56: SIN PAGO | X56: MEDICO | Y56: 56
A57: 34617 | B57: 25307 | C57: 46080 | D57: CC 1037598968 | E57: LADY YAMILEY BEDOYA CORREA | F57: LUISA HERNANDEZ TEJADA | G57: IP0001 | H57: IPL PROCEDIMIENTOS POR ZONA | I57: IPL-SQ - PROCEDIMIENTOS | J57: PROCEDIMIENTOS | K57: 1034 HANDPICO | L57: 350000 | M57: 175000 | N57: 0 | O57: 0 | P57: 0 | Q57: 0 | R57: 175000 | S57: 175000 | T57: 0.5 | U57: SI | W57: SIN PAGO | X57: FACEBOOK | Y57: 37
A58: 23325 | B58: 25317 | C58: 46074 | D58: CC 32296582 | E58: SALOME MARTINEZ | F58: JURANY SANCHEZ | G58: M00007 | H58: MESOTERAPIA CAPILAR | I58: MESOJECT - PROCEDIMIENTOS | J58: PROCEDIMIENTOS | L58: 500000 | M58: 250000 | N58: 0 | O58: 0 | P58: 0 | Q58: 0 | R58: 250000 | S58: 250000 | T58: Revisar insumos | U58: SI | W58: SIN PAGO | X58: MEDICO | Y58: 41
A59: 35795 | B59: 25329 | C59: 46077 | D59: CC 1035283285 | E59: CATALINA HIDALGO COSSIO | F59: JURANY SANCHEZ | G59: 890303 | H59: CONSULTA DE CONTROL - PROCEDIMIENTO | I59: CONSULTA CONTROL - CONSULTA | J59: CONSULTA | L59: 0 | M59: 0 | N59: 0 | O59: 0 | P59: 0 | Q59: 0 | R59: 0 | S59: 0 | T59: Revisar insumos | U59: SI | W59: SIN PAGO | X59: AMIG@ | Y59: 31
A60: 34410 | B60: 25346 | C60: 46080 | D60: CC 1036640623 | E60: LEIDY YULIANA MORALES MUÑOZ | F60: LUISA HERNANDEZ TEJADA | G60: N00001 | H60: NANOPORE CARA + PEELING (PROTOCOLO COMPLETO) | I60: NANOPORE - PROCEDIMIENTOS | J60: PROCEDIMIENTOS | K60: N/A NANOPORE | L60: 600000 | M60: 300000 | N60: 0 | O60: 0 | P60: 0 | Q60: 0 | R60: 300000 | S60: 300000 | T60: Revisar insumos | U60: SI | W60: SIN PAGO | X60: INSTAGRAM | Y60: 33
A61: 28087 | B61: 25354 | C61: 46074 | D61: CC 1037524873 | E61: SARA ISABEL ARROYAVE TABORDA | F61: LINDA ELIANA AROCA LONDOÑO | G61: DL0011 | H61: COMBO 7 (DEPILACIÓN ZONA MINI + MEDIANA) | I61: DEPILACION - COSMETOLOGÍA | J61: COSMETOLOGÍA | K61: 1050 DEPILACIÓN REMOVALL | L61: 132000 | M61: 21991.2 | N61: 0 | O61: 0 | P61: 0 | Q61: 0 | R61: 110008.8 | S61: 107368.8 | T61: 0.8134 | U61: SI | V61: 2026-01-24 11:14:00 | W61: NO | X61: AMIG@ | Y61: 31 | Z61: FE909
A62: 33357 | B62: 25357 | C62: 46074 | D62: TI 1033191452 | E62: SIMON FLOREZ | F62: LUISA HERNANDEZ TEJADA | G62: M00011 | H62: FOTOAGE | I62: FOTOAGE - PROCEDIMIENTOS | J62: PROCEDIMIENTOS | K62: A123 DISPOSITIVO FOTOAGE | L62: 200000 | M62: 100000 | N62: 0 | O62: 0 | P62: 0 | Q62: 0 | R62: 100000 | S62: 100000 | T62: Revisar insumos | U62: SI | W62: SIN PAGO | X62: AMIG@ | Y62: 14
A63: 28721 | B63: 25359 | C63: 46074 | D63: CC 1017166615 | E63: CAROL PULGARIN | F63: LUISA FERNANDA CORREA HERNANDEZ | G63: DL0001 | H63: DEPILACION ZONA PEQUEÑA (AXILAS, LINEA ALBA, MANOS) | I63: DEPILACION - COSMETOLOGÍA | J63: COSMETOLOGÍA | K63: 1050 DEPILACIÓN REMOVALL | L63: 0 | M63: 0 | N63: 0 | O63: 0 | P63: 0 | Q63: 0 | R63: 0 | S63: 0 | T63: 0 | U63: SI | W63: SIN PAGO | X63: AMIG@ | Y63: 37
A64: 28942 | B64: 25360 | C64: 46074 | D64: CC 1020485415 | E64: YULISA GONZALEZ GONZALEZ | F64: JURANY SANCHEZ | G64: PD0014 | H64: ALOPECIA ENTRADAS - PRODEEP | I64: PRODEEP - PROCEDIMIENTOS | J64: PROCEDIMIENTOS | K64: 59 PRODEEP | L64: 350000 | M64: 175000 | N64: 0 | O64: 0 | P64: 0 | Q64: 0 | R64: 175000 | S64: 175000 | T64: Revisar insumos | U64: SI | W64: SIN PAGO | X64: TIKTOK | Y64: 27
A65: 33700 | B65: 25368 | C65: 46081 | D65: CC 1128269024 | E65: SANDRA CRISTINA TORRES MORENO | F65: JURANY SANCHEZ | G65: IP0001 | H65: IPL PROCEDIMIENTOS POR ZONA | I65: IPL-SQ - PROCEDIMIENTOS | J65: PROCEDIMIENTOS | K65: 43 IPL-SQ | L65: 650000 | M65: 325000 | N65: 0 | O65: 0 | P65: 0 | Q65: 0 | R65: 325000 | S65: 325000 | T65: 0.5 | U65: SI | W65: SIN PAGO | X65: INSTAGRAM | Y65: 38
A66: 33993 | B66: 25375 | C66: 46074 | D66: CC 1059092034 | E66: JIMENA ARBELAEZ LOAIZA | F66: LUISA FERNANDA CORREA HERNANDEZ | G66: DL0003 | H66: DEPILACION ZONA GRANDE (PIERNAS, ESPALDA, MUSLOS, PECHO, ABDOMEN) | I66: DEPILACION - COSMETOLOGÍA | J66: COSMETOLOGÍA | K66: 1050 DEPILACIÓN REMOVALL | L66: 140000 | M66: 23800 | N66: 0 | O66: 0 | P66: 0 | Q66: 0 | R66: 116200 | S66: 116200 | T66: 0.83 | U66: SI | W66: SIN PAGO | X66: INSTAGRAM | Y66: 29
A67: 33993 | B67: 25376 | C67: 46074 | D67: CC 1059092034 | E67: JIMENA ARBELAEZ LOAIZA | F67: LUISA FERNANDA CORREA HERNANDEZ | G67: DL0001 | H67: DEPILACION ZONA PEQUEÑA (AXILAS, LINEA ALBA, MANOS) | I67: DEPILACION - COSMETOLOGÍA | J67: COSMETOLOGÍA | K67: 1050 DEPILACIÓN REMOVALL | L67: 60000 | M67: 10200 | N67: 0 | O67: 0 | P67: 0 | Q67: 0 | R67: 49800 | S67: 49800 | T67: 0.83 | U67: SI | W67: SIN PAGO | X67: INSTAGRAM | Y67: 29
A68: 35818 | B68: 25378 | C68: 46073 | D68: CC 1046275504 | E68: ERICK ROBERTO HERNANDEZ JULIO | F68: JURANY SANCHEZ | G68: 890303 | H68: CONSULTA DE CONTROL O DE SEGUIMIENTO POR ESPECIALISTA EN DERMATOLOGÍA < 1 MES | I68: PROCE DERMA - PROCEDIMIENTOS | J68: PROCEDIMIENTOS | L68: 0 | M68: 0 | N68: 0 | O68: 0 | P68: 0 | Q68: 0 | R68: 0 | S68: 0 | T68: 0 | U68: SI | W68: SIN PAGO | X68: INSTAGRAM | Y68: 39
A69: 35819 | B69: 25381 | C69: 46074 | D69: CC 1038358497 | E69: VIVIANA MARIA PINEDA HERNANDEZ | F69: JURANY SANCHEZ | G69: P00008 | H69: PEELING MELASMA MELINE | I69: PEELING - PROCEDIMIENTOS | J69: PROCEDIMIENTOS | L69: 0 | M69: 0 | N69: 0 | O69: 0 | P69: 0 | Q69: 0 | R69: 0 | S69: 0 | T69: Revisar insumos | U69: SI | W69: SIN PAGO | X69: INSTAGRAM | Y69: 38
A70: 21937 | B70: 25387 | C70: 46081 | D70: TI 1013460553 | E70: ISABELA DUQUE CARDONA | F70: LUISA FERNANDA CORREA HERNANDEZ | G70: DL0002 | H70: DEPILACION ZONA MEDIANA ( ROSTRO COMPLETO, BIKINI) | I70: DEPILACION - COSMETOLOGÍA | J70: COSMETOLOGÍA | K70: 1050 DEPILACIÓN REMOVALL | L70: 90000 | M70: 15300 | N70: 0 | O70: 0 | P70: 0 | Q70: 0 | R70: 74700 | S70: 74700 | T70: 0.83 | U70: SI | W70: SIN PAGO | X70: AMIG@ | Y70: 18
A71: 22718 | B71: 25388 | C71: 46081 | D71: CC 42730184 | E71: ADRIANA MARIA CARDONA ZAPATA | F71: LUISA FERNANDA CORREA HERNANDEZ | G71: DL0001 | H71: DEPILACION ZONA PEQUEÑA (AXILAS, LINEA ALBA, MANOS) | I71: DEPILACION - COSMETOLOGÍA | J71: COSMETOLOGÍA | K71: 1050 DEPILACIÓN REMOVALL | L71: 60000 | M71: 10200 | N71: 0 | O71: 0 | P71: 0 | Q71: 0 | R71: 49800 | S71: 49800 | T71: 0.83 | U71: SI | W71: SIN PAGO | X71: AMIG@ | Y71: 58
A72: 35820 | B72: 25390 | C72: 46080 | D72: CC 39288916 | E72: HEIDY PULIDO BARON | F72: LUISA HERNANDEZ TEJADA | G72: HP0012 | H72: HANDPICO HIPERPIGMENTACIONES | I72: HANDPICO - PROCEDIMIENTOS | J72: PROCEDIMIENTOS | L72: 700000 | M72: 350000 | N72: 0 | O72: 0 | P72: 0 | Q72: 0 | R72: 350000 | S72: 350000 | T72: 0.5 | U72: SI | W72: SIN PAGO | X72: AMIG@ | Y72: 40
A73: 31005 | B73: 25395 | C73: 46077 | D73: TI 1036451704 | E73: SAMUEL VILLADA JARAMILLO | F73: LINDA ELIANA AROCA LONDOÑO | G73: DL0002 | H73: DEPILACION ZONA MEDIANA ( ROSTRO COMPLETO, BIKINI) | I73: DEPILACION - COSMETOLOGÍA | J73: COSMETOLOGÍA | K73: 1050 DEPILACIÓN REMOVALL | L73: 90000 | M73: 15300 | N73: 0 | O73: 0 | P73: 0 | Q73: 0 | R73: 74700 | S73: 74700 | T73: 0.83 | U73: SI | W73: SIN PAGO | X73: AMIG@ | Y73: 18
A74: 31349 | B74: 25398 | C74: 46074 | D74: CC 43157831 | E74: GLADYS PAREJA CORREA | F74: JURANY SANCHEZ | G74: IP0001 | H74: IPL PROCEDIMIENTOS POR ZONA | I74: IPL-SQ - PROCEDIMIENTOS | J74: PROCEDIMIENTOS | K74: 43 IPL-SQ | L74: 350000 | M74: 175000 | N74: 0 | O74: 0 | P74: 0 | Q74: 0 | R74: 175000 | S74: 175000 | T74: 0.5 | U74: SI | W74: SIN PAGO | X74: INSTAGRAM | Y74: 46
A75: 31349 | B75: 25399 | C75: 46074 | D75: CC 43157831 | E75: GLADYS PAREJA CORREA | F75: JURANY SANCHEZ | G75: HP0001 | H75: HANDPICO - MELASMA COMPONENTE PIGMENTARIO - PASO 2/2 | I75: HANDPICO - PROCEDIMIENTOS | J75: PROCEDIMIENTOS | K75: 43 IPL-SQ | L75: 350000 | M75: 175000 | N75: 0 | O75: 0 | P75: 0 | Q75: 0 | R75: 175000 | S75: 175000 | T75: 0.5 | U75: SI | W75: SIN PAGO | X75: INSTAGRAM | Y75: 46
A76: 34145 | B76: 25424 | C76: 46079 | D76: CC 1017181777 | E76: MARIA FERNANDA CANO SALINAS | F76: LUISA HERNANDEZ TEJADA | G76: 861426 | H76: JALUPRO CLASIC | I76: INYECTABLES - PROCEDIMIENTOS | J76: PROCEDIMIENTOS | L76: 900000 | M76: 450000 | N76: 0 | O76: 0 | P76: 0 | Q76: 0 | R76: 450000 | S76: 450000 | T76: Revisar insumos | U76: SI | W76: SIN PAGO | X76: INSTAGRAM | Y76: 35
A77: 34145 | B77: 25425 | C77: 46079 | D77: CC 1017181777 | E77: MARIA FERNANDA CANO SALINAS | F77: LUISA HERNANDEZ TEJADA | G77: M00011 | H77: FOTOAGE | I77: FOTOAGE - PROCEDIMIENTOS | J77: PROCEDIMIENTOS | K77: A123 DISPOSITIVO FOTOAGE | L77: 650000 | M77: 325000 | N77: 0 | O77: 0 | P77: 0 | Q77: 0 | R77: 325000 | S77: 325000 | T77: Revisar insumos | U77: SI | W77: SIN PAGO | X77: INSTAGRAM | Y77: 35
A78: 34302 | B78: 25429 | C78: 46076 | D78: CC 43255508 | E78: MARCELA VANEGAS GONZALEZ | F78: JURANY SANCHEZ | G78: 861415 | H78: APLICACIÓN BIOESTIMULADOR SCULPTRA | I78: INYECTABLES - PROCEDIMIENTOS | J78: PROCEDIMIENTOS | L78: 2250000 | M78: 1125000 | N78: 0 | O78: 0 | P78: 0 | Q78: 0 | R78: 1125000 | S78: 1125000 | T78: Revisar insumos | U78: SI | W78: SIN PAGO | X78: AMIG@ | Y78: 44
A79: 35852 | B79: 25452 | C79: 46073 | D79: CC 35406371 | E79: DIANA LUCIA TORRES BONILIA | F79: DANIELA ASTAROT SALAZAR URIBE | G79: 890303 | H79: CONSULTA DE CONTROL O DE SEGUIMIENTO POR ESPECIALISTA EN DERMATOLOGÍA < 1 MES | I79: PROCE DERMA - PROCEDIMIENTOS | J79: PROCEDIMIENTOS | L79: 0 | M79: 0 | N79: 0 | O79: 0 | P79: 0 | Q79: 0 | R79: 0 | S79: 0 | T79: 0 | U79: SI | W79: SIN PAGO | X79: AMIG@ | Y79: 66
A80: 35864 | B80: 25469 | C80: 46076 | D80: CC 1000205150 | E80: MARIA CAMILA ACOSTA PRESIGA | F80: DAVID CHALARCA CANAS | G80: IP0001 | H80: IPL PROCEDIMIENTOS POR ZONA | I80: IPL-SQ - PROCEDIMIENTOS | J80: PROCEDIMIENTOS | L80: 650000 | M80: 325000 | N80: 0 | O80: 0 | P80: 0 | Q80: 0 | R80: 325000 | S80: 325000 | T80: Revisar insumos | U80: SI | W80: SIN PAGO | X80: INSTAGRAM | Y80: 22
A81: 35865 | B81: 25470 | C81: 46073 | D81: CC 1128386036 | E81: NATALIA ANDREA VERA CANO | F81: JURANY SANCHEZ | G81: 890242 | H81: CONSULTA DE PRIMERA VEZ POR MEDICINA ESPECIALIZADA -DERMATOL | I81: CONSULTA PRIMERA VEZ - CONSULTA | J81: CONSULTA | L81: 250000 | M81: 125000 | N81: 0 | O81: 0 | P81: 0 | Q81: 0 | R81: 125000 | S81: 125000 | T81: 0.5 | U81: SI | W81: SIN PAGO | X81: INSTAGRAM | Y81: 0
A82: 35157 | B82: 25483 | C82: 46080 | D82: CC 1040746157 | E82: CATHERINE ARRUBLA MEJIA | F82: DANIELA ASTAROT SALAZAR URIBE | G82: IP0001 | H82: IPL PROCEDIMIENTOS POR ZONA | I82: IPL-SQ - PROCEDIMIENTOS | J82: PROCEDIMIENTOS | K82: 43 IPL-SQ | L82: 650000 | M82: 325000 | N82: 0 | O82: 0 | P82: 0 | Q82: 0 | R82: 325000 | S82: 325000 | T82: Revisar insumos | U82: SI | W82: SIN PAGO | X82: INSTAGRAM | Y82: 32
A83: 35881 | B83: 25492 | C83: 46081 | D83: CC 1047972186 | E83: LEIDY YULIETH TORRES GARZON | F83: DANIELA ASTAROT SALAZAR URIBE | G83: 890303 | H83: CONSULTA DE CONTROL - PROCEDIMIENTO | I83: CONSULTA CONTROL - CONSULTA | J83: CONSULTA | L83: 0 | M83: 0 | N83: 0 | O83: 0 | P83: 0 | Q83: 0 | R83: 0 | S83: 0 | T83: Revisar insumos | U83: SI | W83: SIN PAGO | X83: PAGINA WEB | Y83: 28
A84: 33141 | B84: 25526 | C84: 46080 | D84: TI 1020118206 | E84: SUSANA RUIZ VILLA | F84: LUISA FERNANDA CORREA HERNANDEZ | G84: DL0004 | H84: COMBO 1 ( ZONA MINI+ ZONA PEQUEÑA) | I84: DEPILACION - COSMETOLOGÍA | J84: COSMETOLOGÍA | K84: 1050 DEPILACIÓN REMOVALL | L84: 100000 | M84: 17000 | N84: 0 | O84: 0 | P84: 0 | Q84: 0 | R84: 83000 | S84: 83000 | T84: Revisar insumos | U84: SI | W84: SIN PAGO | X84: PAGINA WEB | Y84: 15
A85: 29275 | B85: 25527 | C85: 46080 | D85: TI 1020118206 | E85: SUSANA RUIZ VILLA | F85: LUISA HERNANDEZ TEJADA | G85: M00011 | H85: FOTOAGE | I85: FOTOAGE - PROCEDIMIENTOS | J85: PROCEDIMIENTOS | K85: A123 DISPOSITIVO FOTOAGE | L85: 650000 | M85: 325000 | N85: 0 | O85: 0 | P85: 0 | Q85: 0 | R85: 325000 | S85: 325000 | T85: Revisar insumos | U85: SI | W85: SIN PAGO | X85: PAGINA WEB | Y85: 15
A86: 31210 | B86: 25528 | C86: 46080 | D86: CC 43578995 | E86: SOL ANGEL VILLA TORRES | F86: LUISA FERNANDA CORREA HERNANDEZ | G86: DL0013 | H86: COMBO 8 (ZONA PEQUEÑA + ZONA MEDIANA) | I86: DEPILACION - COSMETOLOGÍA | J86: COSMETOLOGÍA | L86: 140000 | M86: 2800 | N86: 0 | O86: 0 | P86: 0 | Q86: 0 | R86: 137200 | S86: 137200 | T86: Revisar insumos | U86: SI | W86: SIN PAGO | X86: VITRINA | Y86: 52
A87: 35786 | B87: 25550 | C87: 46080 | D87: CC 1000413796 | E87: SAMUEL RODRIGUEZ SEGURA | F87: DAVID CHALARCA CANAS | G87: CM0006 | H87: COLOR MAX TATUAJE PEQUEÑO 1- 5CM | I87: COLOR MAX - PROCEDIMIENTOS | J87: PROCEDIMIENTOS | K87: NA LÁSER COLOR MAX | L87: 0 | M87: 0 | N87: 0 | O87: 0 | P87: 0 | Q87: 0 | R87: 0 | S87: 0 | T87: 0 | U87: SI | W87: SIN PAGO | X87: MEDICO | Y87: 22
A88: 35920 | B88: 25552 | C88: 46078 | D88: CC 1017204937 | E88: MARIA CAMILA SANCHEZ ISAZA | F88: LUISA HERNANDEZ TEJADA | G88: 890303 | H88: CONSULTA DE CONTROL - PROCEDIMIENTO | I88: CONSULTA CONTROL - CONSULTA | J88: CONSULTA | L88: 0 | M88: 0 | N88: 0 | O88: 0 | P88: 0 | Q88: 0 | R88: 0 | S88: 0 | T88: Revisar insumos | U88: SI | W88: SIN PAGO | X88: INSTAGRAM | Y88: 33
A89: 35674 | B89: 25553 | C89: 46079 | D89: CC 32182874 | E89: LINA JANETH RAMIREZ BETANCUR | F89: LUISA FERNANDA CORREA HERNANDEZ | G89: DL0001 | H89: DEPILACION ZONA PEQUEÑA (AXILAS, LINEA ALBA, MANOS) | I89: DEPILACION - COSMETOLOGÍA | J89: COSMETOLOGÍA | K89: 1050 DEPILACIÓN REMOVALL | L89: 50000 | M89: 8360.6 | N89: 0 | O89: 0 | P89: 0 | Q89: 0 | R89: 41639.4 | S89: 40819.4 | T89: 0.816388 | U89: SI | V89: 2026-01-28 10:58:00 | W89: NO | X89: MEDICO | Y89: 43 | Z89: FE964
A90: 35921 | B90: 25559 | C90: 46078 | D90: CC 1017204937 | E90: MARIA CAMILA SANCHEZ ISAZA | F90: LINDA ELIANA AROCA LONDOÑO | G90: LF0002 | H90: LIMPIEZA FACIAL GOLD | I90: ESTÉTICA - PROCEDIMIENTOS | J90: PROCEDIMIENTOS | L90: 280000 | M90: 47600 | N90: 0 | O90: 0 | P90: 0 | Q90: 0 | R90: 232400 | S90: 232400 | T90: Revisar insumos | U90: SI | W90: SIN PAGO | X90: INSTAGRAM | Y90: 33
A91: 35928 | B91: 25572 | C91: 46080 | D91: CC 43633700 | E91: BIBIANA PATRICIA LOPERA | F91: LUISA HERNANDEZ TEJADA | G91: 890303 | H91: CONSULTA DE CONTROL - PROCEDIMIENTO | I91: CONSULTA CONTROL - CONSULTA | J91: CONSULTA | L91: 0 | M91: 0 | N91: 0 | O91: 0 | P91: 0 | Q91: 0 | R91: 0 | S91: 0 | T91: Revisar insumos | U91: SI | W91: SIN PAGO | X91: GOOGLE | Y91: 48
A92: 35963 | B92: 25639 | C92: 46080 | D92: CE 735291 | E92: ENRIQUE SEGURA | F92: LUISA HERNANDEZ TEJADA | G92: 890303 | H92: CONSULTA DE CONTROL - PROCEDIMIENTO | I92: CONSULTA CONTROL - CONSULTA | J92: CONSULTA | L92: 0 | M92: 0 | N92: 0 | O92: 0 | P92: 0 | Q92: 0 | R92: 0 | S92: 0 | T92: Revisar insumos | U92: SI | W92: SIN PAGO | X92: INSTAGRAM | Y92: 38
A93: 26298 | B93: 25650 | C93: 46079 | D93: CC 9730333 | E93: BLADIMIR JURADO GALLEGO | F93: JURANY SANCHEZ | G93: M00009 | H93: EXOSOMA CAPILAR NANOPORE | I93: MESOJECT - PROCEDIMIENTOS | J93: PROCEDIMIENTOS | L93: 0 | M93: 0 | N93: 0 | O93: 0 | P93: 0 | Q93: 0 | R93: 0 | S93: 0 | T93: Revisar insumos | U93: SI | W93: SIN PAGO | X93: AMIG@ | Y93: 47
A94: 35531 | B94: 25677 | C94: 46073 | D94: CC 1235243501 | E94: VIDALUZ CHIRINO FONTALVO | F94: LUISA HERNANDEZ TEJADA | G94: M00007 | H94: MESOTERAPIA CAPILAR | I94: MESOJECT - PROCEDIMIENTOS | J94: PROCEDIMIENTOS | L94: 500000 | M94: 250000 | N94: 0 | O94: 0 | P94: 0 | Q94: 0 | R94: 250000 | S94: 250000 | T94: Revisar insumos | U94: SI | W94: SIN PAGO | X94: INSTAGRAM | Y94: 35
A95: 35995 | B95: 25710 | C95: 46079 | D95: CC 32494275 | E95: GLORIA MARIA SALINAS | F95: LUISA HERNANDEZ TEJADA | G95: 890303 | H95: CONSULTA DE CONTROL O DE SEGUIMIENTO POR ESPECIALISTA EN DERMATOLOGÍA < 1 MES | I95: PROCE DERMA - PROCEDIMIENTOS | J95: PROCEDIMIENTOS | L95: 0 | M95: 0 | N95: 0 | O95: 0 | P95: 0 | Q95: 0 | R95: 0 | S95: 0 | T95: 0 | U95: SI | W95: SIN PAGO | X95: INSTAGRAM | Y95: 73
A96: 35999 | B96: 25716 | C96: 46074 | D96: CC 1146437519 | E96: ESTEFANY RODRIGUEZ BEDOYA | F96: JURANY SANCHEZ | G96: 890242 | H96: CONSULTA DE PRIMERA VEZ POR MEDICINA ESPECIALIZADA -DERMATOL | I96: CONSULTA PRIMERA VEZ - CONSULTA | J96: CONSULTA | L96: 250000 | M96: 125000 | N96: 0 | O96: 0 | P96: 0 | Q96: 0 | R96: 125000 | S96: 125000 | T96: 0.5 | U96: SI | W96: SIN PAGO | X96: AMIG@ | Y96: 0
A97: 36011 | B97: 25734 | C97: 46080 | D97: CC 71314102 | E97: GUILLERMO AICARDO MESA MARTINEZ | F97: LUISA HERNANDEZ TEJADA | G97: 890303 | H97: CONSULTA DE CONTROL - PROCEDIMIENTO | I97: CONSULTA CONTROL - CONSULTA | J97: CONSULTA | L97: 0 | M97: 0 | N97: 0 | O97: 0 | P97: 0 | Q97: 0 | R97: 0 | S97: 0 | T97: Revisar insumos | U97: SI | W97: SIN PAGO | X97: INSTAGRAM | Y97: 45
A98: 36013 | B98: 25737 | C98: 46080 | D98: CC 43782549 | E98: FRANCY GRACIANO | F98: DANIELA ASTAROT SALAZAR URIBE | G98: 890303 | H98: CONSULTA DE CONTROL - PROCEDIMIENTO | I98: CONSULTA CONTROL - CONSULTA | J98: CONSULTA | L98: 0 | M98: 0 | N98: 0 | O98: 0 | P98: 0 | Q98: 0 | R98: 0 | S98: 0 | T98: Revisar insumos | U98: SI | W98: SIN PAGO | X98: INSTAGRAM | Y98: 41
A99: 36014 | B99: 25738 | C99: 46080 | D99: CC 1036667662 | E99: YULIANA MONSALVE DURANGO | F99: DANIELA ASTAROT SALAZAR URIBE | G99: 890303 | H99: CONSULTA DE CONTROL O DE SEGUIMIENTO POR ESPECIALISTA EN DERMATOLOGÍA < 1 MES | I99: PROCE DERMA - PROCEDIMIENTOS | J99: PROCEDIMIENTOS | L99: 0 | M99: 0 | N99: 0 | O99: 0 | P99: 0 | Q99: 0 | R99: 0 | S99: 0 | T99: 0 | U99: SI | W99: SIN PAGO | X99: GOOGLE | Y99: 29
A100: 30177 | B100: 25748 | C100: 46073 | D100: TI 1011401929 | E100: SANTIAGO RESTREPO GARCIA | F100: LUISA HERNANDEZ TEJADA | G100: N00003 | H100: NANOPORE CICATRICES | I100: NANOPORE - PROCEDIMIENTOS | J100: PROCEDIMIENTOS | K100: N/A NANOPORE | L100: 700000 | M100: 350000 | N100: 0 | O100: 0 | P100: 0 | Q100: 0 | R100: 350000 | S100: 350000 | T100: Revisar insumos | U100: SI | W100: SIN PAGO | X100: INSTAGRAM | Y100: 15
...

Sheet INFO.RENTABILIDAD
A1: # Atención | B1: # Registro | C1: Fecha Realización | D1: Doc. Paciente | E1: Nombre Paciente | F1: Personal Atiende | G1: Códio Cups | H1: Cups | I1: Sub Categoria | J1: Categoria | K1: Dispositivo | L1: Vlr | M1: Costo Comisiones | N1: Costo Insumos | O1: Costo Bancario | P1: Costo Adicional | Q1: Rentabilidad Insumos | R1: Rentabilidad Equipos | S1: Rentabilidad Total | T1: Promedio Porcentaje | U1: Observaciones | V1: Fecha Facturación | W1: Pagado este mes | X1: Procedencia / Recomendacion | Y1: Edad del paciente | Z1: Numero Factura
A2: 34927 | B2: 23972 | C2: 46055 | D2: CC 21690208 | E2: ROSA AMELIA LOPEZ | F2: DAVID CHALARCA CANAS | G2: 890242 | H2: CONSULTA DE PRIMERA VEZ POR MEDICINA ESPECIALIZADA -DERMATOL | I2: CONSULTA PRIMERA VEZ | J2: CONSULTA | L2: 250000 | M2: 125000 | N2: 0 | O2: 0 | P2: 0 | Q2: 0 | R2: 0 | S2: 125000 | T2: 0.5 | V2: 2026-02-02 08:56:00 | W2: SI | X2: INSTAGRAM | Y2: 76 | Z2: FE13840 | AA2: COLOMBIA | AB2: 3108243083
A3: 35869 | B3: 25474 | C3: 46055 | D3: CC 1017200704 | E3: ANA MARIA GAVIRIA LONDOÑO | F3: LUISA HERNANDEZ TEJADA | G3: 890242 | H3: CONSULTA DE PRIMERA VEZ POR MEDICINA ESPECIALIZADA -DERMATOL | I3: CONSULTA PRIMERA VEZ | J3: CONSULTA | L3: 250000 | M3: 122500 | N3: 0 | O3: 5000 | P3: 0 | Q3: 0 | R3: 0 | S3: 122500 | T3: 0.49 | V3: 2026-02-02 08:57:00 | W3: SI | X3: AMIG@ | Y3: 33 | Z3: FE13841 | AA3: COLOMBIA | AB3: 3218495568
A4: 34445 | B4: 24779 | C4: 46055 | D4: CC 1037620729 | E4: ISMAEL ARROYAVE MARTINEZ | F4: DAVID CHALARCA CANAS | G4: 860101 | H4: BIOPSIA 1 LESION | I4: PROCE DERMA | J4: PROCEDIMIENTOS | L4: 550000 | M4: 173950 | N4: 9189 | O4: 11000 | P4: 180000 | Q4: 1911 | R4: 0 | S4: 175861 | T4: 0.31974727 | V4: 2026-02-02 08:41:00 | W4: SI | X4: INSTAGRAM | Y4: 33 | Z4: FE13839 | AA4: COLOMBIA | AB4: 3107464774
A5: 35859 | B5: 25461 | C5: 46055 | D5: CC 1152435193 | E5: LAURA PATRICIA JARAMILLO PEREIRA | F5: LUISA HERNANDEZ TEJADA | G5: 890242 | H5: CONSULTA DE PRIMERA VEZ POR MEDICINA ESPECIALIZADA -DERMATOL | I5: CONSULTA PRIMERA VEZ | J5: CONSULTA | L5: 250000 | M5: 122500 | N5: 0 | O5: 5000 | P5: 0 | Q5: 0 | R5: 0 | S5: 122500 | T5: 0.49 | V5: 2026-02-02 09:20:00 | W5: SI | X5: INSTAGRAM | Y5: 35 | Z5: FE13842 | AA5: COLOMBIA | AB5: 317 5735491
A6: 35960 | B6: 25631 | C6: 46055 | D6: CC 43111978 | E6: MARIA EDINIA VILLA QUINTERO | F6: DANIELA ASTAROT SALAZAR URIBE | G6: 890242 | H6: CONSULTA DE PRIMERA VEZ POR MEDICINA ESPECIALIZADA -DERMATOL | I6: CONSULTA PRIMERA VEZ | J6: CONSULTA | L6: 250000 | M6: 125000 | N6: 0 | O6: 0 | P6: 0 | Q6: 0 | R6: 0 | S6: 125000 | T6: 0.5 | V6: 2026-02-02 09:42:00 | W6: SI | X6: INSTAGRAM | Y6: 46 | Z6: FE13843 | AA6: COLOMBIA | AB6: 3103939698
A7: 35990 | B7: 25697 | C7: 46055 | D7: CC 1020738142 | E7: CAROLINA AYALA JARAMILLO | F7: JURANY SANCHEZ | G7: 890242 | H7: CONSULTA DE PRIMERA VEZ POR MEDICINA ESPECIALIZADA -DERMATOL | I7: CONSULTA PRIMERA VEZ | J7: CONSULTA | L7: 250000 | M7: 122500 | N7: 0 | O7: 5000 | P7: 0 | Q7: 0 | R7: 0 | S7: 122500 | T7: 0.49 | V7: 2026-02-02 09:56:00 | W7: SI | X7: MEDICO | Y7: 37 | Z7: FE13844 | AA7: COLOMBIA | AB7: 3176692683
A8: 35816 | B8: 25374 | C8: 46055 | D8: CC 32354027 | E8: LINA MARIA PELAEZ | F8: LUISA HERNANDEZ TEJADA | G8: 890242 | H8: CONSULTA DE PRIMERA VEZ POR MEDICINA ESPECIALIZADA -DERMATOL | I8: CONSULTA PRIMERA VEZ | J8: CONSULTA | L8: 170000 | M8: 83300 | N8: 0 | O8: 3400 | P8: 0 | Q8: 0 | R8: 0 | S8: 83300 | T8: 0.49 | V8: 2026-02-02 10:28:00 | W8: SI | X8: AMIG@ | Y8: 45 | Z8: FE13846 | AA8: COLOMBIA | AB8: 3146065700
A9: 36052 | B9: 25819 | C9: 46055 | D9: PA A36782304 | E9: ARMONTE EVERETT BUTLER | F9: JURANY SANCHEZ | G9: 890242 | H9: CONSULTA DE PRIMERA VEZ POR MEDICINA ESPECIALIZADA -DERMATOL | I9: CONSULTA PRIMERA VEZ | J9: CONSULTA | L9: 250000 | M9: 122500 | N9: 0 | O9: 5000 | P9: 0 | Q9: 0 | R9: 0 | S9: 122500 | T9: 0.49 | V9: 2026-02-02 14:03:00 | W9: SI | X9: DOCTORALIA | Y9: 30 | Z9: FE13859 | AA9: ESTADOS UNIDOS | AB9: 12027166330
A10: 36012 | B10: 25736 | C10: 46055 | D10: CC 1152455748 | E10: JULIANA VALLEJO JIMENEZ | F10: PAULA ANDREA ARISTIZABAL DIAZ | G10: 890242 | H10: CONSULTA DE PRIMERA VEZ POR MEDICINA ESPECIALIZADA -DERMATOL | I10: CONSULTA PRIMERA VEZ | J10: CONSULTA | L10: 250000 | M10: 122500 | N10: 0 | O10: 5000 | P10: 0 | Q10: 0 | R10: 0 | S10: 122500 | T10: 0.49 | V10: 2026-02-02 13:42:00 | W10: SI | X10: GOOGLE | Y10: 30 | Z10: FE13856 | AA10: COLOMBIA | AB10: 3235223348
A11: 36028 | B11: 25776 | C11: 46055 | D11: CC 1025889338 | E11: SAMANTHA LANIADO GARCIA | F11: JURANY SANCHEZ | G11: 890302 | H11: CONSULTA DE CONTROL O DE SEGUIMIENTO POR MEDICINA ESPECIALIZADA > 1 MES | I11: CONSULTA CONTROL | J11: CONSULTA | L11: 180000 | M11: 88200 | N11: 0 | O11: 3600 | P11: 0 | Q11: 0 | R11: 0 | S11: 88200 | T11: 0.49 | V11: 2026-02-02 13:22:00 | W11: SI | X11: INSTAGRAM | Y11: 19 | Z11: FE13851 | AA11: COLOMBIA | AB11: 3217511369
A12: 36000 | B12: 25718 | C12: 46055 | D12: CC 41686251 | E12: LUZ STELLA CONTRERAS JAIMES | F12: DANIELA ASTAROT SALAZAR URIBE | G12: 890242 | H12: CONSULTA DE PRIMERA VEZ POR MEDICINA ESPECIALIZADA -DERMATOL | I12: CONSULTA PRIMERA VEZ | J12: CONSULTA | L12: 250000 | M12: 122500 | N12: 0 | O12: 5000 | P12: 0 | Q12: 0 | R12: 0 | S12: 122500 | T12: 0.49 | V12: 2026-02-02 13:33:00 | W12: SI | X12: INSTAGRAM | Y12: 67 | Z12: FE13854 | AA12: COLOMBIA | AB12: 4042188771
A13: 36001 | B13: 25721 | C13: 46055 | D13: PA X7881648 | E13: SHAYAN KHAJEHNOURI | F13: JURANY SANCHEZ | G13: 890242 | H13: CONSULTA DE PRIMERA VEZ POR MEDICINA ESPECIALIZADA -DERMATOL | I13: CONSULTA PRIMERA VEZ | J13: CONSULTA | L13: 250000 | M13: 122500 | N13: 0 | O13: 5000 | P13: 0 | Q13: 0 | R13: 0 | S13: 122500 | T13: 0.49 | V13: 2026-02-02 14:08:00 | W13: SI | X13: DOCTORALIA | Y13: 25 | Z13: FE13860 | AA13: SUIZA | AB13: 41791540512
A14: 34589 | B14: 23461 | C14: 46055 | D14: CC 1128444869 | E14: ADRIAN ANDRES RAMIREZ | F14: PAULA ANDREA ARISTIZABAL DIAZ | G14: 890302 | H14: CONSULTA DE CONTROL O DE SEGUIMIENTO POR MEDICINA ESPECIALIZADA > 1 MES | I14: CONSULTA CONTROL | J14: CONSULTA | L14: 180000 | M14: 90000 | N14: 0 | O14: 0 | P14: 0 | Q14: 0 | R14: 0 | S14: 90000 | T14: 0.5 | V14: 2026-02-02 11:28:00 | W14: SI | X14: AMIG@ | Y14: 38 | Z14: FE13847 | AA14: COLOMBIA | AB14: 3117783365
A15: 35512 | B15: 24840 | C15: 46055 | D15: PPT 6859027 | E15: YEMMIRET BEATRIZ CORTEZ GONZALEZ | F15: PAULA ANDREA ARISTIZABAL DIAZ | G15: 890303 | H15: CONSULTA DE CONTROL - PROCEDIMIENTO | I15: CONSULTA CONTROL | J15: CONSULTA | L15: 0 | M15: 0 | N15: 0 | O15: 0 | P15: 0 | Q15: 0 | R15: 0 | S15: 0 | T15: 0 | W15: SIN PAGO | X15: INSTAGRAM | Y15: 22 | AA15: VENEZUELA | AB15: 3043238624
A16: 35966 | B16: 25645 | C16: 46055 | D16: CC 1003308616 | E16: JIMENA FUENTES | F16: LUISA HERNANDEZ TEJADA | G16: 890242 | H16: CONSULTA DE PRIMERA VEZ POR MEDICINA ESPECIALIZADA -DERMATOL | I16: CONSULTA PRIMERA VEZ | J16: CONSULTA | L16: 250000 | M16: 122500 | N16: 0 | O16: 5000 | P16: 0 | Q16: 0 | R16: 0 | S16: 122500 | T16: 0.49 | V16: 2026-02-02 13:27:00 | W16: SI | X16: GOOGLE | Y16: 24 | Z16: FE13853 | AA16: COLOMBIA | AB16: 3212808037
A17: 36051 | B17: 25818 | C17: 46055 | D17: CC 1020738142 | E17: CAROLINA AYALA JARAMILLO | F17: JURANY SANCHEZ | G17: LP0003 | H17: TELANGIECTASIAS FACIALES 6-10 - LONGPULSE | I17: LONGPULSE | J17: PROCEDIMIENTOS | K17: LONGPULSE | L17: 800000 | M17: 392000 | N17: 0 | O17: 16000 | P17: 0 | Q17: 0 | R17: 0 | S17: 392000 | T17: 0.49 | V17: 2026-02-02 13:00:00 | W17: SI | X17: MEDICO | Y17: 37 | Z17: FE13848 | AA17: COLOMBIA | AB17: 3176692683
A18: 35497 | B18: 25172 | C18: 46055 | D18: PA A00817909 | E18: LUIS GABRIEL RIVERA MENDOZA | F18: PAULA ANDREA ARISTIZABAL DIAZ | G18: 868116 | H18: SUBCISION | I18: PROCE DERMA | J18: PROCEDIMIENTOS | L18: 200000 | M18: 89615 | N18: 14583 | O18: 4000 | P18: 0 | Q18: 2187 | R18: 0 | S18: 91802 | T18: 0.45901 | V18: 2026-01-21 13:45:00 | W18: NO | X18: INSTAGRAM | Y18: 44 | Z18: FE13574 | AA18: PUERTO RICO | AB18: 17879105036
A19: 35996 | B19: 25713 | C19: 46055 | D19: CC 38234538 | E19: BEATRIZ EUGENIA VALLEJO CADAVID | F19: DAVID CHALARCA CANAS | G19: 890242 | H19: CONSULTA DE PRIMERA VEZ POR MEDICINA ESPECIALIZADA -DERMATOL | I19: CONSULTA PRIMERA VEZ | J19: CONSULTA | L19: 250000 | M19: 122500 | N19: 0 | O19: 5000 | P19: 0 | Q19: 0 | R19: 0 | S19: 122500 | T19: 0.49 | V19: 2026-02-02 14:12:00 | W19: SI | X19: PAGINA WEB | Y19: 71 | Z19: FE13862 | AA19: COLOMBIA | AB19: 3053325374
A20: 35993 | B20: 25701 | C20: 46055 | D20: TI 1026002032 | E20: STIVEN RAMIREZ MARTINEZ | F20: DAVID CHALARCA CANAS | G20: 890302 | H20: CONSULTA DE CONTROL O DE SEGUIMIENTO POR MEDICINA ESPECIALIZADA > 1 MES | I20: CONSULTA CONTROL | J20: CONSULTA | L20: 180000 | M20: 88200 | N20: 0 | O20: 3600 | P20: 0 | Q20: 0 | R20: 0 | S20: 88200 | T20: 0.49 | V20: 2026-02-02 14:11:00 | W20: SI | X20: MEDICO | Y20: 15 | Z20: FE13861 | AA20: COLOMBIA | AB20: 3107482914
A21: 36058 | B21: 25830 | C21: 46055 | D21: CC 41686251 | E21: LUZ STELLA CONTRERAS JAIMES | F21: DANIELA ASTAROT SALAZAR URIBE | G21: LC0008 | H21: CO2 FULGURACION 1- 5 LESIONES MENORES 0.5 CM | I21: LASER IBLAZE (CO2) | J21: PROCEDIMIENTOS | K21: LÁSER IBLAZE (CO2) | L21: 450000 | M21: 220500 | N21: 0 | O21: 9000 | P21: 0 | Q21: 0 | R21: 0 | S21: 220500 | T21: 0.49 | V21: 2026-02-02 13:36:00 | W21: SI | X21: INSTAGRAM | Y21: 67 | Z21: FE13855 | AA21: COLOMBIA | AB21: 4042188771
A22: 35634 | B22: 25846 | C22: 46055 | D22: PA 7615390 | E22: DARIO FARINELLI | F22: DANIELA ASTAROT SALAZAR URIBE | G22: LC0008 | H22: CO2 FULGURACION 1- 5 LESIONES MENORES 0.5 CM | I22: LASER IBLAZE (CO2) | J22: PROCEDIMIENTOS | K22: LÁSER IBLAZE (CO2) | L22: 0 | M22: 0 | N22: 0 | O22: 0 | P22: 0 | Q22: 0 | R22: 0 | S22: 0 | T22: 0 | W22: SIN PAGO | X22: INSTAGRAM | Y22: 42 | AA22: AUSTRALIA | AB22: 61434263261
A23: 35959 | B23: 25821 | C23: 46055 | D23: CC 1036397369 | E23: ESTEFANIA GARCIA OSORIO | F23: DANIELA ASTAROT SALAZAR URIBE | G23: 861401 | H23: INFILTRACION INTRALESIONAL 1-5 LESIONES | I23: PROCE DERMA | J23: PROCEDIMIENTOS | L23: 300000 | M23: 147000 | N23: 0 | O23: 6000 | P23: 0 | Q23: 0 | R23: 0 | S23: 147000 | T23: 0.49 | V23: 2026-02-02 13:15:00 | W23: SI | X23: GOOGLE | Y23: 33 | Z23: FE13849 | AA23: COLOMBIA | AB23: 3007685166
A24: 35959 | B24: 25630 | C24: 46055 | D24: CC 1036397369 | E24: ESTEFANIA GARCIA OSORIO | F24: DANIELA ASTAROT SALAZAR URIBE | G24: PD0009 | H24: CICATRICES POST QUIRURGICAS 6-10 CMS - PRODEEP | I24: PRODEEP | J24: PROCEDIMIENTOS | K24: PRODEEP | L24: 600000 | M24: 294000 | N24: 0 | O24: 12000 | P24: 0 | Q24: 0 | R24: 0 | S24: 294000 | T24: 0.49 | V24: 2026-02-02 13:15:00 | W24: SI | X24: GOOGLE | Y24: 33 | Z24: FE13850 | AA24: COLOMBIA | AB24: 3007685166
A25: 36058 | B25: 25829 | C25: 46055 | D25: CC 41686251 | E25: LUZ STELLA CONTRERAS JAIMES | F25: DANIELA ASTAROT SALAZAR URIBE | G25: LP0009 | H25: LAGO VENOSO - LONGPULSE | I25: LONGPULSE | J25: PROCEDIMIENTOS | K25: LONGPULSE | L25: 1000000 | M25: 490000 | N25: 0 | O25: 20000 | P25: 0 | Q25: 0 | R25: 0 | S25: 490000 | T25: 0.49 | V25: 2026-02-02 13:36:00 | W25: SI | X25: INSTAGRAM | Y25: 67 | Z25: FE13855 | AA25: COLOMBIA | AB25: 4042188771
A26: 36058 | B26: 25828 | C26: 46055 | D26: CC 41686251 | E26: LUZ STELLA CONTRERAS JAIMES | F26: DANIELA ASTAROT SALAZAR URIBE | G26: P00008 | H26: PEELING MELASMA MELINE | I26: PEELING | J26: PROCEDIMIENTOS | L26: 1000000 | M26: 403300 | N26: 133120.58 | O26: 20000 | P26: 0 | Q26: 40279.42 | R26: 0 | S26: 443579.42 | T26: 0.44357942 | V26: 2026-02-02 13:36:00 | W26: SI | X26: INSTAGRAM | Y26: 67 | Z26: FE13855 | AA26: COLOMBIA | AB26: 4042188771
A27: 36058 | B27: 25835 | C27: 46055 | D27: CC 41686251 | E27: LUZ STELLA CONTRERAS JAIMES | F27: DANIELA ASTAROT SALAZAR URIBE | G27: P00008 | H27: PEELING MELASMA MELINE | I27: PEELING | J27: PROCEDIMIENTOS | L27: 1800000 | M27: 501183 | N27: 633069.55 | O27: 36000 | P27: 0 | Q27: 128564.45 | R27: 0 | S27: 629747.45 | T27: 0.34985969 | V27: 2026-02-02 13:36:00 | W27: SI | X27: INSTAGRAM | Y27: 67 | Z27: FE13855 | AA27: COLOMBIA | AB27: 4042188771
A28: 35497 | B28: 25407 | C28: 46055 | D28: PA A00817909 | E28: LUIS GABRIEL RIVERA MENDOZA | F28: PAULA ANDREA ARISTIZABAL DIAZ | G28: LC0001 | H28: CO2 CICATRICES ACNE CARA | I28: LASER Co2 | J28: PROCEDIMIENTOS | K28: LÁSER IBLAZE (CO2) | L28: 1000000 | M28: 490000 | N28: 0 | O28: 20000 | P28: 0 | Q28: 0 | R28: 0 | S28: 490000 | T28: 0.49 | V28: 2026-02-02 14:01:00 | W28: SI | X28: INSTAGRAM | Y28: 44 | Z28: FE13858 | AA28: PUERTO RICO | AB28: 17879105036
A29: 35497 | B29: 25831 | C29: 46055 | D29: PA A00817909 | E29: LUIS GABRIEL RIVERA MENDOZA | F29: PAULA ANDREA ARISTIZABAL DIAZ | G29: M00011 | H29: FOTOAGE | I29: FOTOAGE | J29: PROCEDIMIENTOS | K29: DISPOSITIVO FOTOAGE | L29: 0 | M29: 0 | N29: 0 | O29: 0 | P29: 0 | Q29: 0 | R29: 0 | S29: 0 | T29: 0 | W29: SIN PAGO | X29: INSTAGRAM | Y29: 44 | AA29: PUERTO RICO | AB29: 17879105036
A30: 35939 | B30: 25595 | C30: 46055 | D30: CC 1090488619 | E30: KAREN ANDREA PEREZ SARAVIA | F30: DAVID CHALARCA CANAS | G30: 890242 | H30: CONSULTA DE PRIMERA VEZ POR MEDICINA ESPECIALIZADA -DERMATOL | I30: CONSULTA PRIMERA VEZ | J30: CONSULTA | L30: 250000 | M30: 122500 | N30: 0 | O30: 5000 | P30: 0 | Q30: 0 | R30: 0 | S30: 122500 | T30: 0.49 | V30: 2026-02-02 14:35:00 | W30: SI | X30: INSTAGRAM | Y30: 30 | Z30: FE13865 | AA30: COLOMBIA | AB30: 3023521130
A31: 35854 | B31: 25854 | C31: 46055 | D31: CC 1000644075 | E31: LUISA FERNANDA CORREA HERNANDEZ | F31: JURANY SANCHEZ | G31: LP0002 | H31: TELANGIECTASIAS FACIALES 1-5 - LONGPULSE | I31: LONGPULSE | J31: PROCEDIMIENTOS | K31: LONGPULSE | L31: 0 | M31: 0 | N31: 0 | O31: 0 | P31: 0 | Q31: 0 | R31: 0 | S31: 0 | T31: 0 | W31: SIN PAGO | X31: MEDICO | Y31: 24 | AA31: COLOMBIA | AB31: 3162859884
A32: 36053 | B32: 25820 | C32: 46055 | D32: CC 79054647 | E32: MAURICIO TORRES RINCON | F32: DAVID CHALARCA CANAS | G32: 863101 | H32: CRIOTERAPIA 1-5 LESIONES | I32: PROCE DERMA | J32: PROCEDIMIENTOS | L32: 350000 | M32: 172000 | N32: 0 | O32: 6000 | P32: 0 | Q32: 0 | R32: 0 | S32: 172000 | T32: 0.49142857 | V32: 2026-02-02 15:51:00 | W32: SI | X32: GOOGLE | Y32: 56 | Z32: FE13867 | AA32: COLOMBIA | AB32: 3154920199
A33: 36075 | B33: 25859 | C33: 46055 | D33: CC 43021146 | E33: MARIA EDITH GOMEZ PALACIO | F33: DAVID CHALARCA CANAS | G33: 890242 | H33: CONSULTA DE PRIMERA VEZ POR MEDICINA ESPECIALIZADA -DERMATOL | I33: CONSULTA PRIMERA VEZ | J33: CONSULTA | L33: 200000 | M33: 98000 | N33: 0 | O33: 4000 | P33: 0 | Q33: 0 | R33: 0 | S33: 98000 | T33: 0.49 | V33: 2026-02-02 17:59:00 | W33: SI | X33: VITRINA | Y33: 71 | Z33: FE13874 | AA33: COLOMBIA | AB33: 3218306660
A34: 35947 | B34: 25609 | C34: 46055 | D34: CC 1036943258 | E34: CRISTIAN CAMILO BARRERA ARIAS | F34: JURANY SANCHEZ | G34: 890242 | H34: CONSULTA DE PRIMERA VEZ POR MEDICINA ESPECIALIZADA -DERMATOL | I34: CONSULTA PRIMERA VEZ | J34: CONSULTA | L34: 250000 | M34: 122500 | N34: 0 | O34: 5000 | P34: 0 | Q34: 0 | R34: 0 | S34: 122500 | T34: 0.49 | V34: 2026-02-02 17:03:00 | W34: SI | X34: GOOGLE | Y34: 33 | Z34: FE13870 | AA34: COLOMBIA | AB34: 3146570663
A35: 35708 | B35: 25646 | C35: 46055 | D35: CC 1037973105 | E35: JOHANA ANDREA QUENGUAN MARIN | F35: DANIELA ASTAROT SALAZAR URIBE | G35: 861416 | H35: APLICACIÓN BIOESTIMULADOR HARMONYCA | I35: INYECTABLES | J35: PROCEDIMIENTOS | L35: 4000000 | M35: 889840 | N35: 1615793 | O35: 80000 | P35: 0 | Q35: 524527 | R35: 0 | S35: 1414367 | T35: 0.35359175 | V35: 2026-02-02 14:46:00 | W35: SI | X35: GOOGLE | Y35: 37 | Z35: FE13866 | AA35: COLOMBIA | AB35: 3117114819
A36: 35708 | B36: 25647 | C36: 46055 | D36: CC 1037973105 | E36: JOHANA ANDREA QUENGUAN MARIN | F36: DANIELA ASTAROT SALAZAR URIBE | G36: 861411 | H36: APLICACIÓN TOXINA BOTULINICA | I36: INYECTABLES | J36: PROCEDIMIENTOS | L36: 0 | M36: 0 | N36: 0 | O36: 0 | P36: 0 | Q36: 0 | R36: 0 | S36: 0 | T36: 0 | W36: SIN PAGO | X36: GOOGLE | Y36: 37 | AA36: COLOMBIA | AB36: 3117114819
A37: 35120 | B37: 24223 | C37: 46055 | D37: CC 1007239177 | E37: SARA OQUENDO TORRES | F37: DAVID CHALARCA CANAS | G37: 890303 | H37: CONSULTA DE CONTROL O DE SEGUIMIENTO POR ESPECIALISTA EN DERMATOLOGÍA < 1 MES | I37: PROCE DERMA | J37: PROCEDIMIENTOS | L37: 0 | M37: 0 | N37: 0 | O37: 0 | P37: 0 | Q37: 0 | R37: 0 | S37: 0 | T37: 0 | W37: SIN PAGO | X37: INSTAGRAM | Y37: 25 | AA37: COLOMBIA | AB37: 3503348467
A38: 28241 | B38: 25869 | C38: 46055 | D38: CC 1035854913 | E38: JURANY SANCHEZ | F38: ISABELLA GONZALEZ MEJIA | G38: TM0002 | H38: TENSAMAX ZONA MEDIANA | I38: TENSAMAX | J38: COSMETOLOGÍA | K38: TENSAMAX | L38: 0 | M38: 0 | N38: 0 | O38: 0 | P38: 0 | Q38: 0 | R38: 0 | S38: 0 | T38: 0 | W38: SIN PAGO | X38: MEDICO | Y38: 36 | AA38: COLOMBIA | AB38: 3008249135
A39: 36031 | B39: 25781 | C39: 46055 | D39: TI 1035001139 | E39: VALERIA DELGADO COUTIN | F39: JURANY SANCHEZ | G39: 890242 | H39: CONSULTA DE PRIMERA VEZ POR MEDICINA ESPECIALIZADA -DERMATOL | I39: CONSULTA PRIMERA VEZ | J39: CONSULTA | L39: 250000 | M39: 125000 | N39: 0 | O39: 0 | P39: 0 | Q39: 0 | R39: 0 | S39: 125000 | T39: 0.5 | V39: 2026-02-02 16:56:00 | W39: SI | X39: INSTAGRAM | Y39: 13 | Z39: FE13868 | AA39: COLOMBIA | AB39: 3113894613
A40: 34985 | B40: 24219 | C40: 46055 | D40: CC 1001818423 | E40: YULISA MICHEL MARRIAGA DURAN | F40: LUISA HERNANDEZ TEJADA | G40: IP0001 | H40: IPL PROCEDIMIENTOS POR ZONA | I40: IPL-SQ | J40: PROCEDIMIENTOS | K40: IPL-SQ | L40: 650000 | M40: 318500 | N40: 0 | O40: 13000 | P40: 0 | Q40: 0 | R40: 0 | S40: 318500 | T40: 0.49 | V40: 2026-02-02 17:08:00 | W40: SI | X40: AMIG@ | Y40: 27 | Z40: FE13871 | AA40: COLOMBIA | AB40: 3122689563
A41: 36050 | B41: 25817 | C41: 46055 | D41: CC 1152435193 | E41: LAURA PATRICIA JARAMILLO PEREIRA | F41: LUISA HERNANDEZ TEJADA | G41: IP0001 | H41: IPL PROCEDIMIENTOS POR ZONA | I41: IPL-SQ | J41: PROCEDIMIENTOS | K41: IPL-SQ | L41: 650000 | M41: 318500 | N41: 0 | O41: 13000 | P41: 0 | Q41: 0 | R41: 0 | S41: 318500 | T41: 0.49 | V41: 2026-02-02 13:45:00 | W41: SI | X41: INSTAGRAM | Y41: 35 | Z41: FE13857 | AA41: COLOMBIA | AB41: 317 5735491
A42: 36055 | B42: 25826 | C42: 46055 | D42: CC 32354027 | E42: LINA MARIA PELAEZ | F42: LUISA HERNANDEZ TEJADA | G42: P00008 | H42: PEELING MELASMA MELINE | I42: PEELING | J42: PROCEDIMIENTOS | L42: 640000 | M42: 19483 | N42: 499953.07 | O42: 12800 | P42: 0 | Q42: 88280.93 | R42: 0 | S42: 107763.93 | T42: 0.16838114 | V42: 2026-02-02 13:26:00 | W42: SI | X42: AMIG@ | Y42: 45 | Z42: FE13852 | AA42: COLOMBIA | AB42: 3146065700
A43: 21286 | B43: 25845 | C43: 46055 | D43: CC 66864649 | E43: NORMA EUGENIA PELAEZ MUÑOZ | F43: LUISA HERNANDEZ TEJADA | G43: 861411 | H43: APLICACIÓN TOXINA BOTULINICA | I43: INYECTABLES | J43: PROCEDIMIENTOS | L43: 1077000 | M43: 338880 | N43: 266400 | O43: 21540 | P43: 0 | Q43: 111300 | R43: 0 | S43: 450180 | T43: 0.41799443 | V43: 2026-02-02 14:25:00 | W43: SI | X43: INSTAGRAM | Y43: 52 | Z43: FE13863 | AA43: COLOMBIA | AB43: 3155617242
A44: 21286 | B44: 25844 | C44: 46055 | D44: CC 66864649 | E44: NORMA EUGENIA PELAEZ MUÑOZ | F44: LUISA HERNANDEZ TEJADA | G44: JL1050 | H44: JALUPRO 2 EN 1 (PROTOCOLO) | I44: INYECTABLES | J44: PROCEDIMIENTOS | L44: 1650000 | M44: 429535 | N44: 590411.16 | O44: 33000 | P44: 0 | Q44: 167518.84 | R44: 0 | S44: 597053.84 | T44: 0.36185081 | V44: 2026-02-02 14:28:00 | W44: SI | X44: INSTAGRAM | Y44: 52 | Z44: FE13864 | AA44: COLOMBIA | AB44: 3155617242
A45: 26439 | B45: 10577 | C45: 46055 | D45: CC 52430253 | E45: GLADIS DEL CARMEN MARIN AMAYA | F45: LUISA HERNANDEZ TEJADA | G45: 890242 | H45: CONSULTA DE PRIMERA VEZ POR MEDICINA ESPECIALIZADA -DERMATOL | I45: CONSULTA PRIMERA VEZ | J45: CONSULTA | L45: 250000 | M45: 125000 | N45: 0 | O45: 0 | P45: 0 | Q45: 0 | R45: 0 | S45: 125000 | T45: 0.5 | V45: 2026-02-02 10:19:00 | W45: SI | X45: DOCTORALIA | Y45: 47 | Z45: FE13845 | AA45: COLOMBIA | AB45: 3182964679
A46: 36081 | B46: 25866 | C46: 46055 | D46: CC 1003431299 | E46: ANGIE RAMOS HERNANDEZ | F46: JURANY SANCHEZ | G46: M00007 | H46: MESOTERAPIA CAPILAR | I46: MESOJECT | J46: PROCEDIMIENTOS | L46: 0 | M46: 0 | N46: 0 | O46: 0 | P46: 0 | Q46: 0 | R46: 0 | S46: 0 | T46: 0 | W46: SIN PAGO | X46: MEDICO | Y46: 25 | AA46: COLOMBIA | AB46: 3143055337
A47: 35892 | B47: 25508 | C47: 46055 | D47: TI 1020452087 | E47: EMMANUEL LOPEZ CASTAÑEDA | F47: DAVID CHALARCA CANAS | G47: M00011 | H47: FOTOAGE | I47: FOTOAGE | J47: PROCEDIMIENTOS | K47: DISPOSITIVO FOTOAGE | L47: 650000 | M47: 286300 | N47: 67284.68 | O47: 0 | P47: 0 | Q47: 10115.32 | R47: 0 | S47: 296415.32 | T47: 0.45602357 | V47: 2026-02-02 17:02:00 | W47: SI | X47: INSTAGRAM | Y47: 15 | Z47: FE13869 | AA47: COLOMBIA | AB47: 3011196577
A48: 36069 | B48: 25851 | C48: 46055 | D48: CC 19313440 | E48: JOSE OSWALDO CARDONA RODRIGUEZ | F48: JURANY SANCHEZ | G48: 890242 | H48: CONSULTA DE PRIMERA VEZ POR MEDICINA ESPECIALIZADA -DERMATOL | I48: CONSULTA PRIMERA VEZ | J48: CONSULTA | L48: 250000 | M48: 122500 | N48: 0 | O48: 5000 | P48: 0 | Q48: 0 | R48: 0 | S48: 122500 | T48: 0.49 | V48: 2026-02-02 17:57:00 | W48: SI | X48: AMIG@ | Y48: 68 | Z48: FE13873 | AA48: COLOMBIA | AB48: 3177662672
A49: 35835 | B49: 25416 | C49: 46055 | D49: TI 1035979001 | E49: MARIANA GALVIS AGUDELO | F49: PAULA ANDREA ARISTIZABAL DIAZ | G49: 890242 | H49: CONSULTA DE PRIMERA VEZ POR MEDICINA ESPECIALIZADA -DERMATOL | I49: CONSULTA PRIMERA VEZ | J49: CONSULTA | L49: 250000 | M49: 122500 | N49: 0 | O49: 5000 | P49: 0 | Q49: 0 | R49: 0 | S49: 122500 | T49: 0.49 | V49: 2026-02-02 17:49:00 | W49: SI | X49: FACEBOOK | Y49: 15 | Z49: FE13872 | AA49: COLOMBIA | AB49: 3012131391
A50: 33850 | B50: 25878 | C50: 46055 | D50: CC 1037663200 | E50: PAULA ANDREA ARISTIZABAL DIAZ | F50: DAVID CHALARCA CANAS | G50: CM0012 | H50: COLOR MAX LENTIGOS EFELIDES O PECAS 1- 30 LESIONES | I50: COLOR MAX | J50: PROCEDIMIENTOS | K50: LÁSER COLOR MAX | L50: 0 | M50: 0 | N50: 0 | O50: 0 | P50: 0 | Q50: 0 | R50: 0 | S50: 0 | T50: 0 | W50: SIN PAGO | X50: AMIG@ | Y50: 27 | AA50: COLOMBIA | AB50: 3106069476
A51: 35708 | B51: 25849 | C51: 46055 | D51: CC 1037973105 | E51: JOHANA ANDREA QUENGUAN MARIN | F51: DANIELA ASTAROT SALAZAR URIBE | G51: CM0012 | H51: COLOR MAX LENTIGOS EFELIDES O PECAS 1- 30 LESIONES | I51: COLOR MAX | J51: PROCEDIMIENTOS | K51: LÁSER COLOR MAX | L51: 0 | M51: 0 | N51: 0 | O51: 0 | P51: 0 | Q51: 0 | R51: 0 | S51: 0 | T51: 0 | W51: SIN PAGO | X51: GOOGLE | Y51: 37 | AA51: COLOMBIA | AB51: 3117114819
A52: 35708 | B52: 25850 | C52: 46055 | D52: CC 1037973105 | E52: JOHANA ANDREA QUENGUAN MARIN | F52: DANIELA ASTAROT SALAZAR URIBE | G52: LC0010 | H52: CO2 FULGURACIONES > 10 LESIONES (CARA, CUELLO O CORPORAL) | I52: LASER Co2 | J52: PROCEDIMIENTOS | K52: LÁSER IBLAZE (CO2) | L52: 0 | M52: 0 | N52: 0 | O52: 0 | P52: 0 | Q52: 0 | R52: 0 | S52: 0 | T52: 0 | W52: SIN PAGO | X52: GOOGLE | Y52: 37 | AA52: COLOMBIA | AB52: 3117114819
A53: 36047 | B53: 25811 | C53: 46056 | D53: CC 66678223 | E53: JHENNY LANCHEROS HERNANDEZ | F53: PAULA ANDREA ARISTIZABAL DIAZ | G53: 890242 | H53: CONSULTA DE PRIMERA VEZ POR MEDICINA ESPECIALIZADA -DERMATOL | I53: CONSULTA PRIMERA VEZ | J53: CONSULTA | L53: 250000 | M53: 122500 | N53: 0 | O53: 5000 | P53: 0 | Q53: 0 | R53: 0 | S53: 122500 | T53: 0.49 | V53: 2026-02-03 12:01:00 | W53: SI | X53: AMIG@ | Y53: 56 | Z53: FE13881 | AA53: COLOMBIA | AB53: 3163034459
A54: 34323 | B54: 25477 | C54: 46056 | D54: CC 1041177249 | E54: SONIA IDALID URREGO USUGA | F54: DAVID CHALARCA CANAS | G54: IP0001 | H54: IPL PROCEDIMIENTOS POR ZONA | I54: IPL-SQ | J54: PROCEDIMIENTOS | K54: IPL-SQ | L54: 650000 | M54: 325000 | N54: 0 | O54: 0 | P54: 0 | Q54: 0 | R54: 0 | S54: 325000 | T54: 0.5 | V54: 2026-02-03 10:23:00 | W54: SI | X54: INSTAGRAM | Y54: 28 | Z54: FE13876 | AA54: COLOMBIA | AB54: 3136379158
A55: 34323 | B55: 25895 | C55: 46056 | D55: CC 1041177249 | E55: SONIA IDALID URREGO USUGA | F55: DAVID CHALARCA CANAS | G55: 861401 | H55: INFILTRACION INTRALESIONAL 1-5 LESIONES | I55: PROCE DERMA | J55: PROCEDIMIENTOS | L55: 0 | M55: 0 | N55: 0 | O55: 0 | P55: 0 | Q55: 0 | R55: 0 | S55: 0 | T55: 0 | W55: SIN PAGO | X55: INSTAGRAM | Y55: 28 | AA55: COLOMBIA | AB55: 3136379158
A56: 34654 | B56: 23552 | C56: 46056 | D56: CC 1070975009 | E56: MARIA ALEJANDRA GARCIA GUTIERREZ | F56: PAULA ANDREA ARISTIZABAL DIAZ | G56: 890302 | H56: CONSULTA DE CONTROL O DE SEGUIMIENTO POR MEDICINA ESPECIALIZADA > 1 MES | I56: CONSULTA CONTROL | J56: CONSULTA | L56: 180000 | M56: 88200 | N56: 0 | O56: 3600 | P56: 0 | Q56: 0 | R56: 0 | S56: 88200 | T56: 0.49 | V56: 2026-02-03 10:50:00 | W56: SI | X56: INSTAGRAM | Y56: 30 | Z56: FE13877 | AA56: COLOMBIA | AB56: 3192828156
A57: 35386 | B57: 24998 | C57: 46056 | D57: CC 43413186 | E57: ADRIANA LUCIA ORTIZ MONTOYA | F57: PAULA ANDREA ARISTIZABAL DIAZ | G57: LC0008 | H57: CO2 FULGURACION 1- 5 LESIONES MENORES 0.5 CM | I57: LASER IBLAZE (CO2) | J57: PROCEDIMIENTOS | K57: IPL-SQ | L57: 0 | M57: 0 | N57: 0 | O57: 0 | P57: 0 | Q57: 0 | R57: 0 | S57: 0 | T57: 0 | W57: SIN PAGO | X57: GOOGLE | Y57: 54 | AA57: COLOMBIA | AB57: 319 3226280
A58: 36104 | B58: 25896 | C58: 46056 | D58: CC 66678223 | E58: JHENNY LANCHEROS HERNANDEZ | F58: PAULA ANDREA ARISTIZABAL DIAZ | G58: CM0012 | H58: COLOR MAX LENTIGOS EFELIDES O PECAS 1- 30 LESIONES | I58: COLOR MAX | J58: PROCEDIMIENTOS | K58: LÁSER COLOR MAX | L58: 200000 | M58: 98000 | N58: 0 | O58: 4000 | P58: 0 | Q58: 0 | R58: 0 | S58: 98000 | T58: 0.49 | V58: 2026-02-03 12:03:00 | W58: SI | X58: AMIG@ | Y58: 56 | Z58: FE13882 | AA58: COLOMBIA | AB58: 3163034459
A59: 34338 | B59: 24427 | C59: 46056 | D59: CC 1032250032 | E59: DEIBIN DAVID PATERNINA MONTOYA | F59: PAULA ANDREA ARISTIZABAL DIAZ | G59: CM0012 | H59: COLOR MAX LENTIGOS EFELIDES O PECAS 1- 30 LESIONES | I59: COLOR MAX | J59: PROCEDIMIENTOS | K59: LÁSER COLOR MAX | L59: 450000 | M59: 225000 | N59: 0 | O59: 0 | P59: 0 | Q59: 0 | R59: 0 | S59: 225000 | T59: 0.5 | V59: 2026-02-03 11:30:00 | W59: SI | X59: INSTAGRAM | Y59: 20 | Z59: FE13878 | AA59: COLOMBIA | AB59: 3102387803
A60: 36097 | B60: 25887 | C60: 46056 | D60: CC 1152219225 | E60: VICTOR MANUEL VANEGAS BUITRAGO | F60: DANIELA ASTAROT SALAZAR URIBE | G60: 890242 | H60: CONSULTA DE PRIMERA VEZ POR MEDICINA ESPECIALIZADA -DERMATOL | I60: CONSULTA PRIMERA VEZ | J60: CONSULTA | L60: 250000 | M60: 122500 | N60: 0 | O60: 5000 | P60: 0 | Q60: 0 | R60: 0 | S60: 122500 | T60: 0.49 | V60: 2026-02-03 13:21:00 | W60: SI | X60: GOOGLE | Y60: 28 | Z60: FE13884 | AA60: COLOMBIA | AB60: 3107358639
A61: 36071 | B61: 25853 | C61: 46056 | D61: CC 1015070195 | E61: SANTIAGO MURILLO FORONDA | F61: JURANY SANCHEZ | G61: 890242 | H61: CONSULTA DE PRIMERA VEZ POR MEDICINA ESPECIALIZADA -DERMATOL | I61: CONSULTA PRIMERA VEZ | J61: CONSULTA | L61: 250000 | M61: 125000 | N61: 0 | O61: 0 | P61: 0 | Q61: 0 | R61: 0 | S61: 125000 | T61: 0.5 | V61: 2026-02-03 13:42:00 | W61: SI | X61: INSTAGRAM | Y61: 19 | Z61: FE13885 | AA61: COLOMBIA | AB61: 3233132090
A62: 36113 | B62: 25906 | C62: 46056 | D62: CC 80768857 | E62: NILSON YAIR MURILLO RENTERIA | F62: DAVID CHALARCA CANAS | G62: 890242 | H62: CONSULTA DE PRIMERA VEZ POR MEDICINA ESPECIALIZADA -DERMATOL | I62: CONSULTA PRIMERA VEZ | J62: CONSULTA | L62: 250000 | M62: 125000 | N62: 0 | O62: 0 | P62: 0 | Q62: 0 | R62: 0 | S62: 125000 | T62: 0.5 | V62: 2026-02-03 13:49:00 | W62: SI | X62: GOOGLE | Y62: 41 | Z62: FE13886 | AA62: COLOMBIA | AB62: 3136157440
A63: 23794 | B63: 25138 | C63: 46056 | D63: CC 1000437820 | E63: DIDIER JURADO GALLEGO | F63: JURANY SANCHEZ | G63: M00009 | H63: EXOSOMA CAPILAR NANOPORE | I63: MESOJECT | J63: PROCEDIMIENTOS | L63: 0 | M63: 0 | N63: 178225.36 | O63: 0 | P63: 0 | Q63: 32874.64 | R63: 0 | S63: -178225.36 | T63: 0 | W63: SIN PAGO | X63: AMIG@ | Y63: 36 | AA63: COLOMBIA | AB63: 3167430922
A64: 34158 | B64: 25615 | C64: 46056 | D64: CC 42872262 | E64: DORA OLIVIA LONDOÑO AGUDELO | F64: DANIELA ASTAROT SALAZAR URIBE | G64: 861426 | H64: APLICACIÓN DE SKINVIVE | I64: INYECTABLES | J64: PROCEDIMIENTOS | L64: 1300000 | M64: 297600 | N64: 599010 | O64: 0 | P64: 0 | Q64: 105790 | R64: 0 | S64: 403390 | T64: 0.3103 | V64: 2026-01-29 09:10:00 | W64: NO | X64: INSTAGRAM | Y64: 67 | Z64: FE13750 | AA64: COLOMBIA | AB64: 3148779647
A65: 35148 | B65: 24273 | C65: 46056 | D65: PA US528364347 | E65: YANELLYS ROMAN DIAZ | F65: DANIELA ASTAROT SALAZAR URIBE | G65: 861411 | H65: APLICACIÓN TOXINA BOTULINICA | I65: INYECTABLES | J65: PROCEDIMIENTOS | L65: 1150000 | M65: 404831 | N65: 208370.46 | O65: 23000 | P65: 0 | Q65: 108967.54 | R65: 0 | S65: 513798.54 | T65: 0.44678134 | V65: 2026-02-03 11:52:00 | W65: SI | X65: INSTAGRAM | Y65: 37 | Z65: FE13879 | AA65: PUERTO RICO | AB65: 1 787-955-4621
A66: 36067 | B66: 25847 | C66: 46056 | D66: CC 1095817711 | E66: MEYNE JULIETTE PEREIRA AYALA | F66: DANIELA ASTAROT SALAZAR URIBE | G66: 890242 | H66: CONSULTA DE PRIMERA VEZ POR MEDICINA ESPECIALIZADA -DERMATOL | I66: CONSULTA PRIMERA VEZ | J66: CONSULTA | L66: 250000 | M66: 122500 | N66: 0 | O66: 5000 | P66: 0 | Q66: 0 | R66: 0 | S66: 122500 | T66: 0.49 | V66: 2026-02-03 14:50:00 | W66: SI | X66: INSTAGRAM | Y66: 32 | Z66: FE13887 | AA66: COLOMBIA | AB66: 3166218289
A67: 36120 | B67: 25915 | C67: 46056 | D67: CC 30083289 | E67: ANA DELIA GARZON | F67: JURANY SANCHEZ | G67: 890242 | H67: CONSULTA DE PRIMERA VEZ POR MEDICINA ESPECIALIZADA -DERMATOL | I67: CONSULTA PRIMERA VEZ | J67: CONSULTA | L67: 250000 | M67: 122500 | N67: 0 | O67: 5000 | P67: 0 | Q67: 0 | R67: 0 | S67: 122500 | T67: 0.49 | V67: 2026-02-03 14:53:00 | W67: SI | X67: INSTAGRAM | Y67: 46 | Z67: FE13888 | AA67: COLOMBIA | AB67: 310 3286950
A68: 36110 | B68: 25903 | C68: 46056 | D68: CE 64903773 | E68: GLADYS GERALDINE MANTILLA MENDOZA | F68: DAVID CHALARCA CANAS | G68: 890242 | H68: CONSULTA DE PRIMERA VEZ POR MEDICINA ESPECIALIZADA -DERMATOL | I68: CONSULTA PRIMERA VEZ | J68: CONSULTA | L68: 250000 | M68: 122500 | N68: 0 | O68: 5000 | P68: 0 | Q68: 0 | R68: 0 | S68: 122500 | T68: 0.49 | V68: 2026-02-03 16:06:00 | W68: SI | X68: GOOGLE | Y68: 34 | Z68: FE13892 | AA68: COLOMBIA | AB68: 59897992403
A69: 36083 | B69: 25868 | C69: 46056 | D69: CC 41909480 | E69: OLGA LUCIA URREA MONCALEANO | F69: STEPHANIA LAGUADO GONZALEZ | G69: 890303 | H69: CONSULTA DE CONTROL - PROCEDIMIENTO | I69: CONSULTA CONTROL | J69: CONSULTA | L69: 0 | M69: 0 | N69: 0 | O69: 0 | P69: 0 | Q69: 0 | R69: 0 | S69: 0 | T69: 0 | W69: SIN PAGO | X69: INSTAGRAM | Y69: 59 | AA69: COLOMBIA | AB69: 3218009726
A70: 36082 | B70: 25867 | C70: 46056 | D70: TI 1040576099 | E70: DEVI VILLA CARDONA | F70: JURANY SANCHEZ | G70: 890242 | H70: CONSULTA DE PRIMERA VEZ POR MEDICINA ESPECIALIZADA -DERMATOL | I70: CONSULTA PRIMERA VEZ | J70: CONSULTA | L70: 250000 | M70: 122500 | N70: 0 | O70: 5000 | P70: 0 | Q70: 0 | R70: 0 | S70: 122500 | T70: 0.49 | V70: 2026-02-03 16:39:00 | W70: SI | X70: AMIG@ | Y70: 11 | Z70: FE13896 | AA70: COLOMBIA | AB70: 3193909428
A71: 36121 | B71: 25916 | C71: 46056 | D71: PA 644888214 | E71: HECTOR SANTA | F71: JURANY SANCHEZ | G71: 861401 | H71: INFILTRACION INTRALESIONAL 1-5 LESIONES | I71: PROCE DERMA | J71: PROCEDIMIENTOS | L71: 300000 | M71: 147000 | N71: 0 | O71: 6000 | P71: 0 | Q71: 0 | R71: 0 | S71: 147000 | T71: 0.49 | V71: 2026-02-03 16:41:00 | W71: SI | X71: GOOGLE | Y71: 29 | Z71: FE13897 | AA71: ESTADOS UNIDOS | AB71: 19172441986
A72: 36064 | B72: 25841 | C72: 46056 | D72: CC 1001596699 | E72: PAULA ANDREA FORTICH HERRERA | F72: JURANY SANCHEZ | G72: 890242 | H72: CONSULTA DE PRIMERA VEZ POR MEDICINA ESPECIALIZADA -DERMATOL | I72: CONSULTA PRIMERA VEZ | J72: CONSULTA | L72: 250000 | M72: 125000 | N72: 0 | O72: 0 | P72: 0 | Q72: 0 | R72: 0 | S72: 125000 | T72: 0.5 | V72: 2026-02-03 16:38:00 | W72: SI | X72: INSTAGRAM | Y72: 30 | Z72: FE13895 | AA72: COLOMBIA | AB72: 3122368103
A73: 36080 | B73: 25865 | C73: 46056 | D73: CC 43816936 | E73: LINA MARIA ALVAREZ OCHOA | F73: JURANY SANCHEZ | G73: 861411 | H73: APLICACIÓN TOXINA BOTULINICA | I73: INYECTABLES | J73: PROCEDIMIENTOS | L73: 0 | M73: 0 | N73: 16462.88 | O73: 0 | P73: 0 | Q73: 8717.12 | R73: 0 | S73: -16462.88 | T73: 0 | W73: SIN PAGO | X73: INSTAGRAM | Y73: 41 | AA73: COLOMBIA | AB73: 3185777775
A74: 36118 | B74: 25912 | C74: 46056 | D74: CC 1037587168 | E74: JENIFER VANEGAS VELEZ | F74: JURANY SANCHEZ | G74: 890242 | H74: CONSULTA DE PRIMERA VEZ POR MEDICINA ESPECIALIZADA -DERMATOL | I74: CONSULTA PRIMERA VEZ | J74: CONSULTA | L74: 250000 | M74: 122500 | N74: 0 | O74: 5000 | P74: 0 | Q74: 0 | R74: 0 | S74: 122500 | T74: 0.49 | V74: 2026-02-03 17:24:00 | W74: SI | X74: INSTAGRAM | Y74: 37 | Z74: FE13899 | AA74: COLOMBIA | AB74: 3122870388
A75: 22514 | B75: 25520 | C75: 46056 | D75: CC 41475573 | E75: ELSA BELTRAN | F75: STEPHANIA LAGUADO GONZALEZ | G75: JL1050 | H75: JALUPRO 2 EN 1 (PROTOCOLO) | I75: INYECTABLES | J75: PROCEDIMIENTOS | L75: 1650000 | M75: 429535 | N75: 601502.28 | O75: 33000 | P75: 0 | Q75: 156427.72 | R75: 0 | S75: 585962.72 | T75: 0.35512892 | V75: 2026-02-03 16:06:00 | W75: SI | X75: VITRINA | Y75: 78 | Z75: FE13891 | AA75: COLOMBIA | AB75: 3112781679
A76: 35899 | B76: 25522 | C76: 46056 | D76: CC 43565986 | E76: MARGARITA MARIA VELASQUEZ LOPERA | F76: STEPHANIA LAGUADO GONZALEZ | G76: 861414 | H76: APLICACIÓN ACIDO HIALURONICO | I76: INYECTABLES | J76: PROCEDIMIENTOS | L76: 1170000 | M76: 379950.5 | N76: 248277.09 | O76: 23400 | P76: 0 | Q76: 138421.91 | R76: 0 | S76: 518372.41 | T76: 0.44305334 | V76: 2026-02-03 16:52:00 | W76: SI | X76: AMIG@ | Y76: 54 | Z76: FE13898 | AA76: COLOMBIA | AB76: 3136159166
A77: 32352 | B77: 25085 | C77: 46056 | D77: CC 1037623487 | E77: VANESA JARAMILLO | F77: DANIELA ASTAROT SALAZAR URIBE | G77: CM0008 | H77: COLOR MAX TATUAJE GRANDE >10 CM | I77: COLOR MAX | J77: PROCEDIMIENTOS | K77: LÁSER COLOR MAX | L77: 650000 | M77: 318500 | N77: 0 | O77: 13000 | P77: 0 | Q77: 0 | R77: 0 | S77: 318500 | T77: 0.49 | V77: 2026-02-03 15:51:00 | W77: SI | X77: AMIG@ | Y77: 33 | Z77: FE13890 | AA77: COLOMBIA | AB77: 3113593846
A78: 31327 | B78: 19094 | C78: 46056 | D78: CC 1037613226 | E78: CRISTINA ALCARAZ | F78: LUISA HERNANDEZ TEJADA | G78: CM0012 | H78: COLOR MAX LENTIGOS EFELIDES O PECAS 1- 30 LESIONES | I78: COLOR MAX | J78: PROCEDIMIENTOS | K78: LÁSER COLOR MAX | L78: 0 | M78: 0 | N78: 0 | O78: 0 | P78: 0 | Q78: 0 | R78: 0 | S78: 0 | T78: 0 | W78: SIN PAGO | X78: AMIG@ | Y78: 35 | AA78: COLOMBIA | AB78: 3192720309
A79: 35358 | B79: 24593 | C79: 46056 | D79: CC 1152207559 | E79: DANIELA SALAZAR IZASA | F79: LUISA HERNANDEZ TEJADA | G79: HP0001 | H79: HANDPICO - MELASMA COMPONENTE PIGMENTARIO - PASO 2/2 | I79: HANDPICO | J79: PROCEDIMIENTOS | K79: HANDPICO | L79: 350000 | M79: 175000 | N79: 0 | O79: 0 | P79: 0 | Q79: 0 | R79: 0 | S79: 175000 | T79: 0.5 | V79: 2026-02-03 09:15:00 | W79: SI | X79: INSTAGRAM | Y79: 31 | Z79: FE13875 | AA79: COLOMBIA | AB79: 3117670140
A80: 35358 | B80: 25891 | C80: 46056 | D80: CC 1152207559 | E80: DANIELA SALAZAR IZASA | F80: LUISA HERNANDEZ TEJADA | G80: IP0001 | H80: IPL PROCEDIMIENTOS POR ZONA | I80: IPL-SQ | J80: PROCEDIMIENTOS | K80: IPL-SQ | L80: 0 | M80: 0 | N80: 0 | O80: 0 | P80: 0 | Q80: 0 | R80: 0 | S80: 0 | T80: 0 | W80: SIN PAGO | X80: INSTAGRAM | Y80: 31 | AA80: COLOMBIA | AB80: 3117670140
A81: 35668 | B81: 25107 | C81: 46056 | D81: CC 1036645121 | E81: DANIEL JARAMILLO GOMEZ | F81: LUISA HERNANDEZ TEJADA | G81: IP0001 | H81: IPL PROCEDIMIENTOS POR ZONA | I81: IPL-SQ | J81: PROCEDIMIENTOS | K81: IPL-SQ | L81: 650000 | M81: 318500 | N81: 0 | O81: 13000 | P81: 0 | Q81: 0 | R81: 0 | S81: 318500 | T81: 0.49 | V81: 2026-02-03 14:58:00 | W81: SI | X81: INSTAGRAM | Y81: 32 | Z81: FE13889 | AA81: COLOMBIA | AB81: 3215637931
A82: 35470 | B82: 25022 | C82: 46056 | D82: CC 70042856 | E82: JORGE LEON PANIAGUA BLANDON | F82: LUISA HERNANDEZ TEJADA | G82: LC0010 | H82: CO2 FULGURACIONES > 10 LESIONES (CARA, CUELLO O CORPORAL) | I82: LASER Co2 | J82: PROCEDIMIENTOS | K82: LÁSER IBLAZE (CO2) | L82: 0 | M82: 0 | N82: 0 | O82: 0 | P82: 0 | Q82: 0 | R82: 0 | S82: 0 | T82: 0 | W82: SIN PAGO | X82: VITRINA | Y82: 74 | AA82: COLOMBIA | AB82: 3206977603
A83: 30870 | B83: 25884 | C83: 46056 | D83: CC 1085327585 | E83: ASTRID CAROLINA CALVACHE VELASQUEZ | F83: LUISA HERNANDEZ TEJADA | G83: 861411 | H83: APLICACIÓN TOXINA BOTULINICA | I83: INYECTABLES | J83: PROCEDIMIENTOS | L83: 1150000 | M83: 406125 | N83: 205786 | O83: 23000 | P83: 0 | Q83: 108964 | R83: 0 | S83: 515089 | T83: 0.44790348 | V83: 2026-02-03 16:18:00 | W83: SI | X83: INSTAGRAM | Y83: 30 | Z83: FE13893 | AA83: COLOMBIA | AB83: 3168431103
A84: 30870 | B84: 25940 | C84: 46056 | D84: CC 1085327585 | E84: ASTRID CAROLINA CALVACHE VELASQUEZ | F84: LUISA HERNANDEZ TEJADA | G84: CM0012 | H84: COLOR MAX LENTIGOS EFELIDES O PECAS 1- 30 LESIONES | I84: COLOR MAX | J84: PROCEDIMIENTOS | K84: LÁSER COLOR MAX | L84: 650000 | M84: 318500 | N84: 0 | O84: 13000 | P84: 0 | Q84: 0 | R84: 0 | S84: 318500 | T84: 0.49 | V84: 2026-02-03 16:28:00 | W84: SI | X84: INSTAGRAM | Y84: 30 | Z84: FE13894 | AA84: COLOMBIA | AB84: 3168431103
A85: 35001 | B85: 24896 | C85: 46056 | D85: CC 1017927343 | E85: MIGUEL ANGEL PRIETO PATIÑO | F85: LUISA HERNANDEZ TEJADA | G85: M00013 | H85: TERAPIA FOTODINÁMICA | I85: FOTOAGE | J85: PROCEDIMIENTOS | K85: PRODEEP | L85: 200000 | M85: 89657.5 | N85: 14500 | O85: 4000 | P85: 0 | Q85: 2185 | R85: 0 | S85: 91842.5 | T85: 0.4592125 | V85: 2026-02-03 11:56:00 | W85: SI | X85: INSTAGRAM | Y85: 19 | Z85: FE13880 | AA85: COLOMBIA | AB85: 3122875859
A86: 31342 | B86: 23319 | C86: 46056 | D86: CC 1005241103 | E86: KATHERINE LINARES JIMENEZ | F86: LUISA HERNANDEZ TEJADA | G86: M00010 | H86: EXOSOMA FACIAL | I86: MESOJECT | J86: PROCEDIMIENTOS | L86: 500000 | M86: 239852.5 | N86: 8750 | O86: 10000 | P86: 0 | Q86: 1545 | R86: 0 | S86: 241397.5 | T86: 0.482795 | V86: 2026-02-03 13:09:00 | W86: SI | X86: GOOGLE | Y86: 24 | Z86: FE13883 | AA86: COLOMBIA | AB86: 3134061176
A87: 36123 | B87: 25918 | C87: 46057 | D87: CC 1001404255 | E87: DENIS MARCELA MORENO LONDOÑO | F87: DAVID CHALARCA CANAS | G87: 890242 | H87: CONSULTA DE PRIMERA VEZ POR MEDICINA ESPECIALIZADA -DERMATOL | I87: CONSULTA PRIMERA VEZ | J87: CONSULTA | L87: 250000 | M87: 122500 | N87: 0 | O87: 5000 | P87: 0 | Q87: 0 | R87: 0 | S87: 122500 | T87: 0.49 | V87: 2026-02-04 09:22:00 | W87: SI | X87: AMIG@ | Y87: 23 | Z87: FE13900 | AA87: COLOMBIA | AB87: 3217220533
A88: 35989 | B88: 25696 | C88: 46057 | D88: CC 43581425 | E88: ANA MARIA MEJIA MEJIA | F88: PAULA ANDREA ARISTIZABAL DIAZ | G88: 890242 | H88: CONSULTA DE PRIMERA VEZ POR MEDICINA ESPECIALIZADA -DERMATOL | I88: CONSULTA PRIMERA VEZ | J88: CONSULTA | L88: 250000 | M88: 122500 | N88: 0 | O88: 5000 | P88: 0 | Q88: 0 | R88: 0 | S88: 122500 | T88: 0.49 | V88: 2026-02-04 12:51:00 | W88: SI | X88: INSTAGRAM | Y88: 51 | Z88: FE13903 | AA88: COLOMBIA | AB88: 3104098415
A89: 35824 | B89: 25978 | C89: 46057 | D89: CC 20275652 | E89: ZULMA FERRER GARCIA | F89: MARIA CAMILA ZULUAGA ALVAREZ | G89: 861411 | H89: APLICACIÓN TOXINA BOTULINICA | I89: INYECTABLES | J89: PROCEDIMIENTOS | L89: 1265000 | M89: 446737.5 | N89: 226364.6 | O89: 25300 | P89: 0 | Q89: 119860.4 | R89: 0 | S89: 566597.9 | T89: 0.44790348 | V89: 2026-02-04 12:24:00 | W89: SI | X89: VITRINA | Y89: 84 | Z89: FE13902 | AA89: COLOMBIA | AB89: 3017770852
A90: 33293 | B90: 25582 | C90: 46057 | D90: CC 32016558 | E90: MARIA OMAIRA TEJADA BARRIENTOS | F90: PAULA ANDREA ARISTIZABAL DIAZ | G90: LP0008 | H90: TRATAMIENTO DE ONICOMICOSIS - LONGPULSE | I90: LONGPULSE | J90: PROCEDIMIENTOS | K90: LONGPULSE | L90: 0 | M90: 0 | N90: 0 | O90: 0 | P90: 0 | Q90: 0 | R90: 0 | S90: 0 | T90: 0 | W90: SIN PAGO | X90: AMIG@ | Y90: 67 | AA90: COLOMBIA | AB90: 3148121576
A91: 33292 | B91: 25580 | C91: 46057 | D91: CC 70090631 | E91: SERGIO ARTURO HERNANDEZ VELASQUEZ | F91: PAULA ANDREA ARISTIZABAL DIAZ | G91: 868115 | H91: DERMOABRASIÓN MECÁNICADE UÑA | I91: PROCE DERMA | J91: PROCEDIMIENTOS | L91: 0 | M91: 0 | N91: 0 | O91: 0 | P91: 0 | Q91: 0 | R91: 0 | S91: 0 | T91: 0 | W91: SIN PAGO | X91: AMIG@ | Y91: 67 | AA91: COLOMBIA | AB91: 3148121602
A92: 36136 | B92: 25937 | C92: 46057 | D92: CC 1052984328 | E92: YULIETH PAOLA ROMERO GOMEZ | F92: PAULA ANDREA ARISTIZABAL DIAZ | G92: 890242 | H92: CONSULTA DE PRIMERA VEZ POR MEDICINA ESPECIALIZADA -DERMATOL | I92: CONSULTA PRIMERA VEZ | J92: CONSULTA | L92: 250000 | M92: 125000 | N92: 0 | O92: 0 | P92: 0 | Q92: 0 | R92: 0 | S92: 125000 | T92: 0.5 | V92: 2026-02-04 13:36:00 | W92: SI | X92: INSTAGRAM | Y92: 33 | Z92: FE13904 | AA92: COLOMBIA | AB92: 3001352138
A93: 35450 | B93: 24753 | C93: 46057 | D93: CC 1020451308 | E93: ELIZABETH HENAO BUSTAMANTE | F93: DANIELA ASTAROT SALAZAR URIBE | G93: 890242 | H93: CONSULTA DE PRIMERA VEZ POR MEDICINA ESPECIALIZADA -DERMATOL | I93: CONSULTA PRIMERA VEZ | J93: CONSULTA | L93: 250000 | M93: 122500 | N93: 0 | O93: 5000 | P93: 0 | Q93: 0 | R93: 0 | S93: 122500 | T93: 0.49 | V93: 2026-02-04 15:51:00 | W93: SI | X93: INSTAGRAM | Y93: 33 | Z93: FE13908 | AA93: COLOMBIA | AB93: 3007923178
A94: 36089 | B94: 25877 | C94: 46057 | D94: CC 1001132050 | E94: SARA VALENTINA SOTO PALACIOS | F94: DAVID CHALARCA CANAS | G94: 890242 | H94: CONSULTA DE PRIMERA VEZ POR MEDICINA ESPECIALIZADA -DERMATOL | I94: CONSULTA PRIMERA VEZ | J94: CONSULTA | L94: 250000 | M94: 122500 | N94: 0 | O94: 5000 | P94: 0 | Q94: 0 | R94: 0 | S94: 122500 | T94: 0.49 | V94: 2026-02-04 15:36:00 | W94: SI | X94: GOOGLE | Y94: 25 | Z94: FE13906 | AA94: COLOMBIA | AB94: 3008407086
A95: 36160 | B95: 25991 | C95: 46057 | D95: CC 127360414 | E95: RUSMARY RUTBEIS BECERRA MEDINA | F95: DANIELA ASTAROT SALAZAR URIBE | G95: 890242 | H95: CONSULTA DE PRIMERA VEZ POR MEDICINA ESPECIALIZADA -DERMATOL | I95: CONSULTA PRIMERA VEZ | J95: CONSULTA | L95: 250000 | M95: 122500 | N95: 0 | O95: 5000 | P95: 0 | Q95: 0 | R95: 0 | S95: 122500 | T95: 0.49 | V95: 2026-02-04 15:12:00 | W95: SI | X95: GOOGLE | Y95: 31 | Z95: FE13905 | AA95: VENEZUELA | AB95: 17869732559
A96: 34511 | B96: 23359 | C96: 46057 | D96: CC 1007448662 | E96: SARA ROTAVISTA ISAZA | F96: PAULA ANDREA ARISTIZABAL DIAZ | G96: 861401 | H96: INFILTRACION INTRALESIONAL 1-5 LESIONES | I96: PROCE DERMA | J96: PROCEDIMIENTOS | L96: 250000 | M96: 122500 | N96: 0 | O96: 5000 | P96: 0 | Q96: 0 | R96: 0 | S96: 122500 | T96: 0.49 | V96: 2026-02-04 17:10:00 | W96: SI | X96: INSTAGRAM | Y96: 23 | Z96: FE13911 | AA96: COLOMBIA | AB96: 3126869957
A97: 36077 | B97: 25861 | C97: 46057 | D97: TI 1028010658 | E97: JUAN JOSE LLANO ARAGON | F97: DANIELA ASTAROT SALAZAR URIBE | G97: 890242 | H97: CONSULTA DE PRIMERA VEZ POR MEDICINA ESPECIALIZADA -DERMATOL | I97: CONSULTA PRIMERA VEZ | J97: CONSULTA | L97: 250000 | M97: 125000 | N97: 0 | O97: 0 | P97: 0 | Q97: 0 | R97: 0 | S97: 125000 | T97: 0.5 | V97: 2026-02-04 17:02:00 | W97: SI | X97: AMIG@ | Y97: 15 | Z97: FE13909 | AA97: COLOMBIA | AB97: 3232896211
A98: 36027 | B98: 25769 | C98: 46057 | D98: CC 42824053 | E98: CARMEN EDITH CASTAÑEDA MONTOYA | F98: STEPHANIA LAGUADO GONZALEZ | G98: 861414 | H98: APLICACIÓN ACIDO HIALURONICO | I98: INYECTABLES | J98: PROCEDIMIENTOS | L98: 0 | M98: 0 | N98: 467388.18 | O98: 0 | P98: 0 | Q98: 272469.82 | R98: 0 | S98: -467388.18 | T98: 0 | W98: SIN PAGO | X98: AMIG@ | Y98: 55 | AA98: COLOMBIA | AB98: 3246848573
A99: 36027 | B99: 25984 | C99: 46057 | D99: CC 42824053 | E99: CARMEN EDITH CASTAÑEDA MONTOYA | F99: STEPHANIA LAGUADO GONZALEZ | G99: 861417 | H99: APLICACIÓN BIOESTIMULADOR RADIESSE | I99: INYECTABLES | J99: PROCEDIMIENTOS | L99: 0 | M99: 0 | N99: 791707 | O99: 0 | P99: 0 | Q99: 139713 | R99: 0 | S99: -791707 | T99: 0 | W99: SIN PAGO | X99: AMIG@ | Y99: 55 | AA99: COLOMBIA | AB99: 3246848573
A100: 36163 | B100: 25997 | C100: 46057 | D100: CC 127360414 | E100: RUSMARY RUTBEIS BECERRA MEDINA | F100: DANIELA ASTAROT SALAZAR URIBE | G100: M00011 | H100: FOTOAGE | I100: FOTOAGE | J100: PROCEDIMIENTOS | K100: DISPOSITIVO FOTOAGE | L100: 650000 | M100: 279800 | N100: 68135.57 | O100: 13000 | P100: 0 | Q100: 9264.43 | R100: 0 | S100: 289064.43 | T100: 0.44471451 | V100: 2026-02-04 15:46:00 | W100: SI | X100: GOOGLE | Y100: 31 | Z100: FE13907 | AA100: VENEZUELA | AB100: 17869732559
...

Sheet TABLERO Y AGENDA
L1: META OBJETIVO | M1: PROYEC DÍA | N1: FECHA | O1: FACTURADO | P1: DÍA HABIL
B2: JUAN PABLO | C2: JUAN PABLO | D2: JUAN PABLO | L2: MABEL | M2: MABEL | N2: MABEL | O2: MABEL | P2: MABEL
B3: FECHA | C3: PROYECIÓN INICIO MES | D3: PROYECIÓN QUINCENA | E3: GESTIÓN COMERCIAL REAL | F3: PAGO SI | G3: PAGO NO | H3: SIN PAGO | I3: SERVICIOS PRESTADOS | J3: % DIF | L3: 19347826 | M3: 3190000 | N3: 46072 | O3: 24284000 | P3: 16
B4: 46054 | C4: 0 | D4: 0 | E4: =SUMIF(INFO.PROYECCIÓN!$C:$C,B4,INFO.PROYECCIÓN!$L:$L) -> 0 | F4: =SUMIFS(INFO.RENTABILIDAD!$L$1:$L$15000,INFO.RENTABILIDAD!$C$1:$C$15000,B4,INFO.RENTABILIDAD!$W$1:$W$15000,"SI") -> 133000 | G4: =SUMIFS(INFO.RENTABILIDAD!$L$1:$L$999,INFO.RENTABILIDAD!$C$1:$C$999,B4,INFO.RENTABILIDAD!$W$1:$W$999,"NO") -> 0 | H4: =SUMIFS(INFO.RENTABILIDAD!$L$1:$L$999,INFO.RENTABILIDAD!$C$1:$C$999,B4,INFO.RENTABILIDAD!$W$1:$W$999,"SIN PAGO") -> 0 | I4: =SUMIF(INFO.RENTABILIDAD!C:C,B4,INFO.RENTABILIDAD!L:L) -> 133000 | J4: - | L4: TUPI GESTIÓN COMERCIAL ABRIL
B5: 46055 | C5: 0 | D5: 0 | E5: =SUMIF(INFO.PROYECCIÓN!$C:$C,B5,INFO.PROYECCIÓN!$L:$L) -> 0 | F5: =SUMIFS(INFO.RENTABILIDAD!$L$1:$L$15000,INFO.RENTABILIDAD!$C$1:$C$15000,B5,INFO.RENTABILIDAD!$W$1:$W$15000,"SI") -> 23167000 | G5: =SUMIFS(INFO.RENTABILIDAD!$L$1:$L$999,INFO.RENTABILIDAD!$C$1:$C$999,B5,INFO.RENTABILIDAD!$W$1:$W$999,"NO") -> 200000 | H5: =SUMIFS(INFO.RENTABILIDAD!$L$1:$L$999,INFO.RENTABILIDAD!$C$1:$C$999,B5,INFO.RENTABILIDAD!$W$1:$W$999,"SIN PAGO") -> 0 | I5: =SUMIF(INFO.RENTABILIDAD!C:C,B5,INFO.RENTABILIDAD!L:L) -> 23367000 | J5: - | L5: FECHAS | M5: RESULTADO | N5: PROYECCIÓN ABRIL | O5: GESTIÓN COM | P5: S. PRESTADOS
B6: 46056 | C6: 0 | D6: 0 | E6: =SUMIF(INFO.PROYECCIÓN!$C:$C,B6,INFO.PROYECCIÓN!$L:$L) -> 0 | F6: =SUMIFS(INFO.RENTABILIDAD!$L$1:$L$15000,INFO.RENTABILIDAD!$C$1:$C$15000,B6,INFO.RENTABILIDAD!$W$1:$W$15000,"SI") -> 14266000 | G6: =SUMIFS(INFO.RENTABILIDAD!$L$1:$L$999,INFO.RENTABILIDAD!$C$1:$C$999,B6,INFO.RENTABILIDAD!$W$1:$W$999,"NO") -> 1350000 | H6: =SUMIFS(INFO.RENTABILIDAD!$L$1:$L$999,INFO.RENTABILIDAD!$C$1:$C$999,B6,INFO.RENTABILIDAD!$W$1:$W$999,"SIN PAGO") -> 0 | I6: =SUMIF(INFO.RENTABILIDAD!C:C,B6,INFO.RENTABILIDAD!L:L) -> 15616000 | J6: - | M6: SEMANA 1 | N6: =SUM(C4:C8) -> 0 | O6: =SUM(E4:E8) -> 0 | P6: =SUM(I4:I8) -> 61422500
B7: 46057 | C7: 0 | D7: 0 | E7: =SUMIF(INFO.PROYECCIÓN!$C:$C,B7,INFO.PROYECCIÓN!$L:$L) -> 0 | F7: =SUMIFS(INFO.RENTABILIDAD!$L$1:$L$15000,INFO.RENTABILIDAD!$C$1:$C$15000,B7,INFO.RENTABILIDAD!$W$1:$W$15000,"SI") -> 6521000 | G7: =SUMIFS(INFO.RENTABILIDAD!$L$1:$L$999,INFO.RENTABILIDAD!$C$1:$C$999,B7,INFO.RENTABILIDAD!$W$1:$W$999,"NO") -> 381000 | H7: =SUMIFS(INFO.RENTABILIDAD!$L$1:$L$999,INFO.RENTABILIDAD!$C$1:$C$999,B7,INFO.RENTABILIDAD!$W$1:$W$999,"SIN PAGO") -> 0 | I7: =SUMIF(INFO.RENTABILIDAD!C:C,B7,INFO.RENTABILIDAD!L:L) -> 6902000 | J7: - | M7: SEMANA 2 | N7: =SUM(C9:C15) -> 0 | O7: =SUM(E9:E15) -> 0 | P7: =SUM(I9:I15) -> 114190500
B8: 46058 | C8: 0 | D8: 0 | E8: =SUMIF(INFO.PROYECCIÓN!$C:$C,B8,INFO.PROYECCIÓN!$L:$L) -> 0 | F8: =SUMIFS(INFO.RENTABILIDAD!$L$1:$L$15000,INFO.RENTABILIDAD!$C$1:$C$15000,B8,INFO.RENTABILIDAD!$W$1:$W$15000,"SI") -> 13902000 | G8: =SUMIFS(INFO.RENTABILIDAD!$L$1:$L$999,INFO.RENTABILIDAD!$C$1:$C$999,B8,INFO.RENTABILIDAD!$W$1:$W$999,"NO") -> 1502500 | H8: =SUMIFS(INFO.RENTABILIDAD!$L$1:$L$999,INFO.RENTABILIDAD!$C$1:$C$999,B8,INFO.RENTABILIDAD!$W$1:$W$999,"SIN PAGO") -> 0 | I8: =SUMIF(INFO.RENTABILIDAD!C:C,B8,INFO.RENTABILIDAD!L:L) -> 15404500 | J8: - | M8: SEMANA 3 | N8: =SUM(C16:C22) -> 0 | O8: =SUM(E16:E22) -> 0 | P8: =SUM(I16:I22) -> 137771000
B9: 46059 | C9: 0 | D9: 0 | E9: =SUMIF(INFO.PROYECCIÓN!$C:$C,B9,INFO.PROYECCIÓN!$L:$L) -> 0 | F9: =SUMIFS(INFO.RENTABILIDAD!$L$1:$L$15000,INFO.RENTABILIDAD!$C$1:$C$15000,B9,INFO.RENTABILIDAD!$W$1:$W$15000,"SI") -> 24645000 | G9: =SUMIFS(INFO.RENTABILIDAD!$L$1:$L$999,INFO.RENTABILIDAD!$C$1:$C$999,B9,INFO.RENTABILIDAD!$W$1:$W$999,"NO") -> 123500 | H9: =SUMIFS(INFO.RENTABILIDAD!$L$1:$L$999,INFO.RENTABILIDAD!$C$1:$C$999,B9,INFO.RENTABILIDAD!$W$1:$W$999,"SIN PAGO") -> 0 | I9: =SUMIF(INFO.RENTABILIDAD!C:C,B9,INFO.RENTABILIDAD!L:L) -> 24768500 | J9: - | M9: SEMANA 4 | N9: =SUM(C23:C29) -> 0 | O9: =SUM(E23:E29) -> 85912500 | P9: =SUM(I23:I29) -> 0
B10: 46060 | C10: 0 | D10: 0 | E10: =SUMIF(INFO.PROYECCIÓN!$C:$C,B10,INFO.PROYECCIÓN!$L:$L) -> 0 | F10: =SUMIFS(INFO.RENTABILIDAD!$L$1:$L$15000,INFO.RENTABILIDAD!$C$1:$C$15000,B10,INFO.RENTABILIDAD!$W$1:$W$15000,"SI") -> 11220000 | G10: =SUMIFS(INFO.RENTABILIDAD!$L$1:$L$999,INFO.RENTABILIDAD!$C$1:$C$999,B10,INFO.RENTABILIDAD!$W$1:$W$999,"NO") -> 940000 | H10: =SUMIFS(INFO.RENTABILIDAD!$L$1:$L$999,INFO.RENTABILIDAD!$C$1:$C$999,B10,INFO.RENTABILIDAD!$W$1:$W$999,"SIN PAGO") -> 0 | I10: =SUMIF(INFO.RENTABILIDAD!C:C,B10,INFO.RENTABILIDAD!L:L) -> 12160000 | J10: - | M10: SEMANA 5 | N10: =SUM(C30:C34) -> 0 | O10: =SUM(E30:E34) -> 19120000 | P10: =SUM(I30:I34) -> 0
B11: 46061 | C11: 0 | D11: 0 | E11: =SUMIF(INFO.PROYECCIÓN!$C:$C,B11,INFO.PROYECCIÓN!$L:$L) -> 0 | F11: =SUMIFS(INFO.RENTABILIDAD!$L$1:$L$15000,INFO.RENTABILIDAD!$C$1:$C$15000,B11,INFO.RENTABILIDAD!$W$1:$W$15000,"SI") -> 610000 | G11: =SUMIFS(INFO.RENTABILIDAD!$L$1:$L$999,INFO.RENTABILIDAD!$C$1:$C$999,B11,INFO.RENTABILIDAD!$W$1:$W$999,"NO") -> 0 | H11: =SUMIFS(INFO.RENTABILIDAD!$L$1:$L$999,INFO.RENTABILIDAD!$C$1:$C$999,B11,INFO.RENTABILIDAD!$W$1:$W$999,"SIN PAGO") -> 0 | I11: =SUMIF(INFO.RENTABILIDAD!C:C,B11,INFO.RENTABILIDAD!L:L) -> 610000 | J11: - | L11: ABRIL | N11: =SUM(N6:N10) -> 0 | O11: =SUM(O6:O10) -> 105032500 | P11: =SUM(P6:P9) -> 313384000
B12: 46062 | C12: 0 | D12: 0 | E12: =SUMIF(INFO.PROYECCIÓN!$C:$C,B12,INFO.PROYECCIÓN!$L:$L) -> 0 | F12: =SUMIFS(INFO.RENTABILIDAD!$L$1:$L$15000,INFO.RENTABILIDAD!$C$1:$C$15000,B12,INFO.RENTABILIDAD!$W$1:$W$15000,"SI") -> 18849500 | G12: =SUMIFS(INFO.RENTABILIDAD!$L$1:$L$999,INFO.RENTABILIDAD!$C$1:$C$999,B12,INFO.RENTABILIDAD!$W$1:$W$999,"NO") -> 0 | H12: =SUMIFS(INFO.RENTABILIDAD!$L$1:$L$999,INFO.RENTABILIDAD!$C$1:$C$999,B12,INFO.RENTABILIDAD!$W$1:$W$999,"SIN PAGO") -> 0 | I12: =SUMIF(INFO.RENTABILIDAD!C:C,B12,INFO.RENTABILIDAD!L:L) -> 18849500 | J12: -
B13: 46063 | C13: 0 | D13: 0 | E13: =SUMIF(INFO.PROYECCIÓN!$C:$C,B13,INFO.PROYECCIÓN!$L:$L) -> 0 | F13: =SUMIFS(INFO.RENTABILIDAD!$L$1:$L$15000,INFO.RENTABILIDAD!$C$1:$C$15000,B13,INFO.RENTABILIDAD!$W$1:$W$15000,"SI") -> 26790000 | G13: =SUMIFS(INFO.RENTABILIDAD!$L$1:$L$999,INFO.RENTABILIDAD!$C$1:$C$999,B13,INFO.RENTABILIDAD!$W$1:$W$999,"NO") -> 332500 | H13: =SUMIFS(INFO.RENTABILIDAD!$L$1:$L$999,INFO.RENTABILIDAD!$C$1:$C$999,B13,INFO.RENTABILIDAD!$W$1:$W$999,"SIN PAGO") -> 0 | I13: =SUMIF(INFO.RENTABILIDAD!C:C,B13,INFO.RENTABILIDAD!L:L) -> 27122500 | J13: - | L13: ='BALANCE PPTO'!D4 -> REPORTE GENERAL
B14: 46064 | C14: 0 | D14: 0 | E14: =SUMIF(INFO.PROYECCIÓN!$C:$C,B14,INFO.PROYECCIÓN!$L:$L) -> 0 | F14: =SUMIFS(INFO.RENTABILIDAD!$L$1:$L$15000,INFO.RENTABILIDAD!$C$1:$C$15000,B14,INFO.RENTABILIDAD!$W$1:$W$15000,"SI") -> 14830000 | G14: =SUMIFS(INFO.RENTABILIDAD!$L$1:$L$999,INFO.RENTABILIDAD!$C$1:$C$999,B14,INFO.RENTABILIDAD!$W$1:$W$999,"NO") -> 0 | H14: =SUMIFS(INFO.RENTABILIDAD!$L$1:$L$999,INFO.RENTABILIDAD!$C$1:$C$999,B14,INFO.RENTABILIDAD!$W$1:$W$999,"SIN PAGO") -> 0 | I14: =SUMIF(INFO.RENTABILIDAD!C:C,B14,INFO.RENTABILIDAD!L:L) -> 14830000 | J14: - | L14: ='BALANCE PPTO'!D5 -> 46072
B15: 46065 | C15: 0 | D15: 0 | E15: =SUMIF(INFO.PROYECCIÓN!$C:$C,B15,INFO.PROYECCIÓN!$L:$L) -> 0 | F15: =SUMIFS(INFO.RENTABILIDAD!$L$1:$L$15000,INFO.RENTABILIDAD!$C$1:$C$15000,B15,INFO.RENTABILIDAD!$W$1:$W$15000,"SI") -> 15850000 | G15: =SUMIFS(INFO.RENTABILIDAD!$L$1:$L$999,INFO.RENTABILIDAD!$C$1:$C$999,B15,INFO.RENTABILIDAD!$W$1:$W$999,"NO") -> 0 | H15: =SUMIFS(INFO.RENTABILIDAD!$L$1:$L$999,INFO.RENTABILIDAD!$C$1:$C$999,B15,INFO.RENTABILIDAD!$W$1:$W$999,"SIN PAGO") -> 0 | I15: =SUMIF(INFO.RENTABILIDAD!C:C,B15,INFO.RENTABILIDAD!L:L) -> 15850000 | J15: -
B16: 46066 | C16: 0 | D16: 0 | E16: =SUMIF(INFO.PROYECCIÓN!$C:$C,B16,INFO.PROYECCIÓN!$L:$L) -> 0 | F16: =SUMIFS(INFO.RENTABILIDAD!$L$1:$L$15000,INFO.RENTABILIDAD!$C$1:$C$15000,B16,INFO.RENTABILIDAD!$W$1:$W$15000,"SI") -> 24510000 | G16: =SUMIFS(INFO.RENTABILIDAD!$L$1:$L$999,INFO.RENTABILIDAD!$C$1:$C$999,B16,INFO.RENTABILIDAD!$W$1:$W$999,"NO") -> 0 | H16: =SUMIFS(INFO.RENTABILIDAD!$L$1:$L$999,INFO.RENTABILIDAD!$C$1:$C$999,B16,INFO.RENTABILIDAD!$W$1:$W$999,"SIN PAGO") -> 0 | I16: =SUMIF(INFO.RENTABILIDAD!C:C,B16,INFO.RENTABILIDAD!L:L) -> 24510000 | J16: - | L16: ='BALANCE PPTO'!D8 -> % ESPERADO AL DÍA | M16: ='BALANCE PPTO'!E8 -> % REAL AL DÍA
B17: 46067 | C17: 0 | D17: 0 | E17: =SUMIF(INFO.PROYECCIÓN!$C:$C,B17,INFO.PROYECCIÓN!$L:$L) -> 0 | F17: =SUMIFS(INFO.RENTABILIDAD!$L$1:$L$15000,INFO.RENTABILIDAD!$C$1:$C$15000,B17,INFO.RENTABILIDAD!$W$1:$W$15000,"SI") -> 14265000 | G17: =SUMIFS(INFO.RENTABILIDAD!$L$1:$L$999,INFO.RENTABILIDAD!$C$1:$C$999,B17,INFO.RENTABILIDAD!$W$1:$W$999,"NO") -> 1240000 | H17: =SUMIFS(INFO.RENTABILIDAD!$L$1:$L$999,INFO.RENTABILIDAD!$C$1:$C$999,B17,INFO.RENTABILIDAD!$W$1:$W$999,"SIN PAGO") -> 0 | I17: =SUMIF(INFO.RENTABILIDAD!C:C,B17,INFO.RENTABILIDAD!L:L) -> 15505000 | J17: - | L17: ='BALANCE PPTO'!D9 -> 0.66666667 | M17: ='BALANCE PPTO'!E9 -> 0.58980192
B18: 46068 | C18: 0 | D18: 0 | E18: =SUMIF(INFO.PROYECCIÓN!$C:$C,B18,INFO.PROYECCIÓN!$L:$L) -> 0 | F18: =SUMIFS(INFO.RENTABILIDAD!$L$1:$L$15000,INFO.RENTABILIDAD!$C$1:$C$15000,B18,INFO.RENTABILIDAD!$W$1:$W$15000,"SI") -> 2130000 | G18: =SUMIFS(INFO.RENTABILIDAD!$L$1:$L$999,INFO.RENTABILIDAD!$C$1:$C$999,B18,INFO.RENTABILIDAD!$W$1:$W$999,"NO") -> 0 | H18: =SUMIFS(INFO.RENTABILIDAD!$L$1:$L$999,INFO.RENTABILIDAD!$C$1:$C$999,B18,INFO.RENTABILIDAD!$W$1:$W$999,"SIN PAGO") -> 0 | I18: =SUMIF(INFO.RENTABILIDAD!C:C,B18,INFO.RENTABILIDAD!L:L) -> 2130000 | J18: - | L18: ='BALANCE PPTO'!D10 -> % DIFERENCIA | M18: ='BALANCE PPTO'!E10 -> NOS FALTA VENDER
B19: 46069 | C19: 0 | D19: 0 | E19: =SUMIF(INFO.PROYECCIÓN!$C:$C,B19,INFO.PROYECCIÓN!$L:$L) -> 0 | F19: =SUMIFS(INFO.RENTABILIDAD!$L$1:$L$15000,INFO.RENTABILIDAD!$C$1:$C$15000,B19,INFO.RENTABILIDAD!$W$1:$W$15000,"SI") -> 26208000 | G19: =SUMIFS(INFO.RENTABILIDAD!$L$1:$L$999,INFO.RENTABILIDAD!$C$1:$C$999,B19,INFO.RENTABILIDAD!$W$1:$W$999,"NO") -> 0 | H19: =SUMIFS(INFO.RENTABILIDAD!$L$1:$L$999,INFO.RENTABILIDAD!$C$1:$C$999,B19,INFO.RENTABILIDAD!$W$1:$W$999,"SIN PAGO") -> 0 | I19: =SUMIF(INFO.RENTABILIDAD!C:C,B19,INFO.RENTABILIDAD!L:L) -> 26208000 | J19: - | L19: ='BALANCE PPTO'!D11 -> -0.076864744 | M19: ='BALANCE PPTO'!E11 -> 0.41019808
B20: 46070 | C20: 0 | D20: 0 | E20: =SUMIF(INFO.PROYECCIÓN!$C:$C,B20,INFO.PROYECCIÓN!$L:$L) -> 0 | F20: =SUMIFS(INFO.RENTABILIDAD!$L$1:$L$15000,INFO.RENTABILIDAD!$C$1:$C$15000,B20,INFO.RENTABILIDAD!$W$1:$W$15000,"SI") -> 24768500 | G20: =SUMIFS(INFO.RENTABILIDAD!$L$1:$L$999,INFO.RENTABILIDAD!$C$1:$C$999,B20,INFO.RENTABILIDAD!$W$1:$W$999,"NO") -> 0 | H20: =SUMIFS(INFO.RENTABILIDAD!$L$1:$L$999,INFO.RENTABILIDAD!$C$1:$C$999,B20,INFO.RENTABILIDAD!$W$1:$W$999,"SIN PAGO") -> 0 | I20: =SUMIF(INFO.RENTABILIDAD!C:C,B20,INFO.RENTABILIDAD!L:L) -> 24768500 | J20: - | L20: ='BALANCE PPTO'!D12 -> 0 | M20: ='BALANCE PPTO'!E12 -> 0
B21: 46071 | C21: 0 | D21: 0 | E21: =SUMIF(INFO.PROYECCIÓN!$C:$C,B21,INFO.PROYECCIÓN!$L:$L) -> 0 | F21: =SUMIFS(INFO.RENTABILIDAD!$L$1:$L$15000,INFO.RENTABILIDAD!$C$1:$C$15000,B21,INFO.RENTABILIDAD!$W$1:$W$15000,"SI") -> 26372000 | G21: =SUMIFS(INFO.RENTABILIDAD!$L$1:$L$999,INFO.RENTABILIDAD!$C$1:$C$999,B21,INFO.RENTABILIDAD!$W$1:$W$999,"NO") -> 0 | H21: =SUMIFS(INFO.RENTABILIDAD!$L$1:$L$999,INFO.RENTABILIDAD!$C$1:$C$999,B21,INFO.RENTABILIDAD!$W$1:$W$999,"SIN PAGO") -> 0 | I21: =SUMIF(INFO.RENTABILIDAD!C:C,B21,INFO.RENTABILIDAD!L:L) -> 26372000 | J21: - | L21: ='BALANCE PPTO'!#REF! -> #REF! | M21: ='BALANCE PPTO'!#REF! -> #REF!
B22: 46072 | C22: 0 | D22: 0 | E22: =SUMIF(INFO.PROYECCIÓN!$C:$C,B22,INFO.PROYECCIÓN!$L:$L) -> 0 | F22: =SUMIFS(INFO.RENTABILIDAD!$L$1:$L$15000,INFO.RENTABILIDAD!$C$1:$C$15000,B22,INFO.RENTABILIDAD!$W$1:$W$15000,"SI") -> 17660000 | G22: =SUMIFS(INFO.RENTABILIDAD!$L$1:$L$999,INFO.RENTABILIDAD!$C$1:$C$999,B22,INFO.RENTABILIDAD!$W$1:$W$999,"NO") -> 617500 | H22: =SUMIFS(INFO.RENTABILIDAD!$L$1:$L$999,INFO.RENTABILIDAD!$C$1:$C$999,B22,INFO.RENTABILIDAD!$W$1:$W$999,"SIN PAGO") -> 0 | I22: =SUMIF(INFO.RENTABILIDAD!C:C,B22,INFO.RENTABILIDAD!L:L) -> 18277500 | J22: -
B23: 46073 | C23: 0 | D23: 0 | E23: =SUMIF(INFO.PROYECCIÓN!$C:$C,B23,INFO.PROYECCIÓN!$L:$L) -> 14678500 | F23: =SUMIFS(INFO.RENTABILIDAD!$L$1:$L$15000,INFO.RENTABILIDAD!$C$1:$C$15000,B23,INFO.RENTABILIDAD!$W$1:$W$15000,"SI") -> 0 | G23: =SUMIFS(INFO.RENTABILIDAD!$L$1:$L$999,INFO.RENTABILIDAD!$C$1:$C$999,B23,INFO.RENTABILIDAD!$W$1:$W$999,"NO") -> 0 | H23: =SUMIFS(INFO.RENTABILIDAD!$L$1:$L$999,INFO.RENTABILIDAD!$C$1:$C$999,B23,INFO.RENTABILIDAD!$W$1:$W$999,"SIN PAGO") -> 0 | I23: =SUMIF(INFO.RENTABILIDAD!C:C,B23,INFO.RENTABILIDAD!L:L) -> 0 | J23: - | L23: ='BALANCE PPTO'!D14 -> ESTRATEGIA FEBRERO
B24: 46074 | C24: 0 | D24: 0 | E24: =SUMIF(INFO.PROYECCIÓN!$C:$C,B24,INFO.PROYECCIÓN!$L:$L) -> 29430000 | F24: =SUMIFS(INFO.RENTABILIDAD!$L$1:$L$15000,INFO.RENTABILIDAD!$C$1:$C$15000,B24,INFO.RENTABILIDAD!$W$1:$W$15000,"SI") -> 0 | G24: =SUMIFS(INFO.RENTABILIDAD!$L$1:$L$999,INFO.RENTABILIDAD!$C$1:$C$999,B24,INFO.RENTABILIDAD!$W$1:$W$999,"NO") -> 0 | H24: =SUMIFS(INFO.RENTABILIDAD!$L$1:$L$999,INFO.RENTABILIDAD!$C$1:$C$999,B24,INFO.RENTABILIDAD!$W$1:$W$999,"SIN PAGO") -> 0 | I24: =SUMIF(INFO.RENTABILIDAD!C:C,B24,INFO.RENTABILIDAD!L:L) -> 0 | J24: - | L24: ='BALANCE PPTO'!D15 -> DÍAS HÁB MES | M24: ='BALANCE PPTO'!E15 -> 24
B25: 46075 | C25: 0 | D25: 0 | E25: =SUMIF(INFO.PROYECCIÓN!$C:$C,B25,INFO.PROYECCIÓN!$L:$L) -> 840000 | F25: =SUMIFS(INFO.RENTABILIDAD!$L$1:$L$15000,INFO.RENTABILIDAD!$C$1:$C$15000,B25,INFO.RENTABILIDAD!$W$1:$W$15000,"SI") -> 0 | G25: =SUMIFS(INFO.RENTABILIDAD!$L$1:$L$999,INFO.RENTABILIDAD!$C$1:$C$999,B25,INFO.RENTABILIDAD!$W$1:$W$999,"NO") -> 0 | H25: =SUMIFS(INFO.RENTABILIDAD!$L$1:$L$999,INFO.RENTABILIDAD!$C$1:$C$999,B25,INFO.RENTABILIDAD!$W$1:$W$999,"SIN PAGO") -> 0 | I25: =SUMIF(INFO.RENTABILIDAD!C:C,B25,INFO.RENTABILIDAD!L:L) -> 0 | J25: - | L25: ='BALANCE PPTO'!D16 -> DÍAS EJECT | M25: =P3 -> 16
B26: 46076 | C26: 0 | D26: 0 | E26: =SUMIF(INFO.PROYECCIÓN!$C:$C,B26,INFO.PROYECCIÓN!$L:$L) -> 15932000 | F26: =SUMIFS(INFO.RENTABILIDAD!$L$1:$L$15000,INFO.RENTABILIDAD!$C$1:$C$15000,B26,INFO.RENTABILIDAD!$W$1:$W$15000,"SI") -> 0 | G26: =SUMIFS(INFO.RENTABILIDAD!$L$1:$L$999,INFO.RENTABILIDAD!$C$1:$C$999,B26,INFO.RENTABILIDAD!$W$1:$W$999,"NO") -> 0 | H26: =SUMIFS(INFO.RENTABILIDAD!$L$1:$L$999,INFO.RENTABILIDAD!$C$1:$C$999,B26,INFO.RENTABILIDAD!$W$1:$W$999,"SIN PAGO") -> 0 | I26: =SUMIF(INFO.RENTABILIDAD!C:C,B26,INFO.RENTABILIDAD!L:L) -> 0 | J26: - | L26: ='BALANCE PPTO'!D17 -> FECHA | M26: ='BALANCE PPTO'!E17 -> 46072
B27: 46077 | C27: 0 | D27: 0 | E27: =SUMIF(INFO.PROYECCIÓN!$C:$C,B27,INFO.PROYECCIÓN!$L:$L) -> 6766000 | F27: =SUMIFS(INFO.RENTABILIDAD!$L$1:$L$15000,INFO.RENTABILIDAD!$C$1:$C$15000,B27,INFO.RENTABILIDAD!$W$1:$W$15000,"SI") -> 0 | G27: =SUMIFS(INFO.RENTABILIDAD!$L$1:$L$999,INFO.RENTABILIDAD!$C$1:$C$999,B27,INFO.RENTABILIDAD!$W$1:$W$999,"NO") -> 0 | H27: =SUMIFS(INFO.RENTABILIDAD!$L$1:$L$999,INFO.RENTABILIDAD!$C$1:$C$999,B27,INFO.RENTABILIDAD!$W$1:$W$999,"SIN PAGO") -> 0 | I27: =SUMIF(INFO.RENTABILIDAD!C:C,B27,INFO.RENTABILIDAD!L:L) -> 0 | J27: - | L27: ='BALANCE PPTO'!D18 -> META ENERO | M27: ='BALANCE PPTO'!E18 -> 520000000
B28: 46078 | C28: 0 | D28: 0 | E28: =SUMIF(INFO.PROYECCIÓN!$C:$C,B28,INFO.PROYECCIÓN!$L:$L) -> 9876000 | F28: =SUMIFS(INFO.RENTABILIDAD!$L$1:$L$15000,INFO.RENTABILIDAD!$C$1:$C$15000,B28,INFO.RENTABILIDAD!$W$1:$W$15000,"SI") -> 0 | G28: =SUMIFS(INFO.RENTABILIDAD!$L$1:$L$999,INFO.RENTABILIDAD!$C$1:$C$999,B28,INFO.RENTABILIDAD!$W$1:$W$999,"NO") -> 0 | H28: =SUMIFS(INFO.RENTABILIDAD!$L$1:$L$999,INFO.RENTABILIDAD!$C$1:$C$999,B28,INFO.RENTABILIDAD!$W$1:$W$999,"SIN PAGO") -> 0 | I28: =SUMIF(INFO.RENTABILIDAD!C:C,B28,INFO.RENTABILIDAD!L:L) -> 0 | J28: - | L28: ='BALANCE PPTO'!D19 -> VENTA ESPERADA FEB | M28: ='BALANCE PPTO'!E19 -> 3.4666667e+08
B29: 46079 | C29: 0 | D29: 0 | E29: =SUMIF(INFO.PROYECCIÓN!$C:$C,B29,INFO.PROYECCIÓN!$L:$L) -> 8390000 | F29: =SUMIFS(INFO.RENTABILIDAD!$L$1:$L$15000,INFO.RENTABILIDAD!$C$1:$C$15000,B29,INFO.RENTABILIDAD!$W$1:$W$15000,"SI") -> 0 | G29: =SUMIFS(INFO.RENTABILIDAD!$L$1:$L$999,INFO.RENTABILIDAD!$C$1:$C$999,B29,INFO.RENTABILIDAD!$W$1:$W$999,"NO") -> 0 | H29: =SUMIFS(INFO.RENTABILIDAD!$L$1:$L$999,INFO.RENTABILIDAD!$C$1:$C$999,B29,INFO.RENTABILIDAD!$W$1:$W$999,"SIN PAGO") -> 0 | I29: =SUMIF(INFO.RENTABILIDAD!C:C,B29,INFO.RENTABILIDAD!L:L) -> 0 | J29: - | L29: ='BALANCE PPTO'!D20 -> FACTURADO FEB | M29: ='BALANCE PPTO'!E20 -> 306697000
B30: 46080 | C30: 0 | D30: 0 | E30: =SUMIF(INFO.PROYECCIÓN!$C:$C,B30,INFO.PROYECCIÓN!$L:$L) -> 15430000 | F30: =SUMIFS(INFO.RENTABILIDAD!$L$1:$L$15000,INFO.RENTABILIDAD!$C$1:$C$15000,B30,INFO.RENTABILIDAD!$W$1:$W$15000,"SI") -> 0 | G30: =SUMIFS(INFO.RENTABILIDAD!$L$1:$L$999,INFO.RENTABILIDAD!$C$1:$C$999,B30,INFO.RENTABILIDAD!$W$1:$W$999,"NO") -> 0 | H30: =SUMIFS(INFO.RENTABILIDAD!$L$1:$L$999,INFO.RENTABILIDAD!$C$1:$C$999,B30,INFO.RENTABILIDAD!$W$1:$W$999,"SIN PAGO") -> 0 | I30: =SUMIF(INFO.RENTABILIDAD!C:C,B30,INFO.RENTABILIDAD!L:L) -> 0 | J30: - | L30: ='BALANCE PPTO'!D21 -> PROYECCIÓN FEB | M30: ='BALANCE PPTO'!E21 -> 105032500
B31: 46081 | C31: 0 | D31: 0 | E31: =SUMIF(INFO.PROYECCIÓN!$C:$C,B31,INFO.PROYECCIÓN!$L:$L) -> 3690000 | F31: =SUMIFS(INFO.RENTABILIDAD!$L$1:$L$15000,INFO.RENTABILIDAD!$C$1:$C$15000,B31,INFO.RENTABILIDAD!$W$1:$W$15000,"SI") -> 0 | G31: =SUMIFS(INFO.RENTABILIDAD!$L$1:$L$999,INFO.RENTABILIDAD!$C$1:$C$999,B31,INFO.RENTABILIDAD!$W$1:$W$999,"NO") -> 0 | H31: =SUMIFS(INFO.RENTABILIDAD!$L$1:$L$999,INFO.RENTABILIDAD!$C$1:$C$999,B31,INFO.RENTABILIDAD!$W$1:$W$999,"SIN PAGO") -> 0 | I31: =SUMIF(INFO.RENTABILIDAD!C:C,B31,INFO.RENTABILIDAD!L:L) -> 0 | J31: - | L31: ='BALANCE PPTO'!D22 -> FALTA X CUMPLIR | M31: ='BALANCE PPTO'!E22 -> 108270500
B32: 0 | C32: 0 | D32: 0 | E32: =SUMIF(INFO.PROYECCIÓN!$C:$C,B32,INFO.PROYECCIÓN!$L:$L) -> 0 | F32: =SUMIFS(INFO.RENTABILIDAD!$L$1:$L$15000,INFO.RENTABILIDAD!$C$1:$C$15000,B32,INFO.RENTABILIDAD!$W$1:$W$15000,"SI") -> 0 | G32: =SUMIFS(INFO.RENTABILIDAD!$L$1:$L$999,INFO.RENTABILIDAD!$C$1:$C$999,B32,INFO.RENTABILIDAD!$W$1:$W$999,"NO") -> 0 | H32: =SUMIFS(INFO.RENTABILIDAD!$L$1:$L$999,INFO.RENTABILIDAD!$C$1:$C$999,B32,INFO.RENTABILIDAD!$W$1:$W$999,"SIN PAGO") -> 0 | I32: =SUMIF(INFO.RENTABILIDAD!C:C,B32,INFO.RENTABILIDAD!L:L) -> 0 | J32: - | L32: ='BALANCE PPTO'!D23 -> RESULTADO ESP | M32: ='BALANCE PPTO'!E23 -> 411729500
B33: 0 | C33: 0 | D33: 0 | E33: =SUMIF(INFO.PROYECCIÓN!$C:$C,B33,INFO.PROYECCIÓN!$L:$L) -> 0 | F33: =SUMIFS(INFO.RENTABILIDAD!$L$1:$L$15000,INFO.RENTABILIDAD!$C$1:$C$15000,B33,INFO.RENTABILIDAD!$W$1:$W$15000,"SI") -> 0 | G33: =SUMIFS(INFO.RENTABILIDAD!$L$1:$L$999,INFO.RENTABILIDAD!$C$1:$C$999,B33,INFO.RENTABILIDAD!$W$1:$W$999,"NO") -> 0 | H33: =SUMIFS(INFO.RENTABILIDAD!$L$1:$L$999,INFO.RENTABILIDAD!$C$1:$C$999,B33,INFO.RENTABILIDAD!$W$1:$W$999,"SIN PAGO") -> 0 | I33: =SUMIF(INFO.RENTABILIDAD!C:C,B33,INFO.RENTABILIDAD!L:L) -> 0 | J33: - | L33: ='BALANCE PPTO'!D24 -> % RESULTADO ESP | M33: ='BALANCE PPTO'!E24 -> 0.7917875
B34: 0 | C34: 0 | D34: 0 | E34: =SUMIF(INFO.PROYECCIÓN!$C:$C,B34,INFO.PROYECCIÓN!$L:$L) -> 0 | F34: =SUMIFS(INFO.RENTABILIDAD!$L$1:$L$15000,INFO.RENTABILIDAD!$C$1:$C$15000,B34,INFO.RENTABILIDAD!$W$1:$W$15000,"SI") -> 0 | G34: =SUMIFS(INFO.RENTABILIDAD!$L$1:$L$999,INFO.RENTABILIDAD!$C$1:$C$999,B34,INFO.RENTABILIDAD!$W$1:$W$999,"NO") -> 0 | H34: =SUMIFS(INFO.RENTABILIDAD!$L$1:$L$999,INFO.RENTABILIDAD!$C$1:$C$999,B34,INFO.RENTABILIDAD!$W$1:$W$999,"SIN PAGO") -> 0 | I34: =SUMIF(INFO.RENTABILIDAD!C:C,B34,INFO.RENTABILIDAD!L:L) -> 0 | J34: - | L34: META DIARIA | M34: =M27/M24 -> 21666667
C35: =SUM(C4:C34) -> 0 | D35: =SUM(D4:D34) -> 0 | E35: =SUM(E4:E34) -> 105032500 | F35: =SUM(F4:F34) -> 306697000 | G35: =SUM(G4:G34) -> 6687000 | H35: =SUM(H4:H34) -> 0 | I35: =SUM(I4:I34) -> 313384000 | J35: -

Sheet REPORTE X DÍAS
B2: % CUMPLIMIENTO POR DÍA DE SERVICIOS FACTURADOS Y REALIZADOS JUNIO 2025 | J2: TABLERO VENTA DIARIA/MENSUAL | M2: TABLERO RESULTADO DÍA
B3: FECHA | C3: META DÍA/HÁBIL | D3: PROYECCIÓN | E3: PENDIENTE | F3: FACTURADO | G3: ANTICIPOS | H3: % | J3: ='TABLERO Y AGENDA'!N3 -> 46072 | M3: =J3 -> 46072
B4: ='TABLERO Y AGENDA'!B4 -> 46054 | C4: 14853333 | D4: ='TABLERO Y AGENDA'!E4 -> 0 | E4: =-(C4-D4) -> -14853333 | F4: ='TABLERO Y AGENDA'!F4 -> 133000 | G4: ='TABLERO Y AGENDA'!G4 -> 0 | H4: 0 | J4: Proyectado Día | K4: ='TABLERO Y AGENDA'!M3 -> 3190000 | M4: Proyectado Día | N4: =K4 -> 3190000
B5: ='TABLERO Y AGENDA'!B5 -> 46055 | C5: 14853333 | D5: ='TABLERO Y AGENDA'!E5 -> 0 | E5: =-(C5-D5) -> -14853333 | F5: ='TABLERO Y AGENDA'!F5 -> 23167000 | G5: ='TABLERO Y AGENDA'!G5 -> 200000 | H5: =(F5/C5) -> 1.5597173 | J5: Objetivo Venta Día | K5: ='TABLERO Y AGENDA'!L3 -> 19347826 | M5: =J5 -> Objetivo Venta Día | N5: =K5 -> 19347826
B6: ='TABLERO Y AGENDA'!B6 -> 46056 | C6: 14853333 | D6: ='TABLERO Y AGENDA'!E6 -> 0 | E6: =-(C6-D6) -> -14853333 | F6: ='TABLERO Y AGENDA'!F6 -> 14266000 | G6: ='TABLERO Y AGENDA'!G6 -> 1350000 | H6: =(F6/C6) -> 0.96045783 | J6: Estado Agendamiento Día | K6: =-K5+K4 -> -16157826 | M6: Cierre Facturado Día | N6: ='TABLERO Y AGENDA'!O3 -> 24284000
B7: ='TABLERO Y AGENDA'!B7 -> 46057 | C7: 14853333 | D7: ='TABLERO Y AGENDA'!E7 -> 0 | E7: =-(C7-D7) -> -14853333 | F7: ='TABLERO Y AGENDA'!F7 -> 6521000 | G7: ='TABLERO Y AGENDA'!G7 -> 381000 | H7: =(F7/C7) -> 0.43902604 | J7: Estado Meta al día | K7: =N8 -> -0.076864744 | M7: % Cumplimiento Día | N7: =N6/N5 -> 1.2551281
B8: ='TABLERO Y AGENDA'!B8 -> 46058 | C8: 14853333 | D8: ='TABLERO Y AGENDA'!E8 -> 0 | E8: =-(C8-D8) -> -14853333 | F8: ='TABLERO Y AGENDA'!F8 -> 13902000 | G8: ='TABLERO Y AGENDA'!G8 -> 1502500 | H8: =(F8/C8) -> 0.93595155 | M8: Cumpliento Meta | N8: ='BALANCE PPTO'!E32 -> -0.076864744
B9: ='TABLERO Y AGENDA'!B9 -> 46059 | C9: 14853333 | D9: ='TABLERO Y AGENDA'!E9 -> 0 | E9: =-(C9-D9) -> -14853333 | F9: ='TABLERO Y AGENDA'!F9 -> 24645000 | G9: ='TABLERO Y AGENDA'!G9 -> 123500 | H9: =(F9/C9) -> 1.6592236
B10: ='TABLERO Y AGENDA'!B10 -> 46060 | C10: 14853333 | D10: ='TABLERO Y AGENDA'!E10 -> 0 | E10: =-(C10-D10) -> -14853333 | F10: ='TABLERO Y AGENDA'!F10 -> 11220000 | G10: ='TABLERO Y AGENDA'!G10 -> 940000 | H10: =(F10/C10) -> 0.75538601
B11: ='TABLERO Y AGENDA'!B11 -> 46061 | C11: 14853333 | D11: ='TABLERO Y AGENDA'!E11 -> 0 | E11: =-(C11-D11) -> -14853333 | F11: ='TABLERO Y AGENDA'!F11 -> 610000 | G11: ='TABLERO Y AGENDA'!G11 -> 0 | H11: =(F11/C11) -> 0.041068224
B12: ='TABLERO Y AGENDA'!B12 -> 46062 | C12: 14853333 | D12: ='TABLERO Y AGENDA'!E12 -> 0 | E12: =-(C12-D12) -> -14853333 | F12: ='TABLERO Y AGENDA'!F12 -> 18849500 | G12: ='TABLERO Y AGENDA'!G12 -> 0 | H12: =(F12/C12) -> 1.2690418 | J12: Día Hábil
B13: ='TABLERO Y AGENDA'!B13 -> 46063 | C13: 14853333 | D13: ='TABLERO Y AGENDA'!E13 -> 0 | E13: =-(C13-D13) -> -14853333 | F13: ='TABLERO Y AGENDA'!F13 -> 26790000 | G13: ='TABLERO Y AGENDA'!G13 -> 332500 | H13: =(F13/C13) -> 1.8036356 | J13: NO INCLUIR EN EL INFORME POR FA !
B14: ='TABLERO Y AGENDA'!B14 -> 46064 | C14: 14853333 | D14: ='TABLERO Y AGENDA'!E14 -> 0 | E14: =-(C14-D14) -> -14853333 | F14: ='TABLERO Y AGENDA'!F14 -> 14830000 | G14: ='TABLERO Y AGENDA'!G14 -> 0 | H14: =(F14/C14) -> 0.99842911 | J14: Objetivo Facuración | K14: ='BALANCE PPTO'!E18 -> 520000000
B15: ='TABLERO Y AGENDA'!B15 -> 46065 | C15: 14853333 | D15: ='TABLERO Y AGENDA'!E15 -> 0 | E15: =-(C15-D15) -> -14853333 | F15: ='TABLERO Y AGENDA'!F15 -> 15850000 | G15: ='TABLERO Y AGENDA'!G15 -> 0 | H15: =(F15/C15) -> 1.0671006 | J15: Objetivo al día | K15: 0
B16: ='TABLERO Y AGENDA'!B16 -> 46066 | C16: 14853333 | D16: ='TABLERO Y AGENDA'!E16 -> 0 | E16: =-(C16-D16) -> -14853333 | F16: ='TABLERO Y AGENDA'!F16 -> 24510000 | G16: ='TABLERO Y AGENDA'!G16 -> 0 | H16: =(F16/C16) -> 1.6501347 | J16: Facturación Real | K16: =SUM('REPORTE X DÍAS'!F4:F34) -> 306697000
B17: ='TABLERO Y AGENDA'!B17 -> 46067 | C17: 14853333 | D17: ='TABLERO Y AGENDA'!E17 -> 0 | E17: =-(C17-D17) -> -14853333 | F17: ='TABLERO Y AGENDA'!F17 -> 14265000 | G17: ='TABLERO Y AGENDA'!G17 -> 1240000 | H17: =(F17/C17) -> 0.96039051 | J17: Proyección Mes | K17: ='TABLERO Y AGENDA'!E35 -> 105032500
B18: ='TABLERO Y AGENDA'!B18 -> 46068 | C18: 14853333 | D18: ='TABLERO Y AGENDA'!E18 -> 0 | E18: =-(C18-D18) -> -14853333 | F18: ='TABLERO Y AGENDA'!F18 -> 2130000 | G18: ='TABLERO Y AGENDA'!G18 -> 0 | H18: =(F18/C18) -> 0.14340216 | J18: Cartera Mes | K18: ='TABLERO Y AGENDA'!H35 -> 0
B19: ='TABLERO Y AGENDA'!B19 -> 46069 | C19: 14853333 | D19: ='TABLERO Y AGENDA'!E19 -> 0 | E19: =-(C19-D19) -> -14853333 | F19: ='TABLERO Y AGENDA'!F19 -> 26208000 | G19: ='TABLERO Y AGENDA'!G19 -> 0 | H19: =(F19/C19) -> 1.7644525 | J19: Anticipos Sep | K19: ='TABLERO Y AGENDA'!G35 -> 6687000
B20: ='TABLERO Y AGENDA'!B20 -> 46070 | C20: 14853333 | D20: ='TABLERO Y AGENDA'!E20 -> 0 | E20: =-(C20-D20) -> -14853333 | F20: ='TABLERO Y AGENDA'!F20 -> 24768500 | G20: ='TABLERO Y AGENDA'!G20 -> 0 | H20: =(F20/C20) -> 1.6675382 | J20: Gestión Pendiente | K20: =K14-K16-K17 -> 108270500
B21: ='TABLERO Y AGENDA'!B21 -> 46071 | C21: 14853333 | D21: ='TABLERO Y AGENDA'!E21 -> 0 | E21: =-(C21-D21) -> -14853333 | F21: ='TABLERO Y AGENDA'!F21 -> 26372000 | G21: ='TABLERO Y AGENDA'!G21 -> 0 | H21: =(F21/C21) -> 1.7754938 | J21: Día Hábil | K21: ='TABLERO Y AGENDA'!P3 -> 16
B22: ='TABLERO Y AGENDA'!B22 -> 46072 | C22: 14853333 | D22: ='TABLERO Y AGENDA'!E22 -> 0 | E22: =-(C22-D22) -> -14853333 | F22: ='TABLERO Y AGENDA'!F22 -> 17660000 | G22: ='TABLERO Y AGENDA'!G22 -> 617500 | H22: =(F22/C22) -> 1.1889587 | J22: Resultado Esperado | K22: =(K16+K17)/K14 -> 0.7917875
B23: ='TABLERO Y AGENDA'!B23 -> 46073 | C23: 14853333 | D23: ='TABLERO Y AGENDA'!E23 -> 14678500 | E23: =-(C23-D23) -> -174833 | F23: ='TABLERO Y AGENDA'!F23 -> 0 | G23: ='TABLERO Y AGENDA'!G23 -> 0 | H23: =(F23/C23) -> 0 | J23: % Al Día | K23: ='BALANCE PPTO'!E30 -> 0.66666667
B24: ='TABLERO Y AGENDA'!B24 -> 46074 | C24: 14853333 | D24: ='TABLERO Y AGENDA'!E24 -> 29430000 | E24: =-(C24-D24) -> 14576667 | F24: ='TABLERO Y AGENDA'!F24 -> 0 | G24: ='TABLERO Y AGENDA'!G24 -> 0 | H24: =(F24/C24) -> 0 | J24: % Real | K24: ='BALANCE PPTO'!E31 -> 0.58980192
B25: ='TABLERO Y AGENDA'!B25 -> 46075 | C25: 14853333 | D25: ='TABLERO Y AGENDA'!E25 -> 840000 | E25: =-(C25-D25) -> -14013333 | F25: ='TABLERO Y AGENDA'!F25 -> 0 | G25: ='TABLERO Y AGENDA'!G25 -> 0 | H25: =(F25/C25) -> 0 | J25: Objetivo Hábil | K25: ='BALANCE PPTO'!E33 -> 21666667
B26: ='TABLERO Y AGENDA'!B26 -> 46076 | C26: 14853333 | D26: ='TABLERO Y AGENDA'!E26 -> 15932000 | E26: =-(C26-D26) -> 1078667 | F26: ='TABLERO Y AGENDA'!F26 -> 0 | G26: ='TABLERO Y AGENDA'!G26 -> 0 | H26: =(F26/C26) -> 0 | J26: Objetivo Domingos | K26: 1000000
B27: ='TABLERO Y AGENDA'!B27 -> 46077 | C27: 14853333 | D27: ='TABLERO Y AGENDA'!E27 -> 6766000 | E27: =-(C27-D27) -> -8087333 | F27: ='TABLERO Y AGENDA'!F27 -> 0 | G27: ='TABLERO Y AGENDA'!G27 -> 0 | H27: =(F27/C27) -> 0
B28: ='TABLERO Y AGENDA'!B28 -> 46078 | C28: 14853333 | D28: ='TABLERO Y AGENDA'!E28 -> 9876000 | E28: =-(C28-D28) -> -4977333 | F28: ='TABLERO Y AGENDA'!F28 -> 0 | G28: ='TABLERO Y AGENDA'!G28 -> 0 | H28: =(F28/C28) -> 0
B29: ='TABLERO Y AGENDA'!B29 -> 46079 | C29: 14853333 | D29: ='TABLERO Y AGENDA'!E29 -> 8390000 | E29: =-(C29-D29) -> -6463333 | F29: ='TABLERO Y AGENDA'!F29 -> 0 | G29: ='TABLERO Y AGENDA'!G29 -> 0 | H29: =(F29/C29) -> 0
B30: ='TABLERO Y AGENDA'!B30 -> 46080 | C30: 14853333 | D30: ='TABLERO Y AGENDA'!E30 -> 15430000 | E30: =-(C30-D30) -> 576667 | F30: ='TABLERO Y AGENDA'!F30 -> 0 | G30: ='TABLERO Y AGENDA'!G30 -> 0 | H30: =(F30/C30) -> 0
B31: ='TABLERO Y AGENDA'!B31 -> 46081 | C31: 14853333 | D31: ='TABLERO Y AGENDA'!E31 -> 3690000 | E31: =-(C31-D31) -> -11163333 | F31: ='TABLERO Y AGENDA'!F31 -> 0 | G31: ='TABLERO Y AGENDA'!G31 -> 0 | H31: =(F31/C31) -> 0
B32: ='TABLERO Y AGENDA'!B32 -> 0 | C32: 14853333 | D32: ='TABLERO Y AGENDA'!E32 -> 0 | E32: =-(C32-D32) -> -14853333 | F32: ='TABLERO Y AGENDA'!F32 -> 0 | G32: ='TABLERO Y AGENDA'!G32 -> 0 | H32: =(F32/C32) -> 0
B33: ='TABLERO Y AGENDA'!B33 -> 0 | C33: 14853333 | D33: ='TABLERO Y AGENDA'!E33 -> 0 | E33: =-(C33-D33) -> -14853333 | F33: ='TABLERO Y AGENDA'!F33 -> 0 | G33: ='TABLERO Y AGENDA'!G33 -> 0 | H33: =(F33/C33) -> 0
B34: ='TABLERO Y AGENDA'!B34 -> 0 | C34: 14853333 | D34: ='TABLERO Y AGENDA'!E34 -> 0 | E34: =-(C34-D34) -> -14853333 | F34: ='TABLERO Y AGENDA'!F34 -> 0 | G34: ='TABLERO Y AGENDA'!G34 -> 0 | H34: =(F34/C34) -> 0
